Workbook

Sheet Summary
A1: California ADU direct-mail targeting: top 100 ZIPs
A2: INTERIM RANKING: no county parcel data could be downloaded in this run (assessor hosts unreachable). Rank = Redfin SFR homes sold (12 mo) x tier weight, a market-size proxy, NOT a count of qualifying lots. Parcel columns read 'no data'.
A3: ZIP-level results are estimates of the share of qualifying lots, not a verified list of homes. Redfin data: 2026-05-31, 2026-02-28, 2025-11-30, 2025-08-31 windows (file updated 2026-06-02 14:33:24.470 Z).
A5: Tier | B5: Mailable ZIPs (live count) | C5: Cumulative ZIPs | D5: SFR homes sold 12 mo in tier | E5: PO-box / unique ZIPs in tier (excluded)
A6: Tier 1 (>= $700/sf) | B6: =COUNTIFS('All ZIPs'!$N$2:$N$1878,1,'All ZIPs'!$M$2:$M$1878,TRUE()) -> 389 | C6: =SUM($B$6:B6) -> 389 | D6: =SUMIFS('All ZIPs'!$K$2:$K$1878,'All ZIPs'!$N$2:$N$1878,1,'All ZIPs'!$M$2:$M$1878,TRUE()) -> 48758 | E6: =COUNTIFS('All ZIPs'!$N$2:$N$1878,1,'All ZIPs'!$M$2:$M$1878,FALSE()) -> 38
A7: Tier 2 ($600-699/sf) | B7: =COUNTIFS('All ZIPs'!$N$2:$N$1878,2,'All ZIPs'!$M$2:$M$1878,TRUE()) -> 169 | C7: =SUM($B$6:B7) -> 558 | D7: =SUMIFS('All ZIPs'!$K$2:$K$1878,'All ZIPs'!$N$2:$N$1878,2,'All ZIPs'!$M$2:$M$1878,TRUE()) -> 22518 | E7: =COUNTIFS('All ZIPs'!$N$2:$N$1878,2,'All ZIPs'!$M$2:$M$1878,FALSE()) -> 17
A8: Tier 3 ($500-599/sf) | B8: =COUNTIFS('All ZIPs'!$N$2:$N$1878,3,'All ZIPs'!$M$2:$M$1878,TRUE()) -> 178 | C8: =SUM($B$6:B8) -> 736 | D8: =SUMIFS('All ZIPs'!$K$2:$K$1878,'All ZIPs'!$N$2:$N$1878,3,'All ZIPs'!$M$2:$M$1878,TRUE()) -> 24198 | E8: =COUNTIFS('All ZIPs'!$N$2:$N$1878,3,'All ZIPs'!$M$2:$M$1878,FALSE()) -> 17
A9: Total (any tier) | B9: =SUM(B6:B8) -> 736 | D9: =SUM(D6:D8) -> 95474 | E9: =SUM(E6:E8) -> 72
A10: Snapshot sorted by the script at config.py defaults.
A11: Rank | B11: ZIP | C11: City | D11: County | E11: Focus region | F11: Neighborhoods | G11: Tier | H11: Median $/sq ft (12 mo) | I11: Median sale price (12 mo) | J11: SFR homes sold (12 mo) | K11: Est. buildable >= 750 (parcels) | L11: Score | M11: Rank basis
A12: 1 | B12: 92677 | C12: Laguna Niguel | D12: Orange | E12: Orange County | F12: El Niguel Heights; Niguel Summit | G12: Tier 1 (>= $700/sf) | H12: 811.06558 | I12: 1723455.2 | J12: 424 | K12: no data | L12: 1272 | M12: INTERIM: Redfin SFR sales (12 mo) x tier weight
A13: 2 | B13: 94550 | C13: Livermore | D13: Alameda | E13: Berkeley / Oakland / Alameda County | F13: Sandhurst; The Grove; Village II; Vinsanto II; Livermorium Plaza / Mills Square Park; Lizzie Fountain Plaza | G13: Tier 1 (>= $700/sf) | H13: 704.67241 | I13: 1341359.2 | J13: 412 | K13: no data | L13: 1236 | M13: INTERIM: Redfin SFR sales (12 mo) x tier weight
A14: 3 | B14: 95125 | C14: San Jose | D14: Santa Clara | E14: Peninsula & South Bay (Santa Clara / San Mateo) | F14: Dry Creek; Willow Glen | G14: Tier 1 (>= $700/sf) | H14: 1137.9459 | I14: 2062863.5 | J14: 381 | K14: no data | L14: 1143 | M14: INTERIM: Redfin SFR sales (12 mo) x tier weight
A15: 4 | B15: 92024 | C15: Encinitas | D15: San Diego | E15: San Diego | F15: Leucadia; Olivenhain; Downtown Encinitas; Encinitas Highlands; Encinitas Ranch; Fox Point Farms; Manzanita Cove; Old Encinitas; Pacific Serena; Val Sereno; New Encinitas; Poinsettia Heights; Quail Gardens; Rancho Encinitas; Village Park | G15: Tier 1 (>= $700/sf) | H15: 964.56064 | I15: 2278542 | J15: 369 | K15: no data | L15: 1107 | M15: INTERIM: Redfin SFR sales (12 mo) x tier weight
A16: 5 | B16: 95124 | C16: San Jose | D16: Santa Clara | E16: Peninsula & South Bay (Santa Clara / San Mateo) | F16: Willow Glen Place | G16: Tier 1 (>= $700/sf) | H16: 1220.4989 | I16: 2057880.4 | J16: 368 | K16: no data | L16: 1104 | M16: INTERIM: Redfin SFR sales (12 mo) x tier weight
A17: 6 | B17: 96161 | C17: Truckee | D17: Placer | E17: Rest of California | F17: Glenshire-Devonshire; Tahoe Donner; Armstrong; Blitz Tract; Cambridge Estates; Devonshire; Donner Crest; Donner Lake Village; Donner Pines Tract; Donner Ski Haven; Donner Tract; Donner Trail; Donner Woods; Emmons Tract; Gateway Park; Glenshire; Gray's Crossing; Juniper Creek Ranch; Juniper Heights; Juniper Hill; Klondike Flat; Lakeview; Martis Peak; Martiswood Estates; Meadow Lake Park; Old Greenwood; Olympic Heights; Plavada Woodlands; Ponderosa Fairway Estates; Ponderosa Palisades; Ponderosa Ranchos; Prosser Lake Heights; Prosser Lakeview Estates; Schaffer's Mill; Sierra Bluff; Southside Highlands; The Meadows; Weeks Tract; Gateway; Lahontan; Martis Camp; Sierra Meadows; West End Donner | G17: Tier 2 ($600-699/sf) | H17: 612.99992 | I17: 1264262.7 | J17: 533 | K17: no data | L17: 1066 | M17: INTERIM: Redfin SFR sales (12 mo) x tier weight
A18: 7 | B18: 92117 | C18: San Diego | D18: San Diego | E18: San Diego | F18: Bay Ho; Clairemont; Clairemont Mesa Gateway; Diane Village; North Mount Estates; Riviera Highlands; Triumph; Westridge; Alcott Estates; Clairemont Village; East Clairemont; Eureka Lemon; North Clairemont | G18: Tier 1 (>= $700/sf) | H18: 805.70845 | I18: 1173166.2 | J18: 349 | K18: no data | L18: 1047 | M18: INTERIM: Redfin SFR sales (12 mo) x tier weight
A19: 8 | B19: 94112 | C19: San Francisco | D19: San Francisco | E19: San Francisco | F19: Ocean View; Outer Mission; St. Mary's Park; Westwood Park; Crocker-Amazon; Excelsior; Ingleside | G19: Tier 1 (>= $700/sf) | H19: 856.09109 | I19: 1247670.1 | J19: 335 | K19: no data | L19: 1005 | M19: INTERIM: Redfin SFR sales (12 mo) x tier weight
A20: 9 | B20: 92646 | C20: Huntington Beach | D20: Orange | E20: Orange County | G20: Tier 1 (>= $700/sf) | H20: 825.07272 | I20: 1512396.4 | J20: 333 | K20: no data | L20: 999 | M20: INTERIM: Redfin SFR sales (12 mo) x tier weight
A21: 10 | B21: 94010 | C21: Burlingame | D21: San Mateo | E21: Peninsula & South Bay (Santa Clara / San Mateo) | F21: Burlingame Hills; Burlingame Village; Burlingame Town Square | G21: Tier 1 (>= $700/sf) | H21: 1516.4872 | I21: 3999650.9 | J21: 328 | K21: no data | L21: 984 | M21: INTERIM: Redfin SFR sales (12 mo) x tier weight
A22: 11 | B22: 95123 | C22: San Jose | D22: Santa Clara | E22: Peninsula & South Bay (Santa Clara / San Mateo) | F22: Parkview | G22: Tier 1 (>= $700/sf) | H22: 911.12898 | I22: 1504662.6 | J22: 326 | K22: no data | L22: 978 | M22: INTERIM: Redfin SFR sales (12 mo) x tier weight
A23: 12 | B23: 94025 | C23: Menlo Park | D23: San Mateo | E23: Peninsula & South Bay (Santa Clara / San Mateo) | F23: Stanford Hills; Stanford Weekend Acres; Hacker Square | G23: Tier 1 (>= $700/sf) | H23: 1691.4166 | I23: 3314959.5 | J23: 321 | K23: no data | L23: 963 | M23: INTERIM: Redfin SFR sales (12 mo) x tier weight
A24: 13 | B24: 90066 | C24: Los Angeles | D24: Los Angeles | E24: Los Angeles County | F24: Mar Vista; Culver Garden; Westdale; Del Rey | G24: Tier 1 (>= $700/sf) | H24: 1163.8054 | I24: 2137363.5 | J24: 315 | K24: no data | L24: 945 | M24: INTERIM: Redfin SFR sales (12 mo) x tier weight
A25: 14 | B25: 94566 | C25: Pleasanton | D25: Alameda | E25: Berkeley / Oakland / Alameda County | F25: Del Prado; Irby Ranch; Ruby Hill; Shadow Cliffs | G25: Tier 1 (>= $700/sf) | H25: 817.19279 | I25: 1860016.4 | J25: 305 | K25: no data | L25: 915 | M25: INTERIM: Redfin SFR sales (12 mo) x tier weight
A26: 15 | B26: 90275 | C26: Rancho Palos Verdes | D26: Los Angeles | E26: Los Angeles County | G26: Tier 1 (>= $700/sf) | H26: 789.09299 | I26: 1885413.9 | J26: 302 | K26: no data | L26: 906 | M26: INTERIM: Redfin SFR sales (12 mo) x tier weight
A27: 16 | B27: 94568 | C27: Dublin | D27: Alameda | E27: Berkeley / Oakland / Alameda County | G27: Tier 1 (>= $700/sf) | H27: 730.13592 | I27: 1573461.3 | J27: 297 | K27: no data | L27: 891 | M27: INTERIM: Redfin SFR sales (12 mo) x tier weight
A28: 17 | B28: 94536 | C28: Fremont | D28: Alameda | E28: Berkeley / Oakland / Alameda County | F28: Centerville District; Niles District; Niles Junction; Shinn | G28: Tier 1 (>= $700/sf) | H28: 1002.4841 | I28: 1701938.8 | J28: 294 | K28: no data | L28: 882 | M28: INTERIM: Redfin SFR sales (12 mo) x tier weight
A29: 18 | B29: 90808 | C29: Long Beach | D29: Los Angeles | E29: Los Angeles County | G29: Tier 1 (>= $700/sf) | H29: 716.19567 | I29: 1068413.8 | J29: 290 | K29: no data | L29: 870 | M29: INTERIM: Redfin SFR sales (12 mo) x tier weight
A30: 19 | B30: 92037 | C30: La Jolla | D30: San Diego | E30: San Diego | F30: La Jolla; Biology Field Station; Campus Services Complex; Earl Warren College; Eleanor Roosevelt College; John Muir College; Lower Hermosa; Miurlands West; Mount La Jolla; North Campus; Pepper Canyon; Revelle College; Ridge Walk North Living and Learning Neighborhood; Ridgegate; Science Research Park; Seventh College at the Village; Sixth College; Thurgood Marshall College; University Center; Upper Hermosa; Windansea Beach; Windemere; Beach Barber Tract; Bird Rock; Executive Square; Golden Triangle; Hidden Valley; Katzin Courtyard; La Jolla Alta; La Jolla Country Club; La Jolla Farms; La Jolla Heights; La Jolla Hermosa; La Jolla Mesa; La Jolla Shores; La Jolla Village; Matthews Quadrangle; Soledad South; The Muirlands; Village of La Jolla | G30: Tier 1 (>= $700/sf) | H30: 1361.8037 | I30: 3616364.4 | J30: 284 | K30: no data | L30: 852 | M30: INTERIM: Redfin SFR sales (12 mo) x tier weight
A31: 20 | B31: 95120 | C31: San Jose | D31: Santa Clara | E31: Peninsula & South Bay (Santa Clara / San Mateo) | F31: Almaden Valley | G31: Tier 1 (>= $700/sf) | H31: 1003.0732 | I31: 2322145.4 | J31: 282 | K31: no data | L31: 846 | M31: INTERIM: Redfin SFR sales (12 mo) x tier weight
A32: 21 | B32: 92009 | C32: Carlsbad | D32: San Diego | E32: San Diego | F32: La Costa; Bressi Ranch; La Costa Greens; La Costa Oaks; La Costa Ridge; La Costa Valley; Rancho Carrillo | G32: Tier 1 (>= $700/sf) | H32: 705.44022 | I32: 1852998.2 | J32: 281 | K32: no data | L32: 843 | M32: INTERIM: Redfin SFR sales (12 mo) x tier weight
A33: 22 | B33: 94941 | C33: Mill Valley | D33: Marin | E33: Marin | F33: Almonte | G33: Tier 1 (>= $700/sf) | H33: 1083.9878 | I33: 2277544.8 | J33: 279 | K33: no data | L33: 837 | M33: INTERIM: Redfin SFR sales (12 mo) x tier weight
A34: 23 | B34: 92129 | C34: San Diego | D34: San Diego | E34: San Diego | F34: Rancho Peñasquitos; Torrey Highlands; Greystone Torrey Highlands; Penasquitos Creek; Rhodes Crossing; Rolling Hills; Sun Ridge Vista; Terramar; Torrey Glenn; Torrey Ranch; Adobe Bluffs; Canyon Hills; Heritage Bluffs; Merge 56; Park Village; Penasquitos Village; Peñasquitos Point; Rancho Peñasquitos Town Center; Ridgewood; Sunset Hills; Torrey Del Mar; Torrey Meadows; Torrey Santa Fe; Twin Trails | G34: Tier 1 (>= $700/sf) | H34: 704.04314 | I34: 1376469.3 | J34: 277 | K34: no data | L34: 831 | M34: INTERIM: Redfin SFR sales (12 mo) x tier weight
A35: 24 | B35: 90815 | C35: Long Beach | D35: Los Angeles | E35: Los Angeles County | F35: Los Altos | G35: Tier 1 (>= $700/sf) | H35: 736.42722 | I35: 1136425.5 | J35: 275 | K35: no data | L35: 825 | M35: INTERIM: Redfin SFR sales (12 mo) x tier weight
A36: 25 | B36: 90049 | C36: Los Angeles | D36: Los Angeles | E36: Los Angeles County | F36: Brentwood; Brentwood Glen; Brentwood Heights; Brentwood Park; Brentwood Village; Westgate Heights; Republic of Artsakh Square | G36: Tier 1 (>= $700/sf) | H36: 1323.402 | I36: 4033362.6 | J36: 273 | K36: no data | L36: 819 | M36: INTERIM: Redfin SFR sales (12 mo) x tier weight
A37: 26 | B37: 94549 | C37: Lafayette | D37: Contra Costa | E37: Rest of California | F37: Burton Valley; Reliez Valley | G37: Tier 1 (>= $700/sf) | H37: 827.75787 | I37: 2055615.7 | J37: 268 | K37: no data | L37: 804 | M37: INTERIM: Redfin SFR sales (12 mo) x tier weight
A38: 27 | B38: 92651 | C38: Laguna Beach | D38: Orange | E38: Orange County | F38: Emerald Bay | G38: Tier 1 (>= $700/sf) | H38: 1545.4744 | I38: 3121949.1 | J38: 265 | K38: no data | L38: 795 | M38: INTERIM: Redfin SFR sales (12 mo) x tier weight
A39: 28 | B39: 94070 | C39: San Carlos | D39: San Mateo | E39: Peninsula & South Bay (Santa Clara / San Mateo) | F39: Devonshire | G39: Tier 1 (>= $700/sf) | H39: 1389.7012 | I39: 2696220.8 | J39: 265 | K39: no data | L39: 795 | M39: INTERIM: Redfin SFR sales (12 mo) x tier weight
A40: 29 | B40: 95127 | C40: San Jose | D40: Santa Clara | E40: Peninsula & South Bay (Santa Clara / San Mateo) | F40: Alum Rock | G40: Tier 1 (>= $700/sf) | H40: 795.73846 | I40: 1173622.6 | J40: 265 | K40: no data | L40: 795 | M40: INTERIM: Redfin SFR sales (12 mo) x tier weight
A41: 30 | B41: 94087 | C41: Sunnyvale | D41: Santa Clara | E41: Peninsula & South Bay (Santa Clara / San Mateo) | F41: Birdland | G41: Tier 1 (>= $700/sf) | H41: 1663.5655 | I41: 2974583.3 | J41: 264 | K41: no data | L41: 792 | M41: INTERIM: Redfin SFR sales (12 mo) x tier weight
... A47: 36 | B47: 94611 | C47: Oakland | D47: Alameda | E47: Berkeley / Oakland / Alameda County | F47: Broadway Auto Row; Harrison/Oakland; Montclair; Oak Glen Park; Piedmont Avenue; Piedmont Pines; Westlake | G47: Tier 2 ($600-699/sf) | H47: 686.28151 | I47: 1441336.8 | J47: 386 | K47: no data | L47: 772 | M47: INTERIM: Redfin SFR sales (12 mo) x tier weight
A48: 37 | B48: 94560 | C48: Newark | D48: Alameda | E48: Berkeley / Oakland / Alameda County | G48: Tier 1 (>= $700/sf) | H48: 837.30364 | I48: 1415045.1 | J48: 255 | K48: no data | L48: 765 | M48: INTERIM: Redfin SFR sales (12 mo) x tier weight
A49: 38 | B49: 92660 | C49: Newport Beach | D49: Orange | E49: Orange County | F49: UCI - North Campus; Bayside Village; Belcourt; Castaways; Granville; Harbor Cove; Harbor Hill; Harbor View Knoll; Island Lagoon; Newport Hills; Newport North; North Bluff; One Ford Road; Sea View; Seawind; The Bluffs; The Plaza; Villa Point; Big Canyon; Bonita Canyon; Dover Shores; Eastbluff; Harbor Island; Harbor Ridge; Harbor View; Newport Ridge; Upper Bay | G49: Tier 1 (>= $700/sf) | H49: 1380.84 | I49: 3893911.4 | J49: 254 | K49: no data | L49: 762 | M49: INTERIM: Redfin SFR sales (12 mo) x tier weight
A50: 39 | B50: 92127 | C50: San Diego | D50: San Diego | E50: San Diego | F50: Black Mountain Ranch; 4S Commons; Auberge; Bel Etage; Camino Bernardo; Deer Ridge; Dove Canyon; Ivygate; Nicole Ridge; Paseo Montenero; Stone Ranch; Tanner Ridge; Verrazano; Village Green; 4S Ranch Business Park; Del Sur; North 4S Ranch; Rancho Bernardo Business Park; Santaluz; South 4S Ranch; Westwood | G50: Tier 1 (>= $700/sf) | H50: 713.32127 | I50: 2127369 | J50: 252 | K50: no data | L50: 756 | M50: INTERIM: Redfin SFR sales (12 mo) x tier weight
A51: 40 | B51: 92064 | C51: Poway | D51: San Diego | E51: San Diego | F51: Bridlewood; Bridlewood Country Estates; Bridlewood Lakeside; Carriage Heights; Casa Real Poway; Cicero; Colony; Country Squire Estates; Cree; Espola Verde; Flair; Gate; Golden City; Green Valley Estates North; Green Valley Estates South; Green Valley Summit; Hickory; Holiday Estates; Holland; Huntington Gate; Kentfield; La Paz Village; Ladera Piedra; Las Cadenas; Midland Estates; Midland Grove; Norwalk; O'Reno; Padre Woods; Parkway Business Centre; Piermont; Pomerado Business Park; Pomerado Gardens; Poway Corporate Center; Poway Grove Park; Poway Mesa North; Poway Mesa South; Poway Portals; Poway Woods; Rancho Arbolitos Palisades; Rancho Arbolitos Parkside; Rancho Arbolitos Woodside; Rancho La Paz; Rancho Poway; Rancho Verde; Range View Estates; Rayo Del Sol; Rollin Glen; Stone Canyon Ranch; Stoneridge Chateaus; Summerfield Estates; Sunrise Ranch; Sycamore Creek; Taunt; Temple; The Grove; The Ranch; Twin Circle; Valle Del Norte; Valle Verde Estates; Avocado Glen; Green Valley; Old Coach; Old Poway; Poway Town Center; Rancho Arbolitos; South Poway Business Park; Twin Peaks | G51: Tier 2 ($600-699/sf) | H51: 641.68389 | I51: 1304946.7 | J51: 375 | K51: no data | L51: 750 | M51: INTERIM: Redfin SFR sales (12 mo) x tier weight
A52: 41 | B52: 92679 | C52: Rancho Santa Margarita | D52: Orange | E52: Orange County | F52: Dove Canyon; Portola Hills; Robinson Ranch | G52: Tier 2 ($600-699/sf) | H52: 631.13114 | I52: 1707626.7 | J52: 375 | K52: no data | L52: 750 | M52: INTERIM: Redfin SFR sales (12 mo) x tier weight
A53: 42 | B53: 90068 | C53: Los Angeles | D53: Los Angeles | E53: Los Angeles County | F53: Beachwood Canyon; Hollywood Dell; Whitley Heights Historic District; Hollywood Hills | G53: Tier 1 (>= $700/sf) | H53: 870.9198 | I53: 1959068.5 | J53: 248 | K53: no data | L53: 744 | M53: INTERIM: Redfin SFR sales (12 mo) x tier weight
A54: 43 | B54: 95037 | C54: Morgan Hill | D54: Santa Clara | E54: Peninsula & South Bay (Santa Clara / San Mateo) | G54: Tier 2 ($600-699/sf) | H54: 660.69466 | I54: 1471168 | J54: 372 | K54: no data | L54: 744 | M54: INTERIM: Redfin SFR sales (12 mo) x tier weight
A55: 44 | B55: 90210 | C55: Beverly Hills | D55: Los Angeles | E55: Los Angeles County | F55: The Flats; Trousdale Estates; Beverly Crest | G55: Tier 1 (>= $700/sf) | H55: 1275.3541 | I55: 5961425.1 | J55: 247 | K55: no data | L55: 741 | M55: INTERIM: Redfin SFR sales (12 mo) x tier weight
A56: 45 | B56: 92626 | C56: Costa Mesa | D56: Orange | E56: Orange County | F56: College Park; Mesa Verde | G56: Tier 1 (>= $700/sf) | H56: 888.08112 | I56: 1588421.1 | J56: 247 | K56: no data | L56: 741 | M56: INTERIM: Redfin SFR sales (12 mo) x tier weight
A57: 46 | B57: 94587 | C57: Union City | D57: Alameda | E57: Berkeley / Oakland / Alameda County | F57: Alvarado; Decoto; Contempo; Colt Court | G57: Tier 1 (>= $700/sf) | H57: 814.84483 | I57: 1383502 | J57: 247 | K57: no data | L57: 741 | M57: INTERIM: Redfin SFR sales (12 mo) x tier weight
A58: 47 | B58: 90274 | C58: Palos Verdes Peninsula | D58: Los Angeles | E58: Los Angeles County | F58: Palos Verdes Estates; Rolling Hills; Rolling Hills Estates | G58: Tier 1 (>= $700/sf) | H58: 975.8403 | I58: 2669432.9 | J58: 246 | K58: no data | L58: 738 | M58: INTERIM: Redfin SFR sales (12 mo) x tier weight
A59: 48 | B59: 94526 | C59: Danville | D59: Contra Costa | E59: Rest of California | F59: Anderson Ranch; Brookview; California Chateau; Crow Canyon Heights; Danville Ranch; Diablo Highlands; Diablo West; Osborn Estates; Sycamore Creek; Sycamore Homes; Windstream | G59: Tier 1 (>= $700/sf) | H59: 818.4109 | I59: 1889532.5 | J59: 246 | K59: no data | L59: 738 | M59: INTERIM: Redfin SFR sales (12 mo) x tier weight
A60: 49 | B60: 95051 | C60: Santa Clara | D60: Santa Clara | E60: Peninsula & South Bay (Santa Clara / San Mateo) | G60: Tier 1 (>= $700/sf) | H60: 1419.1115 | I60: 2196512.2 | J60: 246 | K60: no data | L60: 738 | M60: INTERIM: Redfin SFR sales (12 mo) x tier weight
A61: 50 | B61: 94062 | C61: Redwood City | D61: San Mateo | E61: Peninsula & South Bay (Santa Clara / San Mateo) | F61: Emerald Lake Hills; Kensington Square | G61: Tier 1 (>= $700/sf) | H61: 1306.3344 | I61: 2963163.3 | J61: 245 | K61: no data | L61: 735 | M61: INTERIM: Redfin SFR sales (12 mo) x tier weight
A62: 51 | B62: 92115 | C62: San Diego | D62: San Diego | E62: San Diego | F62: Mid-City; Montezuma Mesa; Alvarado Estates; Baja Canyon; College View Estates; The Triangle; Colina Park; Darnall; El Cerrito; El Cerrito Heights; Little Saigon; Mesa Colony; Oak Park; Rolando; Rolando Park; Talmadge | G62: Tier 1 (>= $700/sf) | H62: 717.53638 | I62: 934370.9 | J62: 244 | K62: no data | L62: 732 | M62: INTERIM: Redfin SFR sales (12 mo) x tier weight
A63: 52 | B63: 94044 | C63: Pacifica | D63: San Mateo | E63: Peninsula & South Bay (Santa Clara / San Mateo) | F63: Castle Hill; Edgemar; Fairway Park; Hilton Heights; Linda Mar; Pacific Manor; Pedro Valley; Rockaway Beach; Sharp Park; Shelter Cove; Vallemar | G63: Tier 1 (>= $700/sf) | H63: 867.36228 | I63: 1319405.7 | J63: 244 | K63: no data | L63: 732 | M63: INTERIM: Redfin SFR sales (12 mo) x tier weight
A64: 53 | B64: 94539 | C64: Fremont | D64: Alameda | E64: Berkeley / Oakland / Alameda County | F64: Mission San Jose District; Warm Springs District | G64: Tier 1 (>= $700/sf) | H64: 1193.9697 | I64: 2395041.7 | J64: 240 | K64: no data | L64: 720 | M64: INTERIM: Redfin SFR sales (12 mo) x tier weight
A65: 54 | B65: 92675 | C65: San Juan Capistrano | D65: Orange | E65: Orange County | F65: Rienda; Rancho Mission Viejo | G65: Tier 1 (>= $700/sf) | H65: 725.47033 | I65: 1875146.4 | J65: 239 | K65: no data | L65: 717 | M65: INTERIM: Redfin SFR sales (12 mo) x tier weight
A66: 55 | B66: 90046 | C66: Los Angeles | D66: Los Angeles | E66: Los Angeles County | F66: Hollywood Hills West | G66: Tier 1 (>= $700/sf) | H66: 963.51314 | I66: 2237252.1 | J66: 238 | K66: no data | L66: 714 | M66: INTERIM: Redfin SFR sales (12 mo) x tier weight
A67: 56 | B67: 92672 | C67: San Clemente | D67: Orange | E67: Orange County | F67: Bay Cliff Village; Colony Cove; Sea Summit | G67: Tier 1 (>= $700/sf) | H67: 999.24195 | I67: 1906691.2 | J67: 238 | K67: no data | L67: 714 | M67: INTERIM: Redfin SFR sales (12 mo) x tier weight
A68: 57 | B68: 94901 | C68: San Rafael | D68: Marin | E68: Marin | F68: Canal; Chicken Point; Dominican | G68: Tier 1 (>= $700/sf) | H68: 757.76377 | I68: 1526617.6 | J68: 238 | K68: no data | L68: 714 | M68: INTERIM: Redfin SFR sales (12 mo) x tier weight
A69: 58 | B69: 95476 | C69: Sonoma | D69: Sonoma | E69: Rest of California | G69: Tier 2 ($600-699/sf) | H69: 644.47498 | I69: 1110382 | J69: 356 | K69: no data | L69: 712 | M69: INTERIM: Redfin SFR sales (12 mo) x tier weight
A70: 59 | B70: 90045 | C70: Los Angeles | D70: Los Angeles | E70: Los Angeles County | F70: Westchester; Westchester Triangle | G70: Tier 1 (>= $700/sf) | H70: 952.25122 | I70: 1706886.1 | J70: 237 | K70: no data | L70: 711 | M70: INTERIM: Redfin SFR sales (12 mo) x tier weight
A71: 60 | B71: 94105 | C71: San Francisco | D71: San Francisco | E71: San Francisco | F71: Rincon Hill; 50 Beale Street Plaza; 560 Mission Street Plaza; Foundry Square | G71: Tier 1 (>= $700/sf) | H71: 1097.7808 | I71: 1149831.2 | J71: 237 | K71: no data | L71: 711 | M71: INTERIM: Redfin SFR sales (12 mo) x tier weight
A72: 61 | B72: 95003 | C72: Aptos | D72: Santa Cruz | E72: Rest of California | G72: Tier 1 (>= $700/sf) | H72: 815.35008 | I72: 1507561.2 | J72: 237 | K72: no data | L72: 711 | M72: INTERIM: Redfin SFR sales (12 mo) x tier weight
A73: 62 | B73: 94015 | C73: Daly City | D73: San Mateo | E73: Peninsula & South Bay (Santa Clara / San Mateo) | F73: Serramonte; Westlake | G73: Tier 1 (>= $700/sf) | H73: 856.38105 | I73: 1282665.3 | J73: 236 | K73: no data | L73: 708 | M73: INTERIM: Redfin SFR sales (12 mo) x tier weight
A74: 63 | B74: 94583 | C74: San Ramon | D74: Contra Costa | E74: Rest of California | F74: Alexander Square | G74: Tier 1 (>= $700/sf) | H74: 749.0144 | I74: 1516092.1 | J74: 236 | K74: no data | L74: 708 | M74: INTERIM: Redfin SFR sales (12 mo) x tier weight
A75: 64 | B75: 94563 | C75: Orinda | D75: Contra Costa | E75: Rest of California | F75: Glorietta; Wilder; Orinda Theatre Square | G75: Tier 1 (>= $700/sf) | H75: 768.83347 | I75: 1911534.2 | J75: 234 | K75: no data | L75: 702 | M75: INTERIM: Redfin SFR sales (12 mo) x tier weight
A76: 65 | B76: 92648 | C76: Huntington Beach | D76: Orange | E76: Orange County | G76: Tier 1 (>= $700/sf) | H76: 846.0964 | I76: 2023515 | J76: 233 | K76: no data | L76: 699 | M76: INTERIM: Redfin SFR sales (12 mo) x tier weight
A77: 66 | B77: 94116 | C77: San Francisco | D77: San Francisco | E77: San Francisco | F77: Parkside; Forest Hill; Golden Gate Heights | G77: Tier 1 (>= $700/sf) | H77: 1093.2446 | I77: 1793051.5 | J77: 233 | K77: no data | L77: 699 | M77: INTERIM: Redfin SFR sales (12 mo) x tier weight
A78: 67 | B78: 90065 | C78: Los Angeles | D78: Los Angeles | E78: Los Angeles County | F78: Dayton Avenue; Glassell Park; Mount Washington; Bobby Brown Uptown Gay and Lesbian Alliance Square; Cypress Park | G78: Tier 1 (>= $700/sf) | H78: 806.80722 | I78: 1241510 | J78: 232 | K78: no data | L78: 696 | M78: INTERIM: Redfin SFR sales (12 mo) x tier weight
A79: 68 | B79: 92886 | C79: Yorba Linda | D79: Orange | E79: Orange County | F79: Country Club; Fairlynn | G79: Tier 2 ($600-699/sf) | H79: 659.11359 | I79: 1486793.1 | J79: 348 | K79: no data | L79: 696 | M79: INTERIM: Redfin SFR sales (12 mo) x tier weight
A80: 69 | B80: 92691 | C80: Mission Viejo | D80: Orange | E80: Orange County | G80: Tier 2 ($600-699/sf) | H80: 672.26668 | I80: 1335247.1 | J80: 344 | K80: no data | L80: 688 | M80: INTERIM: Redfin SFR sales (12 mo) x tier weight
A81: 70 | B81: 92705 | C81: Santa Ana | D81: Orange | E81: Orange County | F81: Cowan Heights; Fairbridge Square; Lemon Heights; Lyon Street; North Tustin; Young Square; Panorama Heights | G81: Tier 1 (>= $700/sf) | H81: 703.34542 | I81: 1752550.2 | J81: 229 | K81: no data | L81: 687 | M81: INTERIM: Redfin SFR sales (12 mo) x tier weight
A82: 71 | B82: 92694 | C82: Ladera Ranch | D82: Orange | E82: Orange County | F82: Los Patrones | G82: Tier 2 ($600-699/sf) | H82: 656.34391 | I82: 1504487.9 | J82: 341 | K82: no data | L82: 682 | M82: INTERIM: Redfin SFR sales (12 mo) x tier weight
A83: 72 | B83: 92647 | C83: Huntington Beach | D83: Orange | E83: Orange County | G83: Tier 1 (>= $700/sf) | H83: 811.46192 | I83: 1301519.8 | J83: 227 | K83: no data | L83: 681 | M83: INTERIM: Redfin SFR sales (12 mo) x tier weight
A84: 73 | B84: 94080 | C84: South San Francisco | D84: San Mateo | E84: Peninsula & South Bay (Santa Clara / San Mateo) | F84: South San Francisco BART Plaza | G84: Tier 1 (>= $700/sf) | H84: 885.31412 | I84: 1290977.8 | J84: 225 | K84: no data | L84: 675 | M84: INTERIM: Redfin SFR sales (12 mo) x tier weight
A85: 74 | B85: 94403 | C85: San Mateo | D85: San Mateo | E85: Peninsula & South Bay (Santa Clara / San Mateo) | F85: Bay Meadows Town Square | G85: Tier 1 (>= $700/sf) | H85: 1233.3342 | I85: 2103080.4 | J85: 224 | K85: no data | L85: 672 | M85: INTERIM: Redfin SFR sales (12 mo) x tier weight
A86: 75 | B86: 94061 | C86: Redwood City | D86: San Mateo | E86: Peninsula & South Bay (Santa Clara / San Mateo) | F86: Sequoia Tract | G86: Tier 1 (>= $700/sf) | H86: 1288.5232 | I86: 2198370 | J86: 223 | K86: no data | L86: 669 | M86: INTERIM: Redfin SFR sales (12 mo) x tier weight
A87: 76 | B87: 94131 | C87: San Francisco | D87: San Francisco | E87: San Francisco | F87: Diamond Heights; Forest Knolls; Sunnyside; Glen Park | G87: Tier 1 (>= $700/sf) | H87: 1182.7691 | I87: 2057031.4 | J87: 223 | K87: no data | L87: 669 | M87: INTERIM: Redfin SFR sales (12 mo) x tier weight
A88: 77 | B88: 94402 | C88: San Mateo | D88: San Mateo | E88: Peninsula & South Bay (Santa Clara / San Mateo) | G88: Tier 1 (>= $700/sf) | H88: 1351.5091 | I88: 2643433.5 | J88: 218 | K88: no data | L88: 654 | M88: INTERIM: Redfin SFR sales (12 mo) x tier weight
A89: 78 | B89: 94602 | C89: Oakland | D89: Alameda | E89: Berkeley / Oakland / Alameda County | F89: Oakland Hills; Dimond District; Glenview; Oakmore Highlands | G89: Tier 1 (>= $700/sf) | H89: 719.58458 | I89: 1100004.6 | J89: 217 | K89: no data | L89: 651 | M89: INTERIM: Redfin SFR sales (12 mo) x tier weight
A90: 79 | B90: 94122 | C90: San Francisco | D90: San Francisco | E90: San Francisco | F90: Sunset District; Inner Sunset; Outer Sunset | G90: Tier 1 (>= $700/sf) | H90: 1102.9881 | I90: 1805560.2 | J90: 216 | K90: no data | L90: 648 | M90: INTERIM: Redfin SFR sales (12 mo) x tier weight
A91: 80 | B91: 94903 | C91: San Rafael | D91: Marin | E91: Marin | F91: Terra Linda | G91: Tier 1 (>= $700/sf) | H91: 787.22453 | I91: 1376342.6 | J91: 216 | K91: no data | L91: 648 | M91: INTERIM: Redfin SFR sales (12 mo) x tier weight
A92: 81 | B92: 90042 | C92: Los Angeles | D92: Los Angeles | E92: Los Angeles County | F92: Highland Park | G92: Tier 1 (>= $700/sf) | H92: 910.32727 | I92: 1218744.2 | J92: 215 | K92: no data | L92: 645 | M92: INTERIM: Redfin SFR sales (12 mo) x tier weight
A93: 82 | B93: 91604 | C93: Studio City | D93: Los Angeles | E93: Los Angeles County | F93: Studio City; Studio City Neighborhood Council District; Silver Triangle | G93: Tier 1 (>= $700/sf) | H93: 929.38437 | I93: 2222325.6 | J93: 215 | K93: no data | L93: 645 | M93: INTERIM: Redfin SFR sales (12 mo) x tier weight
A94: 83 | B94: 91302 | C94: Calabasas | D94: Los Angeles | E94: Los Angeles County | F94: Braewood | G94: Tier 1 (>= $700/sf) | H94: 708.53292 | I94: 2000032.7 | J94: 214 | K94: no data | L94: 642 | M94: INTERIM: Redfin SFR sales (12 mo) x tier weight
A95: 84 | B95: 94024 | C95: Los Altos | D95: Santa Clara | E95: Peninsula & South Bay (Santa Clara / San Mateo) | F95: Creston | G95: Tier 1 (>= $700/sf) | H95: 1798.3022 | I95: 4535658.9 | J95: 214 | K95: no data | L95: 642 | M95: INTERIM: Redfin SFR sales (12 mo) x tier weight
A96: 85 | B96: 91423 | C96: Sherman Oaks | D96: Los Angeles | E96: Los Angeles County | F96: Sherman Village | G96: Tier 1 (>= $700/sf) | H96: 820.79183 | I96: 1981969.5 | J96: 213 | K96: no data | L96: 639 | M96: INTERIM: Redfin SFR sales (12 mo) x tier weight
A97: 86 | B97: 94506 | C97: Danville | D97: Contra Costa | E97: Rest of California | F97: California Shadowhawk; Meadow Creek; Northridge Estates; Woodside Oaks | G97: Tier 1 (>= $700/sf) | H97: 726.81368 | I97: 2372046.9 | J97: 213 | K97: no data | L97: 639 | M97: INTERIM: Redfin SFR sales (12 mo) x tier weight
A98: 87 | B98: 95014 | C98: Cupertino | D98: Santa Clara | E98: Peninsula & South Bay (Santa Clara / San Mateo) | F98: Rancho Rinconada; Wilson Park; Academic Quad; Cupertino Civic Center; Olive Court; Rally Court | G98: Tier 1 (>= $700/sf) | H98: 1673.3281 | I98: 3404641.5 | J98: 212 | K98: no data | L98: 636 | M98: INTERIM: Redfin SFR sales (12 mo) x tier weight
A99: 88 | B99: 95008 | C99: Campbell | D99: Santa Clara | E99: Peninsula & South Bay (Santa Clara / San Mateo) | F99: San Tomas; Campbell Courtyard; Quad | G99: Tier 1 (>= $700/sf) | H99: 1232.7196 | I99: 2132189.6 | J99: 211 | K99: no data | L99: 633 | M99: INTERIM: Redfin SFR sales (12 mo) x tier weight
A100: 89 | B100: 92673 | C100: San Clemente | D100: Orange | E100: Orange County | F100: Portofino; San Rafael; Compass Pointe; El Encanto; Flora Vista; San Angelo; Talega | G100: Tier 1 (>= $700/sf) | H100: 710.1822 | I100: 1848358.2 | J100: 210 | K100: no data | L100: 630 | M100: INTERIM: Redfin SFR sales (12 mo) x tier weight
A101: 90 | B101: 92618 | C101: Irvine | D101: Orange | E101: Orange County | F101: Altair; Cypress Village; Great Park; Irvine Spectrum; Laguna Altura; Los Olivos; Oak Creek; Portola Springs; Woodbury East; Lambert Ranch; Travata; Woodbury Place Apartments | G101: Tier 1 (>= $700/sf) | H101: 835.06192 | I101: 2375134 | J101: 209 | K101: no data | L101: 627 | M101: INTERIM: Redfin SFR sales (12 mo) x tier weight
A102: 91 | B102: 94546 | C102: Hayward | D102: Alameda | E102: Berkeley / Oakland / Alameda County | G102: Tier 2 ($600-699/sf) | H102: 695.01202 | I102: 1107667.7 | J102: 313 | K102: no data | L102: 626 | M102: INTERIM: Redfin SFR sales (12 mo) x tier weight
A103: 92 | B103: 94501 | C103: Alameda | D103: Alameda | E103: Berkeley / Oakland / Alameda County | F103: East End; Fernside; Gold Coast; South Shore; West End; Woodstock | G103: Tier 1 (>= $700/sf) | H103: 785.37641 | I103: 1372843.8 | J103: 208 | K103: no data | L103: 624 | M103: INTERIM: Redfin SFR sales (12 mo) x tier weight
A104: 93 | B104: 95070 | C104: Saratoga | D104: Santa Clara | E104: Peninsula & South Bay (Santa Clara / San Mateo) | G104: Tier 1 (>= $700/sf) | H104: 1578.8767 | I104: 4336254.8 | J104: 208 | K104: no data | L104: 624 | M104: INTERIM: Redfin SFR sales (12 mo) x tier weight
A105: 94 | B105: 91361 | C105: Westlake Village | D105: Ventura | E105: Ventura | F105: Bridgehaven; First Neighborhood; Westlake Bay; Westshore | G105: Tier 1 (>= $700/sf) | H105: 714.2615 | I105: 1922487.9 | J105: 207 | K105: no data | L105: 621 | M105: INTERIM: Redfin SFR sales (12 mo) x tier weight
A106: 95 | B106: 90650 | C106: Norwalk | D106: Los Angeles | E106: Los Angeles County | G106: Tier 2 ($600-699/sf) | H106: 636.7825 | I106: 759563.11 | J106: 309 | K106: no data | L106: 618 | M106: INTERIM: Redfin SFR sales (12 mo) x tier weight
...

Sheet All ZIPs
A1: Rank | B1: ZIP | C1: City | D1: County | E1: Focus region | F1: Neighborhoods | G1: Redfin metro | H1: Median sale $/sq ft (12 mo) | I1: $/sq ft basis | J1: Median sale price (12 mo) | K1: Homes sold (12 mo) | L1: Thin sample (<5 sales) | M1: Has ZIP boundary (ZCTA) | N1: Tier | O1: Tier weight | P1: Total SFR parcels | Q1: SFR lots >= 5,000 sq ft | R1: % SFR lots >= 5,000 | S1: Est. buildable >= 750 sq ft | T1: % est. buildable >= 750 | U1: Est. buildable >= 1,200 sq ft | V1: Flag: contiguous area likely < 750 | W1: Median lot size (sq ft) | X1: Parcel data | Y1: Rank score (qualifying parcels x weight) | Z1: Interim score (homes sold x weight) | AA1: Rank basis | AB1: Building footprints (all) | AC1: House-scale footprints (600-6,000 sq ft) | AD1: Footprints sourced from Microsoft | AE1: Median house-scale footprint (sq ft) | AF1: Latest-quarter $/sq ft | AG1: Latest-quarter $/sq ft YoY | AH1: County share of ZIP area | AI1: City source | AJ1: Other postal cities (>=10% of addresses) | AK1: Overture locality (largest overlap)
A2: 1 | B2: 92677 | C2: Laguna Niguel | D2: Orange | E2: Orange County | F2: El Niguel Heights; Niguel Summit | G2: Anaheim, CA | H2: 811.06558 | I2: SFR | J2: 1723455.2 | K2: 424 | M2: =TRUE() -> TRUE | N2: =IF(H2="","",IF(H2>=Assumptions!$B$5,1,IF(H2>=Assumptions!$B$6,2,IF(H2>=Assumptions!$B$7,3,"")))) -> 1 | O2: =IF(N2=1,Assumptions!$B$8,IF(N2=2,Assumptions!$B$9,IF(N2=3,Assumptions!$B$10,0))) -> 3 | P2: no data | Q2: no data | R2: no data | S2: no data | T2: no data | U2: no data | V2: no data | W2: no data | X2: no data | Y2: =IF(AND(X2="processed",ISNUMBER(S2)),S2*O2,"") | Z2: =IF(ISNUMBER(K2),K2*O2,0) -> 1272 | AA2: INTERIM: Redfin SFR sales (12 mo) x tier weight | AB2: 19157 | AC2: 17471 | AD2: 261 | AE2: 2521.2434 | AF2: 842.42056 | AG2: 0.011334465 | AH2: 1 | AI2: postal city of 100% of address points | AJ2: Laguna Niguel | AK2: Laguna Niguel
A3: 2 | B3: 94550 | C3: Livermore | D3: Alameda | E3: Berkeley / Oakland / Alameda County | F3: Sandhurst; The Grove; Village II; Vinsanto II; Livermorium Plaza / Mills Square Park; Lizzie Fountain Plaza | G3: Oakland, CA | H3: 704.67241 | I3: SFR | J3: 1341359.2 | K3: 412 | M3: =TRUE() -> TRUE | N3: =IF(H3="","",IF(H3>=Assumptions!$B$5,1,IF(H3>=Assumptions!$B$6,2,IF(H3>=Assumptions!$B$7,3,"")))) -> 1 | O3: =IF(N3=1,Assumptions!$B$8,IF(N3=2,Assumptions!$B$9,IF(N3=3,Assumptions!$B$10,0))) -> 3 | P3: no data | Q3: no data | R3: no data | S3: no data | T3: no data | U3: no data | V3: no data | W3: no data | X3: no data | Y3: =IF(AND(X3="processed",ISNUMBER(S3)),S3*O3,"") | Z3: =IF(ISNUMBER(K3),K3*O3,0) -> 1236 | AA3: INTERIM: Redfin SFR sales (12 mo) x tier weight | AB3: 21065 | AC3: 18532 | AD3: 4984 | AE3: 2510.7314 | AF3: 740.22577 | AG3: 0.019543651 | AH3: 0.67441355 | AI3: locality polygon (largest overlap) | AK3: Livermore
A4: 3 | B4: 95125 | C4: San Jose | D4: Santa Clara | E4: Peninsula & South Bay (Santa Clara / San Mateo) | F4: Dry Creek; Willow Glen | G4: San Jose, CA | H4: 1137.9459 | I4: SFR | J4: 2062863.5 | K4: 381 | M4: =TRUE() -> TRUE | N4: =IF(H4="","",IF(H4>=Assumptions!$B$5,1,IF(H4>=Assumptions!$B$6,2,IF(H4>=Assumptions!$B$7,3,"")))) -> 1 | O4: =IF(N4=1,Assumptions!$B$8,IF(N4=2,Assumptions!$B$9,IF(N4=3,Assumptions!$B$10,0))) -> 3 | P4: no data | Q4: no data | R4: no data | S4: no data | T4: no data | U4: no data | V4: no data | W4: no data | X4: no data | Y4: =IF(AND(X4="processed",ISNUMBER(S4)),S4*O4,"") | Z4: =IF(ISNUMBER(K4),K4*O4,0) -> 1143 | AA4: INTERIM: Redfin SFR sales (12 mo) x tier weight | AB4: 25731 | AC4: 17724 | AD4: 515 | AE4: 2122.4167 | AF4: 1176.0398 | AG4: -0.015815354 | AH4: 1 | AI4: postal city of 99% of address points | AJ4: San Jose | AK4: San Jose
A5: 4 | B5: 92024 | C5: Encinitas | D5: San Diego | E5: San Diego | F5: Leucadia; Olivenhain; Downtown Encinitas; Encinitas Highlands; Encinitas Ranch; Fox Point Farms; Manzanita Cove; Old Encinitas; Pacific Serena; Val Sereno; New Encinitas; Poinsettia Heights; Quail Gardens; Rancho Encinitas; Village Park | G5: San Diego, CA | H5: 964.56064 | I5: SFR | J5: 2278542 | K5: 369 | M5: =TRUE() -> TRUE | N5: =IF(H5="","",IF(H5>=Assumptions!$B$5,1,IF(H5>=Assumptions!$B$6,2,IF(H5>=Assumptions!$B$7,3,"")))) -> 1 | O5: =IF(N5=1,Assumptions!$B$8,IF(N5=2,Assumptions!$B$9,IF(N5=3,Assumptions!$B$10,0))) -> 3 | P5: no data | Q5: no data | R5: no data | S5: no data | T5: no data | U5: no data | V5: no data | W5: no data | X5: no data | Y5: =IF(AND(X5="processed",ISNUMBER(S5)),S5*O5,"") | Z5: =IF(ISNUMBER(K5),K5*O5,0) -> 1107 | AA5: INTERIM: Redfin SFR sales (12 mo) x tier weight | AB5: 21782 | AC5: 17409 | AD5: 844 | AE5: 2482.032 | AF5: 977.26857 | AG5: 0.052769642 | AH5: 0.96634422 | AI5: postal city of 99% of address points | AJ5: Encinitas | AK5: Encinitas
A6: 5 | B6: 95124 | C6: San Jose | D6: Santa Clara | E6: Peninsula & South Bay (Santa Clara / San Mateo) | F6: Willow Glen Place | G6: San Jose, CA | H6: 1220.4989 | I6: SFR | J6: 2057880.4 | K6: 368 | M6: =TRUE() -> TRUE | N6: =IF(H6="","",IF(H6>=Assumptions!$B$5,1,IF(H6>=Assumptions!$B$6,2,IF(H6>=Assumptions!$B$7,3,"")))) -> 1 | O6: =IF(N6=1,Assumptions!$B$8,IF(N6=2,Assumptions!$B$9,IF(N6=3,Assumptions!$B$10,0))) -> 3 | P6: no data | Q6: no data | R6: no data | S6: no data | T6: no data | U6: no data | V6: no data | W6: no data | X6: no data | Y6: =IF(AND(X6="processed",ISNUMBER(S6)),S6*O6,"") | Z6: =IF(ISNUMBER(K6),K6*O6,0) -> 1104 | AA6: INTERIM: Redfin SFR sales (12 mo) x tier weight | AB6: 20690 | AC6: 15442 | AD6: 190 | AE6: 2457.561 | AF6: 1261.6487 | AG6: -0.0070049688 | AH6: 1 | AI6: postal city of 99% of address points | AJ6: San Jose | AK6: San Jose
A7: 6 | B7: 96161 | C7: Truckee | D7: Placer | E7: Rest of California | F7: Glenshire-Devonshire; Tahoe Donner; Armstrong; Blitz Tract; Cambridge Estates; Devonshire; Donner Crest; Donner Lake Village; Donner Pines Tract; Donner Ski Haven; Donner Tract; Donner Trail; Donner Woods; Emmons Tract; Gateway Park; Glenshire; Gray's Crossing; Juniper Creek Ranch; Juniper Heights; Juniper Hill; Klondike Flat; Lakeview; Martis Peak; Martiswood Estates; Meadow Lake Park; Old Greenwood; Olympic Heights; Plavada Woodlands; Ponderosa Fairway Estates; Ponderosa Palisades; Ponderosa Ranchos; Prosser Lake Heights; Prosser Lakeview Estates; Schaffer's Mill; Sierra Bluff; Southside Highlands; The Meadows; Weeks Tract; Gateway; Lahontan; Martis Camp; Sierra Meadows; West End Donner | G7: Sacramento, CA | H7: 612.99992 | I7: SFR | J7: 1264262.7 | K7: 533 | M7: =TRUE() -> TRUE | N7: =IF(H7="","",IF(H7>=Assumptions!$B$5,1,IF(H7>=Assumptions!$B$6,2,IF(H7>=Assumptions!$B$7,3,"")))) -> 2 | O7: =IF(N7=1,Assumptions!$B$8,IF(N7=2,Assumptions!$B$9,IF(N7=3,Assumptions!$B$10,0))) -> 2 | P7: no data | Q7: no data | R7: no data | S7: no data | T7: no data | U7: no data | V7: no data | W7: no data | X7: no data | Y7: =IF(AND(X7="processed",ISNUMBER(S7)),S7*O7,"") | Z7: =IF(ISNUMBER(K7),K7*O7,0) -> 1066 | AA7: INTERIM: Redfin SFR sales (12 mo) x tier weight | AB7: 16846 | AC7: 15188 | AD7: 11181 | AE7: 1971.8755 | AF7: 649.99596 | AG7: 0.012026708 | AH7: 0.56042357 | AI7: postal city of 100% of address points | AJ7: Truckee | AK7: Truckee
A8: 7 | B8: 92117 | C8: San Diego | D8: San Diego | E8: San Diego | F8: Bay Ho; Clairemont; Clairemont Mesa Gateway; Diane Village; North Mount Estates; Riviera Highlands; Triumph; Westridge; Alcott Estates; Clairemont Village; East Clairemont; Eureka Lemon; North Clairemont | G8: San Diego, CA | H8: 805.70845 | I8: SFR | J8: 1173166.2 | K8: 349 | M8: =TRUE() -> TRUE | N8: =IF(H8="","",IF(H8>=Assumptions!$B$5,1,IF(H8>=Assumptions!$B$6,2,IF(H8>=Assumptions!$B$7,3,"")))) -> 1 | O8: =IF(N8=1,Assumptions!$B$8,IF(N8=2,Assumptions!$B$9,IF(N8=3,Assumptions!$B$10,0))) -> 3 | P8: no data | Q8: no data | R8: no data | S8: no data | T8: no data | U8: no data | V8: no data | W8: no data | X8: no data | Y8: =IF(AND(X8="processed",ISNUMBER(S8)),S8*O8,"") | Z8: =IF(ISNUMBER(K8),K8*O8,0) -> 1047 | AA8: INTERIM: Redfin SFR sales (12 mo) x tier weight | AB8: 18445 | AC8: 15595 | AD8: 544 | AE8: 2245.3982 | AF8: 827.52613 | AG8: 0.047134748 | AH8: 1 | AI8: postal city of 100% of address points | AJ8: San Diego | AK8: San Diego
A9: 8 | B9: 94112 | C9: San Francisco | D9: San Francisco | E9: San Francisco | F9: Ocean View; Outer Mission; St. Mary's Park; Westwood Park; Crocker-Amazon; Excelsior; Ingleside | G9: San Francisco, CA | H9: 856.09109 | I9: SFR | J9: 1247670.1 | K9: 335 | M9: =TRUE() -> TRUE | N9: =IF(H9="","",IF(H9>=Assumptions!$B$5,1,IF(H9>=Assumptions!$B$6,2,IF(H9>=Assumptions!$B$7,3,"")))) -> 1 | O9: =IF(N9=1,Assumptions!$B$8,IF(N9=2,Assumptions!$B$9,IF(N9=3,Assumptions!$B$10,0))) -> 3 | P9: no data | Q9: no data | R9: no data | S9: no data | T9: no data | U9: no data | V9: no data | W9: no data | X9: no data | Y9: =IF(AND(X9="processed",ISNUMBER(S9)),S9*O9,"") | Z9: =IF(ISNUMBER(K9),K9*O9,0) -> 1005 | AA9: INTERIM: Redfin SFR sales (12 mo) x tier weight | AB9: 19050 | AC9: 18175 | AD9: 147 | AE9: 1289.9436 | AF9: 919.41392 | AG9: 0.15367727 | AH9: 0.99863204 | AI9: postal city of 100% of address points | AJ9: San Francisco | AK9: Daly City
A10: 9 | B10: 92646 | C10: Huntington Beach | D10: Orange | E10: Orange County | G10: Anaheim, CA | H10: 825.07272 | I10: SFR | J10: 1512396.4 | K10: 333 | M10: =TRUE() -> TRUE | N10: =IF(H10="","",IF(H10>=Assumptions!$B$5,1,IF(H10>=Assumptions!$B$6,2,IF(H10>=Assumptions!$B$7,3,"")))) -> 1 | O10: =IF(N10=1,Assumptions!$B$8,IF(N10=2,Assumptions!$B$9,IF(N10=3,Assumptions!$B$10,0))) -> 3 | P10: no data | Q10: no data | R10: no data | S10: no data | T10: no data | U10: no data | V10: no data | W10: no data | X10: no data | Y10: =IF(AND(X10="processed",ISNUMBER(S10)),S10*O10,"") | Z10: =IF(ISNUMBER(K10),K10*O10,0) -> 999 | AA10: INTERIM: Redfin SFR sales (12 mo) x tier weight | AB10: 18051 | AC10: 16987 | AD10: 534 | AE10: 2346.4419 | AF10: 839.73129 | AG10: 0.035250809 | AH10: 0.94444728 | AI10: postal city of 100% of address points | AJ10: Huntington Beach | AK10: Huntington Beach
A11: 10 | B11: 94010 | C11: Burlingame | D11: San Mateo | E11: Peninsula & South Bay (Santa Clara / San Mateo) | F11: Burlingame Hills; Burlingame Village; Burlingame Town Square | G11: San Francisco, CA | H11: 1516.4872 | I11: SFR | J11: 3999650.9 | K11: 328 | M11: =TRUE() -> TRUE | N11: =IF(H11="","",IF(H11>=Assumptions!$B$5,1,IF(H11>=Assumptions!$B$6,2,IF(H11>=Assumptions!$B$7,3,"")))) -> 1 | O11: =IF(N11=1,Assumptions!$B$8,IF(N11=2,Assumptions!$B$9,IF(N11=3,Assumptions!$B$10,0))) -> 3 | P11: no data | Q11: no data | R11: no data | S11: no data | T11: no data | U11: no data | V11: no data | W11: no data | X11: no data | Y11: =IF(AND(X11="processed",ISNUMBER(S11)),S11*O11,"") | Z11: =IF(ISNUMBER(K11),K11*O11,0) -> 984 | AA11: INTERIM: Redfin SFR sales (12 mo) x tier weight | AB11: 15853 | AC11: 12741 | AD11: 617 | AE11: 2403.5564 | AF11: 1573.5641 | AG11: 0.068606402 | AH11: 0.9782138 | AI11: postal city of 71% of address points | AJ11: Burlingame; Hillsborough | AK11: Hillsborough
A12: 11 | B12: 95123 | C12: San Jose | D12: Santa Clara | E12: Peninsula & South Bay (Santa Clara / San Mateo) | F12: Parkview | G12: San Jose, CA | H12: 911.12898 | I12: SFR | J12: 1504662.6 | K12: 326 | M12: =TRUE() -> TRUE | N12: =IF(H12="","",IF(H12>=Assumptions!$B$5,1,IF(H12>=Assumptions!$B$6,2,IF(H12>=Assumptions!$B$7,3,"")))) -> 1 | O12: =IF(N12=1,Assumptions!$B$8,IF(N12=2,Assumptions!$B$9,IF(N12=3,Assumptions!$B$10,0))) -> 3 | P12: no data | Q12: no data | R12: no data | S12: no data | T12: no data | U12: no data | V12: no data | W12: no data | X12: no data | Y12: =IF(AND(X12="processed",ISNUMBER(S12)),S12*O12,"") | Z12: =IF(ISNUMBER(K12),K12*O12,0) -> 978 | AA12: INTERIM: Redfin SFR sales (12 mo) x tier weight | AB12: 20834 | AC12: 16054 | AD12: 196 | AE12: 2331.7593 | AF12: 920.91008 | AG12: -0.031627636 | AH12: 1 | AI12: postal city of 100% of address points | AJ12: San Jose | AK12: San Jose
A13: 12 | B13: 94025 | C13: Menlo Park | D13: San Mateo | E13: Peninsula & South Bay (Santa Clara / San Mateo) | F13: Stanford Hills; Stanford Weekend Acres; Hacker Square | G13: San Francisco, CA | H13: 1691.4166 | I13: SFR | J13: 3314959.5 | K13: 321 | M13: =TRUE() -> TRUE | N13: =IF(H13="","",IF(H13>=Assumptions!$B$5,1,IF(H13>=Assumptions!$B$6,2,IF(H13>=Assumptions!$B$7,3,"")))) -> 1 | O13: =IF(N13=1,Assumptions!$B$8,IF(N13=2,Assumptions!$B$9,IF(N13=3,Assumptions!$B$10,0))) -> 3 | P13: no data | Q13: no data | R13: no data | S13: no data | T13: no data | U13: no data | V13: no data | W13: no data | X13: no data | Y13: =IF(AND(X13="processed",ISNUMBER(S13)),S13*O13,"") | Z13: =IF(ISNUMBER(K13),K13*O13,0) -> 963 | AA13: INTERIM: Redfin SFR sales (12 mo) x tier weight | AB13: 16385 | AC13: 13018 | AD13: 135 | AE13: 2194.3567 | AF13: 1753.3715 | AG13: 0.06321944 | AH13: 0.97136118 | AI13: postal city of 98% of address points | AJ13: Menlo Park | AK13: Menlo Park
A14: 13 | B14: 90066 | C14: Los Angeles | D14: Los Angeles | E14: Los Angeles County | F14: Mar Vista; Culver Garden; Westdale; Del Rey | G14: Los Angeles, CA | H14: 1163.8054 | I14: SFR | J14: 2137363.5 | K14: 315 | M14: =TRUE() -> TRUE | N14: =IF(H14="","",IF(H14>=Assumptions!$B$5,1,IF(H14>=Assumptions!$B$6,2,IF(H14>=Assumptions!$B$7,3,"")))) -> 1 | O14: =IF(N14=1,Assumptions!$B$8,IF(N14=2,Assumptions!$B$9,IF(N14=3,Assumptions!$B$10,0))) -> 3 | P14: no data | Q14: no data | R14: no data | S14: no data | T14: no data | U14: no data | V14: no data | W14: no data | X14: no data | Y14: =IF(AND(X14="processed",ISNUMBER(S14)),S14*O14,"") | Z14: =IF(ISNUMBER(K14),K14*O14,0) -> 945 | AA14: INTERIM: Redfin SFR sales (12 mo) x tier weight | AB14: 20229 | AC14: 13736 | AD14: 93 | AE14: 1785.4412 | AF14: 1157.8604 | AG14: 0.012843134 | AH14: 1 | AI14: postal city of 100% of address points | AJ14: Los Angeles | AK14: Los Angeles
A15: 14 | B15: 94566 | C15: Pleasanton | D15: Alameda | E15: Berkeley / Oakland / Alameda County | F15: Del Prado; Irby Ranch; Ruby Hill; Shadow Cliffs | G15: Oakland, CA | H15: 817.19279 | I15: SFR | J15: 1860016.4 | K15: 305 | M15: =TRUE() -> TRUE | N15: =IF(H15="","",IF(H15>=Assumptions!$B$5,1,IF(H15>=Assumptions!$B$6,2,IF(H15>=Assumptions!$B$7,3,"")))) -> 1 | O15: =IF(N15=1,Assumptions!$B$8,IF(N15=2,Assumptions!$B$9,IF(N15=3,Assumptions!$B$10,0))) -> 3 | P15: no data | Q15: no data | R15: no data | S15: no data | T15: no data | U15: no data | V15: no data | W15: no data | X15: no data | Y15: =IF(AND(X15="processed",ISNUMBER(S15)),S15*O15,"") | Z15: =IF(ISNUMBER(K15),K15*O15,0) -> 915 | AA15: INTERIM: Redfin SFR sales (12 mo) x tier weight | AB15: 14276 | AC15: 12880 | AD15: 1613 | AE15: 2527.3198 | AF15: 864.45354 | AG15: -0.035685599 | AH15: 1 | AI15: locality polygon (largest overlap) | AK15: Pleasanton
A16: 15 | B16: 90275 | C16: Rancho Palos Verdes | D16: Los Angeles | E16: Los Angeles County | G16: Los Angeles, CA | H16: 789.09299 | I16: SFR | J16: 1885413.9 | K16: 302 | M16: =TRUE() -> TRUE | N16: =IF(H16="","",IF(H16>=Assumptions!$B$5,1,IF(H16>=Assumptions!$B$6,2,IF(H16>=Assumptions!$B$7,3,"")))) -> 1 | O16: =IF(N16=1,Assumptions!$B$8,IF(N16=2,Assumptions!$B$9,IF(N16=3,Assumptions!$B$10,0))) -> 3 | P16: no data | Q16: no data | R16: no data | S16: no data | T16: no data | U16: no data | V16: no data | W16: no data | X16: no data | Y16: =IF(AND(X16="processed",ISNUMBER(S16)),S16*O16,"") | Z16: =IF(ISNUMBER(K16),K16*O16,0) -> 906 | AA16: INTERIM: Redfin SFR sales (12 mo) x tier weight | AB16: 14943 | AC16: 13618 | AD16: 192 | AE16: 2939.3169 | AF16: 767.45465 | AG16: -0.054227908 | AH16: 0.80379325 | AI16: postal city of 100% of address points | AJ16: Rancho Palos Verdes | AK16: Rancho Palos Verdes
A17: 16 | B17: 94568 | C17: Dublin | D17: Alameda | E17: Berkeley / Oakland / Alameda County | G17: Oakland, CA | H17: 730.13592 | I17: SFR | J17: 1573461.3 | K17: 297 | M17: =TRUE() -> TRUE | N17: =IF(H17="","",IF(H17>=Assumptions!$B$5,1,IF(H17>=Assumptions!$B$6,2,IF(H17>=Assumptions!$B$7,3,"")))) -> 1 | O17: =IF(N17=1,Assumptions!$B$8,IF(N17=2,Assumptions!$B$9,IF(N17=3,Assumptions!$B$10,0))) -> 3 | P17: no data | Q17: no data | R17: no data | S17: no data | T17: no data | U17: no data | V17: no data | W17: no data | X17: no data | Y17: =IF(AND(X17="processed",ISNUMBER(S17)),S17*O17,"") | Z17: =IF(ISNUMBER(K17),K17*O17,0) -> 891 | AA17: INTERIM: Redfin SFR sales (12 mo) x tier weight | AB17: 14324 | AC17: 13010 | AD17: 950 | AE17: 2109.5432 | AF17: 691.59316 | AG17: -0.095818594 | AH17: 0.99834932 | AI17: locality polygon (largest overlap) | AK17: Dublin
A18: 17 | B18: 94536 | C18: Fremont | D18: Alameda | E18: Berkeley / Oakland / Alameda County | F18: Centerville District; Niles District; Niles Junction; Shinn | G18: Oakland, CA | H18: 1002.4841 | I18: SFR | J18: 1701938.8 | K18: 294 | M18: =TRUE() -> TRUE | N18: =IF(H18="","",IF(H18>=Assumptions!$B$5,1,IF(H18>=Assumptions!$B$6,2,IF(H18>=Assumptions!$B$7,3,"")))) -> 1 | O18: =IF(N18=1,Assumptions!$B$8,IF(N18=2,Assumptions!$B$9,IF(N18=3,Assumptions!$B$10,0))) -> 3 | P18: no data | Q18: no data | R18: no data | S18: no data | T18: no data | U18: no data | V18: no data | W18: no data | X18: no data | Y18: =IF(AND(X18="processed",ISNUMBER(S18)),S18*O18,"") | Z18: =IF(ISNUMBER(K18),K18*O18,0) -> 882 | AA18: INTERIM: Redfin SFR sales (12 mo) x tier weight | AB18: 20813 | AC18: 17549 | AD18: 97 | AE18: 2348.4919 | AF18: 991.73554 | AG18: -0.053512397 | AH18: 1 | AI18: locality polygon (largest overlap) | AK18: Fremont
A19: 18 | B19: 90808 | C19: Long Beach | D19: Los Angeles | E19: Los Angeles County | G19: Los Angeles, CA | H19: 716.19567 | I19: SFR | J19: 1068413.8 | K19: 290 | M19: =TRUE() -> TRUE | N19: =IF(H19="","",IF(H19>=Assumptions!$B$5,1,IF(H19>=Assumptions!$B$6,2,IF(H19>=Assumptions!$B$7,3,"")))) -> 1 | O19: =IF(N19=1,Assumptions!$B$8,IF(N19=2,Assumptions!$B$9,IF(N19=3,Assumptions!$B$10,0))) -> 3 | P19: no data | Q19: no data | R19: no data | S19: no data | T19: no data | U19: no data | V19: no data | W19: no data | X19: no data | Y19: =IF(AND(X19="processed",ISNUMBER(S19)),S19*O19,"") | Z19: =IF(ISNUMBER(K19),K19*O19,0) -> 870 | AA19: INTERIM: Redfin SFR sales (12 mo) x tier weight | AB19: 21868 | AC19: 15489 | AD19: 173 | AE19: 1964.3456 | AF19: 709.59159 | AG19: -0.086511294 | AH19: 0.99960364 | AI19: postal city of 100% of address points | AJ19: Long Beach | AK19: Long Beach
A20: 19 | B20: 92037 | C20: La Jolla | D20: San Diego | E20: San Diego | F20: La Jolla; Biology Field Station; Campus Services Complex; Earl Warren College; Eleanor Roosevelt College; John Muir College; Lower Hermosa; Miurlands West; Mount La Jolla; North Campus; Pepper Canyon; Revelle College; Ridge Walk North Living and Learning Neighborhood; Ridgegate; Science Research Park; Seventh College at the Village; Sixth College; Thurgood Marshall College; University Center; Upper Hermosa; Windansea Beach; Windemere; Beach Barber Tract; Bird Rock; Executive Square; Golden Triangle; Hidden Valley; Katzin Courtyard; La Jolla Alta; La Jolla Country Club; La Jolla Farms; La Jolla Heights; La Jolla Hermosa; La Jolla Mesa; La Jolla Shores; La Jolla Village; Matthews Quadrangle; Soledad South; The Muirlands; Village of La Jolla | G20: San Diego, CA | H20: 1361.8037 | I20: SFR | J20: 3616364.4 | K20: 284 | M20: =TRUE() -> TRUE | N20: =IF(H20="","",IF(H20>=Assumptions!$B$5,1,IF(H20>=Assumptions!$B$6,2,IF(H20>=Assumptions!$B$7,3,"")))) -> 1 | O20: =IF(N20=1,Assumptions!$B$8,IF(N20=2,Assumptions!$B$9,IF(N20=3,Assumptions!$B$10,0))) -> 3 | P20: no data | Q20: no data | R20: no data | S20: no data | T20: no data | U20: no data | V20: no data | W20: no data | X20: no data | Y20: =IF(AND(X20="processed",ISNUMBER(S20)),S20*O20,"") | Z20: =IF(ISNUMBER(K20),K20*O20,0) -> 852 | AA20: INTERIM: Redfin SFR sales (12 mo) x tier weight | AB20: 14975 | AC20: 11792 | AD20: 388 | AE20: 2963.929 | AF20: 1372.7698 | AG20: 0.065571199 | AH20: 0.9022674 | AI20: postal city of 100% of address points | AJ20: La Jolla | AK20: San Diego
A21: 20 | B21: 95120 | C21: San Jose | D21: Santa Clara | E21: Peninsula & South Bay (Santa Clara / San Mateo) | F21: Almaden Valley | G21: San Jose, CA | H21: 1003.0732 | I21: SFR | J21: 2322145.4 | K21: 282 | M21: =TRUE() -> TRUE | N21: =IF(H21="","",IF(H21>=Assumptions!$B$5,1,IF(H21>=Assumptions!$B$6,2,IF(H21>=Assumptions!$B$7,3,"")))) -> 1 | O21: =IF(N21=1,Assumptions!$B$8,IF(N21=2,Assumptions!$B$9,IF(N21=3,Assumptions!$B$10,0))) -> 3 | P21: no data | Q21: no data | R21: no data | S21: no data | T21: no data | U21: no data | V21: no data | W21: no data | X21: no data | Y21: =IF(AND(X21="processed",ISNUMBER(S21)),S21*O21,"") | Z21: =IF(ISNUMBER(K21),K21*O21,0) -> 846 | AA21: INTERIM: Redfin SFR sales (12 mo) x tier weight | AB21: 17646 | AC21: 12737 | AD21: 638 | AE21: 2787.3027 | AF21: 1039.268 | AG21: -0.016310202 | AH21: 1 | AI21: postal city of 100% of address points | AJ21: San Jose | AK21: San Jose
A22: 21 | B22: 92009 | C22: Carlsbad | D22: San Diego | E22: San Diego | F22: La Costa; Bressi Ranch; La Costa Greens; La Costa Oaks; La Costa Ridge; La Costa Valley; Rancho Carrillo | G22: San Diego, CA | H22: 705.44022 | I22: SFR | J22: 1852998.2 | K22: 281 | M22: =TRUE() -> TRUE | N22: =IF(H22="","",IF(H22>=Assumptions!$B$5,1,IF(H22>=Assumptions!$B$6,2,IF(H22>=Assumptions!$B$7,3,"")))) -> 1 | O22: =IF(N22=1,Assumptions!$B$8,IF(N22=2,Assumptions!$B$9,IF(N22=3,Assumptions!$B$10,0))) -> 3 | P22: no data | Q22: no data | R22: no data | S22: no data | T22: no data | U22: no data | V22: no data | W22: no data | X22: no data | Y22: =IF(AND(X22="processed",ISNUMBER(S22)),S22*O22,"") | Z22: =IF(ISNUMBER(K22),K22*O22,0) -> 843 | AA22: INTERIM: Redfin SFR sales (12 mo) x tier weight | AB22: 13786 | AC22: 12308 | AD22: 155 | AE22: 2809.7068 | AF22: 704.18698 | AG22: -0.037496793 | AH22: 0.98988361 | AI22: postal city of 100% of address points | AJ22: Carlsbad | AK22: Carlsbad
A23: 22 | B23: 94941 | C23: Mill Valley | D23: Marin | E23: Marin | F23: Almonte | G23: San Rafael, CA | H23: 1083.9878 | I23: SFR | J23: 2277544.8 | K23: 279 | M23: =TRUE() -> TRUE | N23: =IF(H23="","",IF(H23>=Assumptions!$B$5,1,IF(H23>=Assumptions!$B$6,2,IF(H23>=Assumptions!$B$7,3,"")))) -> 1 | O23: =IF(N23=1,Assumptions!$B$8,IF(N23=2,Assumptions!$B$9,IF(N23=3,Assumptions!$B$10,0))) -> 3 | P23: no data | Q23: no data | R23: no data | S23: no data | T23: no data | U23: no data | V23: no data | W23: no data | X23: no data | Y23: =IF(AND(X23="processed",ISNUMBER(S23)),S23*O23,"") | Z23: =IF(ISNUMBER(K23),K23*O23,0) -> 837 | AA23: INTERIM: Redfin SFR sales (12 mo) x tier weight | AB23: 14418 | AC23: 11097 | AD23: 329 | AE23: 1839.2679 | AF23: 1123.1884 | AG23: 0.04435088 | AH23: 0.96647119 | AI23: postal city of 100% of address points | AJ23: Mill Valley | AK23: Mill Valley
A24: 23 | B24: 92129 | C24: San Diego | D24: San Diego | E24: San Diego | F24: Rancho Peñasquitos; Torrey Highlands; Greystone Torrey Highlands; Penasquitos Creek; Rhodes Crossing; Rolling Hills; Sun Ridge Vista; Terramar; Torrey Glenn; Torrey Ranch; Adobe Bluffs; Canyon Hills; Heritage Bluffs; Merge 56; Park Village; Penasquitos Village; Peñasquitos Point; Rancho Peñasquitos Town Center; Ridgewood; Sunset Hills; Torrey Del Mar; Torrey Meadows; Torrey Santa Fe; Twin Trails | G24: San Diego, CA | H24: 704.04314 | I24: SFR | J24: 1376469.3 | K24: 277 | M24: =TRUE() -> TRUE | N24: =IF(H24="","",IF(H24>=Assumptions!$B$5,1,IF(H24>=Assumptions!$B$6,2,IF(H24>=Assumptions!$B$7,3,"")))) -> 1 | O24: =IF(N24=1,Assumptions!$B$8,IF(N24=2,Assumptions!$B$9,IF(N24=3,Assumptions!$B$10,0))) -> 3 | P24: no data | Q24: no data | R24: no data | S24: no data | T24: no data | U24: no data | V24: no data | W24: no data | X24: no data | Y24: =IF(AND(X24="processed",ISNUMBER(S24)),S24*O24,"") | Z24: =IF(ISNUMBER(K24),K24*O24,0) -> 831 | AA24: INTERIM: Redfin SFR sales (12 mo) x tier weight | AB24: 14991 | AC24: 14004 | AD24: 2541 | AE24: 2353.5459 | AF24: 740.04671 | AG24: -0.011827258 | AH24: 1 | AI24: postal city of 100% of address points | AJ24: San Diego | AK24: San Diego
A25: 24 | B25: 90815 | C25: Long Beach | D25: Los Angeles | E25: Los Angeles County | F25: Los Altos | G25: Los Angeles, CA | H25: 736.42722 | I25: SFR | J25: 1136425.5 | K25: 275 | M25: =TRUE() -> TRUE | N25: =IF(H25="","",IF(H25>=Assumptions!$B$5,1,IF(H25>=Assumptions!$B$6,2,IF(H25>=Assumptions!$B$7,3,"")))) -> 1 | O25: =IF(N25=1,Assumptions!$B$8,IF(N25=2,Assumptions!$B$9,IF(N25=3,Assumptions!$B$10,0))) -> 3 | P25: no data | Q25: no data | R25: no data | S25: no data | T25: no data | U25: no data | V25: no data | W25: no data | X25: no data | Y25: =IF(AND(X25="processed",ISNUMBER(S25)),S25*O25,"") | Z25: =IF(ISNUMBER(K25),K25*O25,0) -> 825 | AA25: INTERIM: Redfin SFR sales (12 mo) x tier weight | AB25: 18313 | AC25: 13177 | AD25: 127 | AE25: 2100.2444 | AF25: 767.89838 | AG25: 0.12549254 | AH25: 0.99850212 | AI25: postal city of 100% of address points | AJ25: Long Beach | AK25: Long Beach
A26: 25 | B26: 90049 | C26: Los Angeles | D26: Los Angeles | E26: Los Angeles County | F26: Brentwood; Brentwood Glen; Brentwood Heights; Brentwood Park; Brentwood Village; Westgate Heights; Republic of Artsakh Square | G26: Los Angeles, CA | H26: 1323.402 | I26: SFR | J26: 4033362.6 | K26: 273 | M26: =TRUE() -> TRUE | N26: =IF(H26="","",IF(H26>=Assumptions!$B$5,1,IF(H26>=Assumptions!$B$6,2,IF(H26>=Assumptions!$B$7,3,"")))) -> 1 | O26: =IF(N26=1,Assumptions!$B$8,IF(N26=2,Assumptions!$B$9,IF(N26=3,Assumptions!$B$10,0))) -> 3 | P26: no data | Q26: no data | R26: no data | S26: no data | T26: no data | U26: no data | V26: no data | W26: no data | X26: no data | Y26: =IF(AND(X26="processed",ISNUMBER(S26)),S26*O26,"") | Z26: =IF(ISNUMBER(K26),K26*O26,0) -> 819 | AA26: INTERIM: Redfin SFR sales (12 mo) x tier weight | AB26: 11865 | AC26: 8963 | AD26: 185 | AE26: 3101.5984 | AF26: 1284.9162 | AG26: -0.03792536 | AH26: 1 | AI26: postal city of 100% of address points | AJ26: Los Angeles | AK26: Los Angeles
A27: 26 | B27: 94549 | C27: Lafayette | D27: Contra Costa | E27: Rest of California | F27: Burton Valley; Reliez Valley | G27: Oakland, CA | H27: 827.75787 | I27: SFR | J27: 2055615.7 | K27: 268 | M27: =TRUE() -> TRUE | N27: =IF(H27="","",IF(H27>=Assumptions!$B$5,1,IF(H27>=Assumptions!$B$6,2,IF(H27>=Assumptions!$B$7,3,"")))) -> 1 | O27: =IF(N27=1,Assumptions!$B$8,IF(N27=2,Assumptions!$B$9,IF(N27=3,Assumptions!$B$10,0))) -> 3 | P27: no data | Q27: no data | R27: no data | S27: no data | T27: no data | U27: no data | V27: no data | W27: no data | X27: no data | Y27: =IF(AND(X27="processed",ISNUMBER(S27)),S27*O27,"") | Z27: =IF(ISNUMBER(K27),K27*O27,0) -> 804 | AA27: INTERIM: Redfin SFR sales (12 mo) x tier weight | AB27: 10986 | AC27: 9858 | AD27: 9532 | AE27: 3016.2686 | AF27: 846.5198 | AG27: -0.058195321 | AH27: 1 | AI27: postal city of 100% of address points | AJ27: Lafayette | AK27: Lafayette
A28: 27 | B28: 92651 | C28: Laguna Beach | D28: Orange | E28: Orange County | F28: Emerald Bay | G28: Anaheim, CA | H28: 1545.4744 | I28: SFR | J28: 3121949.1 | K28: 265 | M28: =TRUE() -> TRUE | N28: =IF(H28="","",IF(H28>=Assumptions!$B$5,1,IF(H28>=Assumptions!$B$6,2,IF(H28>=Assumptions!$B$7,3,"")))) -> 1 | O28: =IF(N28=1,Assumptions!$B$8,IF(N28=2,Assumptions!$B$9,IF(N28=3,Assumptions!$B$10,0))) -> 3 | P28: no data | Q28: no data | R28: no data | S28: no data | T28: no data | U28: no data | V28: no data | W28: no data | X28: no data | Y28: =IF(AND(X28="processed",ISNUMBER(S28)),S28*O28,"") | Z28: =IF(ISNUMBER(K28),K28*O28,0) -> 795 | AA28: INTERIM: Redfin SFR sales (12 mo) x tier weight | AB28: 12290 | AC28: 10871 | AD28: 222 | AE28: 2074.5979 | AF28: 1541.6263 | AG28: -0.056773413 | AH28: 0.87800533 | AI28: postal city of 99% of address points | AJ28: Laguna Beach | AK28: Laguna Beach
A29: 28 | B29: 94070 | C29: San Carlos | D29: San Mateo | E29: Peninsula & South Bay (Santa Clara / San Mateo) | F29: Devonshire | G29: San Francisco, CA | H29: 1389.7012 | I29: SFR | J29: 2696220.8 | K29: 265 | M29: =TRUE() -> TRUE | N29: =IF(H29="","",IF(H29>=Assumptions!$B$5,1,IF(H29>=Assumptions!$B$6,2,IF(H29>=Assumptions!$B$7,3,"")))) -> 1 | O29: =IF(N29=1,Assumptions!$B$8,IF(N29=2,Assumptions!$B$9,IF(N29=3,Assumptions!$B$10,0))) -> 3 | P29: no data | Q29: no data | R29: no data | S29: no data | T29: no data | U29: no data | V29: no data | W29: no data | X29: no data | Y29: =IF(AND(X29="processed",ISNUMBER(S29)),S29*O29,"") | Z29: =IF(ISNUMBER(K29),K29*O29,0) -> 795 | AA29: INTERIM: Redfin SFR sales (12 mo) x tier weight | AB29: 11614 | AC29: 9901 | AD29: 134 | AE29: 2264.7549 | AF29: 1447.9167 | AG29: -0.064509352 | AH29: 0.99905451 | AI29: postal city of 99% of address points | AJ29: San Carlos | AK29: San Carlos
A30: 29 | B30: 95127 | C30: San Jose | D30: Santa Clara | E30: Peninsula & South Bay (Santa Clara / San Mateo) | F30: Alum Rock | G30: San Jose, CA | H30: 795.73846 | I30: SFR | J30: 1173622.6 | K30: 265 | M30: =TRUE() -> TRUE | N30: =IF(H30="","",IF(H30>=Assumptions!$B$5,1,IF(H30>=Assumptions!$B$6,2,IF(H30>=Assumptions!$B$7,3,"")))) -> 1 | O30: =IF(N30=1,Assumptions!$B$8,IF(N30=2,Assumptions!$B$9,IF(N30=3,Assumptions!$B$10,0))) -> 3 | P30: no data | Q30: no data | R30: no data | S30: no data | T30: no data | U30: no data | V30: no data | W30: no data | X30: no data | Y30: =IF(AND(X30="processed",ISNUMBER(S30)),S30*O30,"") | Z30: =IF(ISNUMBER(K30),K30*O30,0) -> 795 | AA30: INTERIM: Redfin SFR sales (12 mo) x tier weight | AB30: 19790 | AC30: 15146 | AD30: 1356 | AE30: 2118.6934 | AF30: 855.48492 | AG30: -0.029898979 | AH30: 1 | AI30: postal city of 100% of address points | AJ30: San Jose | AK30: San Jose
A31: 30 | B31: 94087 | C31: Sunnyvale | D31: Santa Clara | E31: Peninsula & South Bay (Santa Clara / San Mateo) | F31: Birdland | G31: San Jose, CA | H31: 1663.5655 | I31: SFR | J31: 2974583.3 | K31: 264 | M31: =TRUE() -> TRUE | N31: =IF(H31="","",IF(H31>=Assumptions!$B$5,1,IF(H31>=Assumptions!$B$6,2,IF(H31>=Assumptions!$B$7,3,"")))) -> 1 | O31: =IF(N31=1,Assumptions!$B$8,IF(N31=2,Assumptions!$B$9,IF(N31=3,Assumptions!$B$10,0))) -> 3 | P31: no data | Q31: no data | R31: no data | S31: no data | T31: no data | U31: no data | V31: no data | W31: no data | X31: no data | Y31: =IF(AND(X31="processed",ISNUMBER(S31)),S31*O31,"") | Z31: =IF(ISNUMBER(K31),K31*O31,0) -> 792 | AA31: INTERIM: Redfin SFR sales (12 mo) x tier weight | AB31: 16013 | AC31: 14159 | AD31: 352 | AE31: 2598.8044 | AF31: 1700.5137 | AG31: 0.003999641 | AH31: 1 | AI31: postal city of 100% of address points | AJ31: Sunnyvale | AK31: Sunnyvale
... A36: 35 | B36: 94110 | C36: San Francisco | D36: San Francisco | E36: San Francisco | F36: Mission; Bernal Heights | G36: San Francisco, CA | H36: 1088.6932 | I36: SFR | J36: 1544831.4 | K36: 258 | M36: =TRUE() -> TRUE | N36: =IF(H36="","",IF(H36>=Assumptions!$B$5,1,IF(H36>=Assumptions!$B$6,2,IF(H36>=Assumptions!$B$7,3,"")))) -> 1 | O36: =IF(N36=1,Assumptions!$B$8,IF(N36=2,Assumptions!$B$9,IF(N36=3,Assumptions!$B$10,0))) -> 3 | P36: no data | Q36: no data | R36: no data | S36: no data | T36: no data | U36: no data | V36: no data | W36: no data | X36: no data | Y36: =IF(AND(X36="processed",ISNUMBER(S36)),S36*O36,"") | Z36: =IF(ISNUMBER(K36),K36*O36,0) -> 774 | AA36: INTERIM: Redfin SFR sales (12 mo) x tier weight | AB36: 13215 | AC36: 12201 | AD36: 124 | AE36: 1283.7965 | AF36: 1270.6044 | AG36: 0.17144305 | AH36: 1 | AI36: postal city of 100% of address points | AJ36: San Francisco | AK36: San Francisco
A37: 36 | B37: 94611 | C37: Oakland | D37: Alameda | E37: Berkeley / Oakland / Alameda County | F37: Broadway Auto Row; Harrison/Oakland; Montclair; Oak Glen Park; Piedmont Avenue; Piedmont Pines; Westlake | G37: Oakland, CA | H37: 686.28151 | I37: SFR | J37: 1441336.8 | K37: 386 | M37: =TRUE() -> TRUE | N37: =IF(H37="","",IF(H37>=Assumptions!$B$5,1,IF(H37>=Assumptions!$B$6,2,IF(H37>=Assumptions!$B$7,3,"")))) -> 2 | O37: =IF(N37=1,Assumptions!$B$8,IF(N37=2,Assumptions!$B$9,IF(N37=3,Assumptions!$B$10,0))) -> 2 | P37: no data | Q37: no data | R37: no data | S37: no data | T37: no data | U37: no data | V37: no data | W37: no data | X37: no data | Y37: =IF(AND(X37="processed",ISNUMBER(S37)),S37*O37,"") | Z37: =IF(ISNUMBER(K37),K37*O37,0) -> 772 | AA37: INTERIM: Redfin SFR sales (12 mo) x tier weight | AB37: 14504 | AC37: 12003 | AD37: 222 | AE37: 1859.3853 | AF37: 746.78282 | AG37: 0.050811815 | AH37: 0.69565794 | AI37: locality polygon (largest overlap) | AK37: Oakland
A38: 37 | B38: 94560 | C38: Newark | D38: Alameda | E38: Berkeley / Oakland / Alameda County | G38: Oakland, CA | H38: 837.30364 | I38: SFR | J38: 1415045.1 | K38: 255 | M38: =TRUE() -> TRUE | N38: =IF(H38="","",IF(H38>=Assumptions!$B$5,1,IF(H38>=Assumptions!$B$6,2,IF(H38>=Assumptions!$B$7,3,"")))) -> 1 | O38: =IF(N38=1,Assumptions!$B$8,IF(N38=2,Assumptions!$B$9,IF(N38=3,Assumptions!$B$10,0))) -> 3 | P38: no data | Q38: no data | R38: no data | S38: no data | T38: no data | U38: no data | V38: no data | W38: no data | X38: no data | Y38: =IF(AND(X38="processed",ISNUMBER(S38)),S38*O38,"") | Z38: =IF(ISNUMBER(K38),K38*O38,0) -> 765 | AA38: INTERIM: Redfin SFR sales (12 mo) x tier weight | AB38: 13771 | AC38: 12732 | AD38: 379 | AE38: 2171.5312 | AF38: 860.50984 | AG38: -0.039838664 | AH38: 0.97684247 | AI38: locality polygon (largest overlap) | AK38: Newark
A39: 38 | B39: 92660 | C39: Newport Beach | D39: Orange | E39: Orange County | F39: UCI - North Campus; Bayside Village; Belcourt; Castaways; Granville; Harbor Cove; Harbor Hill; Harbor View Knoll; Island Lagoon; Newport Hills; Newport North; North Bluff; One Ford Road; Sea View; Seawind; The Bluffs; The Plaza; Villa Point; Big Canyon; Bonita Canyon; Dover Shores; Eastbluff; Harbor Island; Harbor Ridge; Harbor View; Newport Ridge; Upper Bay | G39: Anaheim, CA | H39: 1380.84 | I39: SFR | J39: 3893911.4 | K39: 254 | M39: =TRUE() -> TRUE | N39: =IF(H39="","",IF(H39>=Assumptions!$B$5,1,IF(H39>=Assumptions!$B$6,2,IF(H39>=Assumptions!$B$7,3,"")))) -> 1 | O39: =IF(N39=1,Assumptions!$B$8,IF(N39=2,Assumptions!$B$9,IF(N39=3,Assumptions!$B$10,0))) -> 3 | P39: no data | Q39: no data | R39: no data | S39: no data | T39: no data | U39: no data | V39: no data | W39: no data | X39: no data | Y39: =IF(AND(X39="processed",ISNUMBER(S39)),S39*O39,"") | Z39: =IF(ISNUMBER(K39),K39*O39,0) -> 762 | AA39: INTERIM: Redfin SFR sales (12 mo) x tier weight | AB39: 11926 | AC39: 10170 | AD39: 359 | AE39: 2954.4165 | AF39: 1478.8724 | AG39: 0.047389643 | AH39: 1 | AI39: postal city of 100% of address points | AJ39: Newport Beach | AK39: Newport Beach
A40: 39 | B40: 92127 | C40: San Diego | D40: San Diego | E40: San Diego | F40: Black Mountain Ranch; 4S Commons; Auberge; Bel Etage; Camino Bernardo; Deer Ridge; Dove Canyon; Ivygate; Nicole Ridge; Paseo Montenero; Stone Ranch; Tanner Ridge; Verrazano; Village Green; 4S Ranch Business Park; Del Sur; North 4S Ranch; Rancho Bernardo Business Park; Santaluz; South 4S Ranch; Westwood | G40: San Diego, CA | H40: 713.32127 | I40: SFR | J40: 2127369 | K40: 252 | M40: =TRUE() -> TRUE | N40: =IF(H40="","",IF(H40>=Assumptions!$B$5,1,IF(H40>=Assumptions!$B$6,2,IF(H40>=Assumptions!$B$7,3,"")))) -> 1 | O40: =IF(N40=1,Assumptions!$B$8,IF(N40=2,Assumptions!$B$9,IF(N40=3,Assumptions!$B$10,0))) -> 3 | P40: no data | Q40: no data | R40: no data | S40: no data | T40: no data | U40: no data | V40: no data | W40: no data | X40: no data | Y40: =IF(AND(X40="processed",ISNUMBER(S40)),S40*O40,"") | Z40: =IF(ISNUMBER(K40),K40*O40,0) -> 756 | AA40: INTERIM: Redfin SFR sales (12 mo) x tier weight | AB40: 14157 | AC40: 11513 | AD40: 471 | AE40: 2641.4402 | AF40: 728.29132 | AG40: -0.015384016 | AH40: 1 | AI40: postal city of 100% of address points | AJ40: San Diego | AK40: San Diego
A41: 40 | B41: 92064 | C41: Poway | D41: San Diego | E41: San Diego | F41: Bridlewood; Bridlewood Country Estates; Bridlewood Lakeside; Carriage Heights; Casa Real Poway; Cicero; Colony; Country Squire Estates; Cree; Espola Verde; Flair; Gate; Golden City; Green Valley Estates North; Green Valley Estates South; Green Valley Summit; Hickory; Holiday Estates; Holland; Huntington Gate; Kentfield; La Paz Village; Ladera Piedra; Las Cadenas; Midland Estates; Midland Grove; Norwalk; O'Reno; Padre Woods; Parkway Business Centre; Piermont; Pomerado Business Park; Pomerado Gardens; Poway Corporate Center; Poway Grove Park; Poway Mesa North; Poway Mesa South; Poway Portals; Poway Woods; Rancho Arbolitos Palisades; Rancho Arbolitos Parkside; Rancho Arbolitos Woodside; Rancho La Paz; Rancho Poway; Rancho Verde; Range View Estates; Rayo Del Sol; Rollin Glen; Stone Canyon Ranch; Stoneridge Chateaus; Summerfield Estates; Sunrise Ranch; Sycamore Creek; Taunt; Temple; The Grove; The Ranch; Twin Circle; Valle Del Norte; Valle Verde Estates; Avocado Glen; Green Valley; Old Coach; Old Poway; Poway Town Center; Rancho Arbolitos; South Poway Business Park; Twin Peaks | G41: San Diego, CA | H41: 641.68389 | I41: SFR | J41: 1304946.7 | K41: 375 | M41: =TRUE() -> TRUE | N41: =IF(H41="","",IF(H41>=Assumptions!$B$5,1,IF(H41>=Assumptions!$B$6,2,IF(H41>=Assumptions!$B$7,3,"")))) -> 2 | O41: =IF(N41=1,Assumptions!$B$8,IF(N41=2,Assumptions!$B$9,IF(N41=3,Assumptions!$B$10,0))) -> 2 | P41: no data | Q41: no data | R41: no data | S41: no data | T41: no data | U41: no data | V41: no data | W41: no data | X41: no data | Y41: =IF(AND(X41="processed",ISNUMBER(S41)),S41*O41,"") | Z41: =IF(ISNUMBER(K41),K41*O41,0) -> 750 | AA41: INTERIM: Redfin SFR sales (12 mo) x tier weight | AB41: 21277 | AC41: 15442 | AD41: 614 | AE41: 2588.7258 | AF41: 651.72591 | AG41: -0.03252838 | AH41: 1 | AI41: postal city of 100% of address points | AJ41: Poway | AK41: Poway
A42: 41 | B42: 92679 | C42: Rancho Santa Margarita | D42: Orange | E42: Orange County | F42: Dove Canyon; Portola Hills; Robinson Ranch | G42: Anaheim, CA | H42: 631.13114 | I42: SFR | J42: 1707626.7 | K42: 375 | M42: =TRUE() -> TRUE | N42: =IF(H42="","",IF(H42>=Assumptions!$B$5,1,IF(H42>=Assumptions!$B$6,2,IF(H42>=Assumptions!$B$7,3,"")))) -> 2 | O42: =IF(N42=1,Assumptions!$B$8,IF(N42=2,Assumptions!$B$9,IF(N42=3,Assumptions!$B$10,0))) -> 2 | P42: no data | Q42: no data | R42: no data | S42: no data | T42: no data | U42: no data | V42: no data | W42: no data | X42: no data | Y42: =IF(AND(X42="processed",ISNUMBER(S42)),S42*O42,"") | Z42: =IF(ISNUMBER(K42),K42*O42,0) -> 750 | AA42: INTERIM: Redfin SFR sales (12 mo) x tier weight | AB42: 10868 | AC42: 9921 | AD42: 125 | AE42: 2672.9153 | AF42: 637.39377 | AG42: -0.0042028514 | AH42: 1 | AI42: locality polygon (largest overlap) | AK42: Rancho Santa Margarita
A43: 42 | B43: 90068 | C43: Los Angeles | D43: Los Angeles | E43: Los Angeles County | F43: Beachwood Canyon; Hollywood Dell; Whitley Heights Historic District; Hollywood Hills | G43: Los Angeles, CA | H43: 870.9198 | I43: SFR | J43: 1959068.5 | K43: 248 | M43: =TRUE() -> TRUE | N43: =IF(H43="","",IF(H43>=Assumptions!$B$5,1,IF(H43>=Assumptions!$B$6,2,IF(H43>=Assumptions!$B$7,3,"")))) -> 1 | O43: =IF(N43=1,Assumptions!$B$8,IF(N43=2,Assumptions!$B$9,IF(N43=3,Assumptions!$B$10,0))) -> 3 | P43: no data | Q43: no data | R43: no data | S43: no data | T43: no data | U43: no data | V43: no data | W43: no data | X43: no data | Y43: =IF(AND(X43="processed",ISNUMBER(S43)),S43*O43,"") | Z43: =IF(ISNUMBER(K43),K43*O43,0) -> 744 | AA43: INTERIM: Redfin SFR sales (12 mo) x tier weight | AB43: 9105 | AC43: 7217 | AD43: 200 | AE43: 1975.3351 | AF43: 861.18252 | AG43: -0.082157766 | AH43: 1 | AI43: postal city of 100% of address points | AJ43: Los Angeles | AK43: Los Angeles
A44: 43 | B44: 95037 | C44: Morgan Hill | D44: Santa Clara | E44: Peninsula & South Bay (Santa Clara / San Mateo) | G44: San Jose, CA | H44: 660.69466 | I44: SFR | J44: 1471168 | K44: 372 | M44: =TRUE() -> TRUE | N44: =IF(H44="","",IF(H44>=Assumptions!$B$5,1,IF(H44>=Assumptions!$B$6,2,IF(H44>=Assumptions!$B$7,3,"")))) -> 2 | O44: =IF(N44=1,Assumptions!$B$8,IF(N44=2,Assumptions!$B$9,IF(N44=3,Assumptions!$B$10,0))) -> 2 | P44: no data | Q44: no data | R44: no data | S44: no data | T44: no data | U44: no data | V44: no data | W44: no data | X44: no data | Y44: =IF(AND(X44="processed",ISNUMBER(S44)),S44*O44,"") | Z44: =IF(ISNUMBER(K44),K44*O44,0) -> 744 | AA44: INTERIM: Redfin SFR sales (12 mo) x tier weight | AB44: 21407 | AC44: 17622 | AD44: 1801 | AE44: 2246.8826 | AF44: 673.07692 | AG44: 0.0045317221 | AH44: 0.99825094 | AI44: postal city of 100% of address points | AJ44: Morgan Hill | AK44: San Jose
A45: 44 | B45: 90210 | C45: Beverly Hills | D45: Los Angeles | E45: Los Angeles County | F45: The Flats; Trousdale Estates; Beverly Crest | G45: Los Angeles, CA | H45: 1275.3541 | I45: SFR | J45: 5961425.1 | K45: 247 | M45: =TRUE() -> TRUE | N45: =IF(H45="","",IF(H45>=Assumptions!$B$5,1,IF(H45>=Assumptions!$B$6,2,IF(H45>=Assumptions!$B$7,3,"")))) -> 1 | O45: =IF(N45=1,Assumptions!$B$8,IF(N45=2,Assumptions!$B$9,IF(N45=3,Assumptions!$B$10,0))) -> 3 | P45: no data | Q45: no data | R45: no data | S45: no data | T45: no data | U45: no data | V45: no data | W45: no data | X45: no data | Y45: =IF(AND(X45="processed",ISNUMBER(S45)),S45*O45,"") | Z45: =IF(ISNUMBER(K45),K45*O45,0) -> 741 | AA45: INTERIM: Redfin SFR sales (12 mo) x tier weight | AB45: 11017 | AC45: 7693 | AD45: 221 | AE45: 3102.2068 | AF45: 1447.9215 | AG45: 0.027307495 | AH45: 1 | AI45: postal city of 100% of address points | AJ45: Beverly Hills | AK45: Los Angeles
A46: 45 | B46: 92626 | C46: Costa Mesa | D46: Orange | E46: Orange County | F46: College Park; Mesa Verde | G46: Anaheim, CA | H46: 888.08112 | I46: SFR | J46: 1588421.1 | K46: 247 | M46: =TRUE() -> TRUE | N46: =IF(H46="","",IF(H46>=Assumptions!$B$5,1,IF(H46>=Assumptions!$B$6,2,IF(H46>=Assumptions!$B$7,3,"")))) -> 1 | O46: =IF(N46=1,Assumptions!$B$8,IF(N46=2,Assumptions!$B$9,IF(N46=3,Assumptions!$B$10,0))) -> 3 | P46: no data | Q46: no data | R46: no data | S46: no data | T46: no data | U46: no data | V46: no data | W46: no data | X46: no data | Y46: =IF(AND(X46="processed",ISNUMBER(S46)),S46*O46,"") | Z46: =IF(ISNUMBER(K46),K46*O46,0) -> 741 | AA46: INTERIM: Redfin SFR sales (12 mo) x tier weight | AB46: 12760 | AC46: 10960 | AD46: 311 | AE46: 2591.3262 | AF46: 925.47236 | AG46: 0.066361353 | AH46: 1 | AI46: postal city of 100% of address points | AJ46: Costa Mesa | AK46: Costa Mesa
A47: 46 | B47: 94587 | C47: Union City | D47: Alameda | E47: Berkeley / Oakland / Alameda County | F47: Alvarado; Decoto; Contempo; Colt Court | G47: Oakland, CA | H47: 814.84483 | I47: SFR | J47: 1383502 | K47: 247 | M47: =TRUE() -> TRUE | N47: =IF(H47="","",IF(H47>=Assumptions!$B$5,1,IF(H47>=Assumptions!$B$6,2,IF(H47>=Assumptions!$B$7,3,"")))) -> 1 | O47: =IF(N47=1,Assumptions!$B$8,IF(N47=2,Assumptions!$B$9,IF(N47=3,Assumptions!$B$10,0))) -> 3 | P47: no data | Q47: no data | R47: no data | S47: no data | T47: no data | U47: no data | V47: no data | W47: no data | X47: no data | Y47: =IF(AND(X47="processed",ISNUMBER(S47)),S47*O47,"") | Z47: =IF(ISNUMBER(K47),K47*O47,0) -> 741 | AA47: INTERIM: Redfin SFR sales (12 mo) x tier weight | AB47: 17260 | AC47: 16062 | AD47: 1028 | AE47: 2220.0244 | AF47: 799.79879 | AG47: -0.048315062 | AH47: 1 | AI47: locality polygon (largest overlap) | AK47: Union City
A48: 47 | B48: 90274 | C48: Palos Verdes Peninsula | D48: Los Angeles | E48: Los Angeles County | F48: Palos Verdes Estates; Rolling Hills; Rolling Hills Estates | G48: Los Angeles, CA | H48: 975.8403 | I48: SFR | J48: 2669432.9 | K48: 246 | M48: =TRUE() -> TRUE | N48: =IF(H48="","",IF(H48>=Assumptions!$B$5,1,IF(H48>=Assumptions!$B$6,2,IF(H48>=Assumptions!$B$7,3,"")))) -> 1 | O48: =IF(N48=1,Assumptions!$B$8,IF(N48=2,Assumptions!$B$9,IF(N48=3,Assumptions!$B$10,0))) -> 3 | P48: no data | Q48: no data | R48: no data | S48: no data | T48: no data | U48: no data | V48: no data | W48: no data | X48: no data | Y48: =IF(AND(X48="processed",ISNUMBER(S48)),S48*O48,"") | Z48: =IF(ISNUMBER(K48),K48*O48,0) -> 738 | AA48: INTERIM: Redfin SFR sales (12 mo) x tier weight | AB48: 11717 | AC48: 9742 | AD48: 276 | AE48: 3011.5574 | AF48: 1009.9926 | AG48: -0.034256634 | AH48: 0.91185097 | AI48: postal city of 100% of address points | AJ48: Palos Verdes Peninsula | AK48: Palos Verdes Estates
A49: 48 | B49: 94526 | C49: Danville | D49: Contra Costa | E49: Rest of California | F49: Anderson Ranch; Brookview; California Chateau; Crow Canyon Heights; Danville Ranch; Diablo Highlands; Diablo West; Osborn Estates; Sycamore Creek; Sycamore Homes; Windstream | G49: Oakland, CA | H49: 818.4109 | I49: SFR | J49: 1889532.5 | K49: 246 | M49: =TRUE() -> TRUE | N49: =IF(H49="","",IF(H49>=Assumptions!$B$5,1,IF(H49>=Assumptions!$B$6,2,IF(H49>=Assumptions!$B$7,3,"")))) -> 1 | O49: =IF(N49=1,Assumptions!$B$8,IF(N49=2,Assumptions!$B$9,IF(N49=3,Assumptions!$B$10,0))) -> 3 | P49: no data | Q49: no data | R49: no data | S49: no data | T49: no data | U49: no data | V49: no data | W49: no data | X49: no data | Y49: =IF(AND(X49="processed",ISNUMBER(S49)),S49*O49,"") | Z49: =IF(ISNUMBER(K49),K49*O49,0) -> 738 | AA49: INTERIM: Redfin SFR sales (12 mo) x tier weight | AB49: 11629 | AC49: 10499 | AD49: 2931 | AE49: 2994.6035 | AF49: 864.8377 | AG49: -0.01003685 | AH49: 1 | AI49: postal city of 99% of address points | AJ49: Danville | AK49: Danville
A50: 49 | B50: 95051 | C50: Santa Clara | D50: Santa Clara | E50: Peninsula & South Bay (Santa Clara / San Mateo) | G50: San Jose, CA | H50: 1419.1115 | I50: SFR | J50: 2196512.2 | K50: 246 | M50: =TRUE() -> TRUE | N50: =IF(H50="","",IF(H50>=Assumptions!$B$5,1,IF(H50>=Assumptions!$B$6,2,IF(H50>=Assumptions!$B$7,3,"")))) -> 1 | O50: =IF(N50=1,Assumptions!$B$8,IF(N50=2,Assumptions!$B$9,IF(N50=3,Assumptions!$B$10,0))) -> 3 | P50: no data | Q50: no data | R50: no data | S50: no data | T50: no data | U50: no data | V50: no data | W50: no data | X50: no data | Y50: =IF(AND(X50="processed",ISNUMBER(S50)),S50*O50,"") | Z50: =IF(ISNUMBER(K50),K50*O50,0) -> 738 | AA50: INTERIM: Redfin SFR sales (12 mo) x tier weight | AB50: 19521 | AC50: 13155 | AD50: 195 | AE50: 2309.8188 | AF50: 1492.228 | AG50: 0.012583272 | AH50: 1 | AI50: postal city of 100% of address points | AJ50: Santa Clara | AK50: Santa Clara
A51: 50 | B51: 94062 | C51: Redwood City | D51: San Mateo | E51: Peninsula & South Bay (Santa Clara / San Mateo) | F51: Emerald Lake Hills; Kensington Square | G51: San Francisco, CA | H51: 1306.3344 | I51: SFR | J51: 2963163.3 | K51: 245 | M51: =TRUE() -> TRUE | N51: =IF(H51="","",IF(H51>=Assumptions!$B$5,1,IF(H51>=Assumptions!$B$6,2,IF(H51>=Assumptions!$B$7,3,"")))) -> 1 | O51: =IF(N51=1,Assumptions!$B$8,IF(N51=2,Assumptions!$B$9,IF(N51=3,Assumptions!$B$10,0))) -> 3 | P51: no data | Q51: no data | R51: no data | S51: no data | T51: no data | U51: no data | V51: no data | W51: no data | X51: no data | Y51: =IF(AND(X51="processed",ISNUMBER(S51)),S51*O51,"") | Z51: =IF(ISNUMBER(K51),K51*O51,0) -> 735 | AA51: INTERIM: Redfin SFR sales (12 mo) x tier weight | AB51: 14614 | AC51: 11315 | AD51: 871 | AE51: 2126.4502 | AF51: 1442.5445 | AG51: 0.15481585 | AH51: 0.99997052 | AI51: postal city of 70% of address points | AJ51: Redwood City; Woodside | AK51: Woodside
A52: 51 | B52: 92115 | C52: San Diego | D52: San Diego | E52: San Diego | F52: Mid-City; Montezuma Mesa; Alvarado Estates; Baja Canyon; College View Estates; The Triangle; Colina Park; Darnall; El Cerrito; El Cerrito Heights; Little Saigon; Mesa Colony; Oak Park; Rolando; Rolando Park; Talmadge | G52: San Diego, CA | H52: 717.53638 | I52: SFR | J52: 934370.9 | K52: 244 | M52: =TRUE() -> TRUE | N52: =IF(H52="","",IF(H52>=Assumptions!$B$5,1,IF(H52>=Assumptions!$B$6,2,IF(H52>=Assumptions!$B$7,3,"")))) -> 1 | O52: =IF(N52=1,Assumptions!$B$8,IF(N52=2,Assumptions!$B$9,IF(N52=3,Assumptions!$B$10,0))) -> 3 | P52: no data | Q52: no data | R52: no data | S52: no data | T52: no data | U52: no data | V52: no data | W52: no data | X52: no data | Y52: =IF(AND(X52="processed",ISNUMBER(S52)),S52*O52,"") | Z52: =IF(ISNUMBER(K52),K52*O52,0) -> 732 | AA52: INTERIM: Redfin SFR sales (12 mo) x tier weight | AB52: 14920 | AC52: 11992 | AD52: 6219 | AE52: 1949.5503 | AF52: 778.66072 | AG52: 0.014045335 | AH52: 1 | AI52: postal city of 100% of address points | AJ52: San Diego | AK52: San Diego
A53: 52 | B53: 94044 | C53: Pacifica | D53: San Mateo | E53: Peninsula & South Bay (Santa Clara / San Mateo) | F53: Castle Hill; Edgemar; Fairway Park; Hilton Heights; Linda Mar; Pacific Manor; Pedro Valley; Rockaway Beach; Sharp Park; Shelter Cove; Vallemar | G53: San Francisco, CA | H53: 867.36228 | I53: SFR | J53: 1319405.7 | K53: 244 | M53: =TRUE() -> TRUE | N53: =IF(H53="","",IF(H53>=Assumptions!$B$5,1,IF(H53>=Assumptions!$B$6,2,IF(H53>=Assumptions!$B$7,3,"")))) -> 1 | O53: =IF(N53=1,Assumptions!$B$8,IF(N53=2,Assumptions!$B$9,IF(N53=3,Assumptions!$B$10,0))) -> 3 | P53: no data | Q53: no data | R53: no data | S53: no data | T53: no data | U53: no data | V53: no data | W53: no data | X53: no data | Y53: =IF(AND(X53="processed",ISNUMBER(S53)),S53*O53,"") | Z53: =IF(ISNUMBER(K53),K53*O53,0) -> 732 | AA53: INTERIM: Redfin SFR sales (12 mo) x tier weight | AB53: 12914 | AC53: 12069 | AD53: 444 | AE53: 1760.6427 | AF53: 884.09464 | AG53: -0.030021878 | AH53: 0.99661289 | AI53: postal city of 100% of address points | AJ53: Pacifica | AK53: Pacifica
A54: 53 | B54: 94539 | C54: Fremont | D54: Alameda | E54: Berkeley / Oakland / Alameda County | F54: Mission San Jose District; Warm Springs District | G54: Oakland, CA | H54: 1193.9697 | I54: SFR | J54: 2395041.7 | K54: 240 | M54: =TRUE() -> TRUE | N54: =IF(H54="","",IF(H54>=Assumptions!$B$5,1,IF(H54>=Assumptions!$B$6,2,IF(H54>=Assumptions!$B$7,3,"")))) -> 1 | O54: =IF(N54=1,Assumptions!$B$8,IF(N54=2,Assumptions!$B$9,IF(N54=3,Assumptions!$B$10,0))) -> 3 | P54: no data | Q54: no data | R54: no data | S54: no data | T54: no data | U54: no data | V54: no data | W54: no data | X54: no data | Y54: =IF(AND(X54="processed",ISNUMBER(S54)),S54*O54,"") | Z54: =IF(ISNUMBER(K54),K54*O54,0) -> 720 | AA54: INTERIM: Redfin SFR sales (12 mo) x tier weight | AB54: 17817 | AC54: 15332 | AD54: 199 | AE54: 2582.2788 | AF54: 1226.7624 | AG54: 0.012921984 | AH54: 0.99960689 | AI54: locality polygon (largest overlap) | AK54: Fremont
A55: 54 | B55: 92675 | C55: San Juan Capistrano | D55: Orange | E55: Orange County | F55: Rienda; Rancho Mission Viejo | G55: Anaheim, CA | H55: 725.47033 | I55: SFR | J55: 1875146.4 | K55: 239 | M55: =TRUE() -> TRUE | N55: =IF(H55="","",IF(H55>=Assumptions!$B$5,1,IF(H55>=Assumptions!$B$6,2,IF(H55>=Assumptions!$B$7,3,"")))) -> 1 | O55: =IF(N55=1,Assumptions!$B$8,IF(N55=2,Assumptions!$B$9,IF(N55=3,Assumptions!$B$10,0))) -> 3 | P55: no data | Q55: no data | R55: no data | S55: no data | T55: no data | U55: no data | V55: no data | W55: no data | X55: no data | Y55: =IF(AND(X55="processed",ISNUMBER(S55)),S55*O55,"") | Z55: =IF(ISNUMBER(K55),K55*O55,0) -> 717 | AA55: INTERIM: Redfin SFR sales (12 mo) x tier weight | AB55: 13569 | AC55: 11994 | AD55: 724 | AE55: 2479.8042 | AF55: 748.93377 | AG55: 0.09023455 | AH55: 0.99970438 | AI55: postal city of 90% of address points | AJ55: San Juan Capistrano | AK55: San Juan Capistrano
A56: 55 | B56: 90046 | C56: Los Angeles | D56: Los Angeles | E56: Los Angeles County | F56: Hollywood Hills West | G56: Los Angeles, CA | H56: 963.51314 | I56: SFR | J56: 2237252.1 | K56: 238 | M56: =TRUE() -> TRUE | N56: =IF(H56="","",IF(H56>=Assumptions!$B$5,1,IF(H56>=Assumptions!$B$6,2,IF(H56>=Assumptions!$B$7,3,"")))) -> 1 | O56: =IF(N56=1,Assumptions!$B$8,IF(N56=2,Assumptions!$B$9,IF(N56=3,Assumptions!$B$10,0))) -> 3 | P56: no data | Q56: no data | R56: no data | S56: no data | T56: no data | U56: no data | V56: no data | W56: no data | X56: no data | Y56: =IF(AND(X56="processed",ISNUMBER(S56)),S56*O56,"") | Z56: =IF(ISNUMBER(K56),K56*O56,0) -> 714 | AA56: INTERIM: Redfin SFR sales (12 mo) x tier weight | AB56: 12619 | AC56: 9295 | AD56: 214 | AE56: 2061.4905 | AF56: 911.34672 | AG56: -0.07898566 | AH56: 1 | AI56: postal city of 100% of address points | AJ56: Los Angeles | AK56: Los Angeles
A57: 56 | B57: 92672 | C57: San Clemente | D57: Orange | E57: Orange County | F57: Bay Cliff Village; Colony Cove; Sea Summit | G57: San Diego, CA | H57: 999.24195 | I57: SFR | J57: 1906691.2 | K57: 238 | M57: =TRUE() -> TRUE | N57: =IF(H57="","",IF(H57>=Assumptions!$B$5,1,IF(H57>=Assumptions!$B$6,2,IF(H57>=Assumptions!$B$7,3,"")))) -> 1 | O57: =IF(N57=1,Assumptions!$B$8,IF(N57=2,Assumptions!$B$9,IF(N57=3,Assumptions!$B$10,0))) -> 3 | P57: no data | Q57: no data | R57: no data | S57: no data | T57: no data | U57: no data | V57: no data | W57: no data | X57: no data | Y57: =IF(AND(X57="processed",ISNUMBER(S57)),S57*O57,"") | Z57: =IF(ISNUMBER(K57),K57*O57,0) -> 714 | AA57: INTERIM: Redfin SFR sales (12 mo) x tier weight | AB57: 11968 | AC57: 10576 | AD57: 210 | AE57: 2338.5576 | AF57: 1032.9376 | AG57: 0.037744041 | AH57: 0.9222134 | AI57: postal city of 100% of address points | AJ57: San Clemente | AK57: San Clemente
A58: 57 | B58: 94901 | C58: San Rafael | D58: Marin | E58: Marin | F58: Canal; Chicken Point; Dominican | G58: San Rafael, CA | H58: 757.76377 | I58: SFR | J58: 1526617.6 | K58: 238 | M58: =TRUE() -> TRUE | N58: =IF(H58="","",IF(H58>=Assumptions!$B$5,1,IF(H58>=Assumptions!$B$6,2,IF(H58>=Assumptions!$B$7,3,"")))) -> 1 | O58: =IF(N58=1,Assumptions!$B$8,IF(N58=2,Assumptions!$B$9,IF(N58=3,Assumptions!$B$10,0))) -> 3 | P58: no data | Q58: no data | R58: no data | S58: no data | T58: no data | U58: no data | V58: no data | W58: no data | X58: no data | Y58: =IF(AND(X58="processed",ISNUMBER(S58)),S58*O58,"") | Z58: =IF(ISNUMBER(K58),K58*O58,0) -> 714 | AA58: INTERIM: Redfin SFR sales (12 mo) x tier weight | AB58: 13900 | AC58: 10452 | AD58: 309 | AE58: 2209.156 | AF58: 777.89662 | AG58: -0.044519481 | AH58: 0.75391039 | AI58: postal city of 100% of address points | AJ58: San Rafael | AK58: San Rafael
A59: 58 | B59: 95476 | C59: Sonoma | D59: Sonoma | E59: Rest of California | G59: Santa Rosa, CA | H59: 644.47498 | I59: SFR | J59: 1110382 | K59: 356 | M59: =TRUE() -> TRUE | N59: =IF(H59="","",IF(H59>=Assumptions!$B$5,1,IF(H59>=Assumptions!$B$6,2,IF(H59>=Assumptions!$B$7,3,"")))) -> 2 | O59: =IF(N59=1,Assumptions!$B$8,IF(N59=2,Assumptions!$B$9,IF(N59=3,Assumptions!$B$10,0))) -> 2 | P59: no data | Q59: no data | R59: no data | S59: no data | T59: no data | U59: no data | V59: no data | W59: no data | X59: no data | Y59: =IF(AND(X59="processed",ISNUMBER(S59)),S59*O59,"") | Z59: =IF(ISNUMBER(K59),K59*O59,0) -> 712 | AA59: INTERIM: Redfin SFR sales (12 mo) x tier weight | AB59: 24739 | AC59: 18252 | AD59: 954 | AE59: 1991.656 | AF59: 686.3149 | AG59: 0.034047784 | AH59: 0.99833991 | AI59: postal city of 100% of address points | AJ59: Sonoma | AK59: Sonoma
A60: 59 | B60: 90045 | C60: Los Angeles | D60: Los Angeles | E60: Los Angeles County | F60: Westchester; Westchester Triangle | G60: Los Angeles, CA | H60: 952.25122 | I60: SFR | J60: 1706886.1 | K60: 237 | M60: =TRUE() -> TRUE | N60: =IF(H60="","",IF(H60>=Assumptions!$B$5,1,IF(H60>=Assumptions!$B$6,2,IF(H60>=Assumptions!$B$7,3,"")))) -> 1 | O60: =IF(N60=1,Assumptions!$B$8,IF(N60=2,Assumptions!$B$9,IF(N60=3,Assumptions!$B$10,0))) -> 3 | P60: no data | Q60: no data | R60: no data | S60: no data | T60: no data | U60: no data | V60: no data | W60: no data | X60: no data | Y60: =IF(AND(X60="processed",ISNUMBER(S60)),S60*O60,"") | Z60: =IF(ISNUMBER(K60),K60*O60,0) -> 711 | AA60: INTERIM: Redfin SFR sales (12 mo) x tier weight | AB60: 18153 | AC60: 11824 | AD60: 159 | AE60: 1922.167 | AF60: 964.76965 | AG60: 0.028300057 | AH60: 1 | AI60: postal city of 100% of address points | AJ60: Los Angeles | AK60: Los Angeles
A61: 60 | B61: 94105 | C61: San Francisco | D61: San Francisco | E61: San Francisco | F61: Rincon Hill; 50 Beale Street Plaza; 560 Mission Street Plaza; Foundry Square | G61: San Francisco, CA | H61: 1097.7808 | I61: All Residential (SFR missing) | J61: 1149831.2 | K61: 237 | M61: =TRUE() -> TRUE | N61: =IF(H61="","",IF(H61>=Assumptions!$B$5,1,IF(H61>=Assumptions!$B$6,2,IF(H61>=Assumptions!$B$7,3,"")))) -> 1 | O61: =IF(N61=1,Assumptions!$B$8,IF(N61=2,Assumptions!$B$9,IF(N61=3,Assumptions!$B$10,0))) -> 3 | P61: no data | Q61: no data | R61: no data | S61: no data | T61: no data | U61: no data | V61: no data | W61: no data | X61: no data | Y61: =IF(AND(X61="processed",ISNUMBER(S61)),S61*O61,"") | Z61: =IF(ISNUMBER(K61),K61*O61,0) -> 711 | AA61: INTERIM: Redfin SFR sales (12 mo) x tier weight | AB61: 345 | AC61: 142 | AD61: 2 | AE61: 2360.3469 | AH61: 0.83133021 | AI61: postal city of 100% of address points | AJ61: San Francisco | AK61: San Francisco
A62: 61 | B62: 95003 | C62: Aptos | D62: Santa Cruz | E62: Rest of California | G62: Santa Cruz, CA | H62: 815.35008 | I62: SFR | J62: 1507561.2 | K62: 237 | M62: =TRUE() -> TRUE | N62: =IF(H62="","",IF(H62>=Assumptions!$B$5,1,IF(H62>=Assumptions!$B$6,2,IF(H62>=Assumptions!$B$7,3,"")))) -> 1 | O62: =IF(N62=1,Assumptions!$B$8,IF(N62=2,Assumptions!$B$9,IF(N62=3,Assumptions!$B$10,0))) -> 3 | P62: no data | Q62: no data | R62: no data | S62: no data | T62: no data | U62: no data | V62: no data | W62: no data | X62: no data | Y62: =IF(AND(X62="processed",ISNUMBER(S62)),S62*O62,"") | Z62: =IF(ISNUMBER(K62),K62*O62,0) -> 711 | AA62: INTERIM: Redfin SFR sales (12 mo) x tier weight | AB62: 12106 | AC62: 10661 | AD62: 6906 | AE62: 2068.5427 | AF62: 844.25793 | AG62: -0.008419064 | AH62: 0.97713257 | AI62: postal city of 100% of address points | AJ62: Aptos | AK62: Capitola
A63: 62 | B63: 94015 | C63: Daly City | D63: San Mateo | E63: Peninsula & South Bay (Santa Clara / San Mateo) | F63: Serramonte; Westlake | G63: San Francisco, CA | H63: 856.38105 | I63: SFR | J63: 1282665.3 | K63: 236 | M63: =TRUE() -> TRUE | N63: =IF(H63="","",IF(H63>=Assumptions!$B$5,1,IF(H63>=Assumptions!$B$6,2,IF(H63>=Assumptions!$B$7,3,"")))) -> 1 | O63: =IF(N63=1,Assumptions!$B$8,IF(N63=2,Assumptions!$B$9,IF(N63=3,Assumptions!$B$10,0))) -> 3 | P63: no data | Q63: no data | R63: no data | S63: no data | T63: no data | U63: no data | V63: no data | W63: no data | X63: no data | Y63: =IF(AND(X63="processed",ISNUMBER(S63)),S63*O63,"") | Z63: =IF(ISNUMBER(K63),K63*O63,0) -> 708 | AA63: INTERIM: Redfin SFR sales (12 mo) x tier weight | AB63: 15102 | AC63: 13368 | AD63: 134 | AE63: 1537.7535 | AF63: 921.24222 | AG63: 0.11459501 | AH63: 0.9986352 | AI63: postal city of 92% of address points | AJ63: Daly City | AK63: Daly City
A64: 63 | B64: 94583 | C64: San Ramon | D64: Contra Costa | E64: Rest of California | F64: Alexander Square | G64: Oakland, CA | H64: 749.0144 | I64: SFR | J64: 1516092.1 | K64: 236 | M64: =TRUE() -> TRUE | N64: =IF(H64="","",IF(H64>=Assumptions!$B$5,1,IF(H64>=Assumptions!$B$6,2,IF(H64>=Assumptions!$B$7,3,"")))) -> 1 | O64: =IF(N64=1,Assumptions!$B$8,IF(N64=2,Assumptions!$B$9,IF(N64=3,Assumptions!$B$10,0))) -> 3 | P64: no data | Q64: no data | R64: no data | S64: no data | T64: no data | U64: no data | V64: no data | W64: no data | X64: no data | Y64: =IF(AND(X64="processed",ISNUMBER(S64)),S64*O64,"") | Z64: =IF(ISNUMBER(K64),K64*O64,0) -> 708 | AA64: INTERIM: Redfin SFR sales (12 mo) x tier weight | AB64: 11234 | AC64: 10362 | AD64: 857 | AE64: 2525.6475 | AF64: 776.31579 | AG64: -0.011623508 | AH64: 0.99616943 | AI64: postal city of 98% of address points | AJ64: San Ramon | AK64: San Ramon
A65: 64 | B65: 94563 | C65: Orinda | D65: Contra Costa | E65: Rest of California | F65: Glorietta; Wilder; Orinda Theatre Square | G65: Oakland, CA | H65: 768.83347 | I65: SFR | J65: 1911534.2 | K65: 234 | M65: =TRUE() -> TRUE | N65: =IF(H65="","",IF(H65>=Assumptions!$B$5,1,IF(H65>=Assumptions!$B$6,2,IF(H65>=Assumptions!$B$7,3,"")))) -> 1 | O65: =IF(N65=1,Assumptions!$B$8,IF(N65=2,Assumptions!$B$9,IF(N65=3,Assumptions!$B$10,0))) -> 3 | P65: no data | Q65: no data | R65: no data | S65: no data | T65: no data | U65: no data | V65: no data | W65: no data | X65: no data | Y65: =IF(AND(X65="processed",ISNUMBER(S65)),S65*O65,"") | Z65: =IF(ISNUMBER(K65),K65*O65,0) -> 702 | AA65: INTERIM: Redfin SFR sales (12 mo) x tier weight | AB65: 7681 | AC65: 7039 | AD65: 6318 | AE65: 3097.8491 | AF65: 789.12891 | AG65: -0.038327586 | AH65: 0.99904637 | AI65: postal city of 100% of address points | AJ65: Orinda | AK65: Orinda
A66: 65 | B66: 92648 | C66: Huntington Beach | D66: Orange | E66: Orange County | G66: Anaheim, CA | H66: 846.0964 | I66: SFR | J66: 2023515 | K66: 233 | M66: =TRUE() -> TRUE | N66: =IF(H66="","",IF(H66>=Assumptions!$B$5,1,IF(H66>=Assumptions!$B$6,2,IF(H66>=Assumptions!$B$7,3,"")))) -> 1 | O66: =IF(N66=1,Assumptions!$B$8,IF(N66=2,Assumptions!$B$9,IF(N66=3,Assumptions!$B$10,0))) -> 3 | P66: no data | Q66: no data | R66: no data | S66: no data | T66: no data | U66: no data | V66: no data | W66: no data | X66: no data | Y66: =IF(AND(X66="processed",ISNUMBER(S66)),S66*O66,"") | Z66: =IF(ISNUMBER(K66),K66*O66,0) -> 699 | AA66: INTERIM: Redfin SFR sales (12 mo) x tier weight | AB66: 13592 | AC66: 11783 | AD66: 1093 | AE66: 2104.3433 | AF66: 877.0109 | AG66: -0.033784565 | AH66: 0.70512277 | AI66: postal city of 100% of address points | AJ66: Huntington Beach | AK66: Huntington Beach
A67: 66 | B67: 94116 | C67: San Francisco | D67: San Francisco | E67: San Francisco | F67: Parkside; Forest Hill; Golden Gate Heights | G67: San Francisco, CA | H67: 1093.2446 | I67: SFR | J67: 1793051.5 | K67: 233 | M67: =TRUE() -> TRUE | N67: =IF(H67="","",IF(H67>=Assumptions!$B$5,1,IF(H67>=Assumptions!$B$6,2,IF(H67>=Assumptions!$B$7,3,"")))) -> 1 | O67: =IF(N67=1,Assumptions!$B$8,IF(N67=2,Assumptions!$B$9,IF(N67=3,Assumptions!$B$10,0))) -> 3 | P67: no data | Q67: no data | R67: no data | S67: no data | T67: no data | U67: no data | V67: no data | W67: no data | X67: no data | Y67: =IF(AND(X67="processed",ISNUMBER(S67)),S67*O67,"") | Z67: =IF(ISNUMBER(K67),K67*O67,0) -> 699 | AA67: INTERIM: Redfin SFR sales (12 mo) x tier weight | AB67: 14344 | AC67: 13796 | AD67: 55 | AE67: 1335.3743 | AF67: 1174.0891 | AG67: 0.12217357 | AH67: 1 | AI67: postal city of 100% of address points | AJ67: San Francisco | AK67: Broadmoor
A68: 67 | B68: 90065 | C68: Los Angeles | D68: Los Angeles | E68: Los Angeles County | F68: Dayton Avenue; Glassell Park; Mount Washington; Bobby Brown Uptown Gay and Lesbian Alliance Square; Cypress Park | G68: Los Angeles, CA | H68: 806.80722 | I68: SFR | J68: 1241510 | K68: 232 | M68: =TRUE() -> TRUE | N68: =IF(H68="","",IF(H68>=Assumptions!$B$5,1,IF(H68>=Assumptions!$B$6,2,IF(H68>=Assumptions!$B$7,3,"")))) -> 1 | O68: =IF(N68=1,Assumptions!$B$8,IF(N68=2,Assumptions!$B$9,IF(N68=3,Assumptions!$B$10,0))) -> 3 | P68: no data | Q68: no data | R68: no data | S68: no data | T68: no data | U68: no data | V68: no data | W68: no data | X68: no data | Y68: =IF(AND(X68="processed",ISNUMBER(S68)),S68*O68,"") | Z68: =IF(ISNUMBER(K68),K68*O68,0) -> 696 | AA68: INTERIM: Redfin SFR sales (12 mo) x tier weight | AB68: 17138 | AC68: 12171 | AD68: 244 | AE68: 1577.6248 | AF68: 844.7242 | AG68: -0.062697062 | AH68: 1 | AI68: postal city of 100% of address points | AJ68: Los Angeles | AK68: Los Angeles
A69: 68 | B69: 92886 | C69: Yorba Linda | D69: Orange | E69: Orange County | F69: Country Club; Fairlynn | G69: Anaheim, CA | H69: 659.11359 | I69: SFR | J69: 1486793.1 | K69: 348 | M69: =TRUE() -> TRUE | N69: =IF(H69="","",IF(H69>=Assumptions!$B$5,1,IF(H69>=Assumptions!$B$6,2,IF(H69>=Assumptions!$B$7,3,"")))) -> 2 | O69: =IF(N69=1,Assumptions!$B$8,IF(N69=2,Assumptions!$B$9,IF(N69=3,Assumptions!$B$10,0))) -> 2 | P69: no data | Q69: no data | R69: no data | S69: no data | T69: no data | U69: no data | V69: no data | W69: no data | X69: no data | Y69: =IF(AND(X69="processed",ISNUMBER(S69)),S69*O69,"") | Z69: =IF(ISNUMBER(K69),K69*O69,0) -> 696 | AA69: INTERIM: Redfin SFR sales (12 mo) x tier weight | AB69: 17320 | AC69: 15577 | AD69: 263 | AE69: 2805.0085 | AF69: 670.57705 | AG69: -0.010664936 | AH69: 0.99699382 | AI69: postal city of 95% of address points | AJ69: Yorba Linda | AK69: Yorba Linda
A70: 69 | B70: 92691 | C70: Mission Viejo | D70: Orange | E70: Orange County | G70: Anaheim, CA | H70: 672.26668 | I70: SFR | J70: 1335247.1 | K70: 344 | M70: =TRUE() -> TRUE | N70: =IF(H70="","",IF(H70>=Assumptions!$B$5,1,IF(H70>=Assumptions!$B$6,2,IF(H70>=Assumptions!$B$7,3,"")))) -> 2 | O70: =IF(N70=1,Assumptions!$B$8,IF(N70=2,Assumptions!$B$9,IF(N70=3,Assumptions!$B$10,0))) -> 2 | P70: no data | Q70: no data | R70: no data | S70: no data | T70: no data | U70: no data | V70: no data | W70: no data | X70: no data | Y70: =IF(AND(X70="processed",ISNUMBER(S70)),S70*O70,"") | Z70: =IF(ISNUMBER(K70),K70*O70,0) -> 688 | AA70: INTERIM: Redfin SFR sales (12 mo) x tier weight | AB70: 14281 | AC70: 13494 | AD70: 96 | AE70: 2430.1443 | AF70: 705.88096 | AG70: 0.017810455 | AH70: 1 | AI70: postal city of 98% of address points | AJ70: Mission Viejo | AK70: Mission Viejo
A71: 70 | B71: 92705 | C71: Santa Ana | D71: Orange | E71: Orange County | F71: Cowan Heights; Fairbridge Square; Lemon Heights; Lyon Street; North Tustin; Young Square; Panorama Heights | G71: Anaheim, CA | H71: 703.34542 | I71: SFR | J71: 1752550.2 | K71: 229 | M71: =TRUE() -> TRUE | N71: =IF(H71="","",IF(H71>=Assumptions!$B$5,1,IF(H71>=Assumptions!$B$6,2,IF(H71>=Assumptions!$B$7,3,"")))) -> 1 | O71: =IF(N71=1,Assumptions!$B$8,IF(N71=2,Assumptions!$B$9,IF(N71=3,Assumptions!$B$10,0))) -> 3 | P71: no data | Q71: no data | R71: no data | S71: no data | T71: no data | U71: no data | V71: no data | W71: no data | X71: no data | Y71: =IF(AND(X71="processed",ISNUMBER(S71)),S71*O71,"") | Z71: =IF(ISNUMBER(K71),K71*O71,0) -> 687 | AA71: INTERIM: Redfin SFR sales (12 mo) x tier weight | AB71: 14398 | AC71: 11970 | AD71: 451 | AE71: 3164.0701 | AF71: 735.715 | AG71: 0.018790104 | AH71: 1 | AI71: postal city of 68% of address points | AJ71: Santa Ana; North Tustin | AK71: Santa Ana
A72: 71 | B72: 92694 | C72: Ladera Ranch | D72: Orange | E72: Orange County | F72: Los Patrones | G72: Anaheim, CA | H72: 656.34391 | I72: SFR | J72: 1504487.9 | K72: 341 | M72: =TRUE() -> TRUE | N72: =IF(H72="","",IF(H72>=Assumptions!$B$5,1,IF(H72>=Assumptions!$B$6,2,IF(H72>=Assumptions!$B$7,3,"")))) -> 2 | O72: =IF(N72=1,Assumptions!$B$8,IF(N72=2,Assumptions!$B$9,IF(N72=3,Assumptions!$B$10,0))) -> 2 | P72: no data | Q72: no data | R72: no data | S72: no data | T72: no data | U72: no data | V72: no data | W72: no data | X72: no data | Y72: =IF(AND(X72="processed",ISNUMBER(S72)),S72*O72,"") | Z72: =IF(ISNUMBER(K72),K72*O72,0) -> 682 | AA72: INTERIM: Redfin SFR sales (12 mo) x tier weight | AB72: 7645 | AC72: 7024 | AD72: 111 | AE72: 2349.8735 | AF72: 666.50149 | AG72: 0.016346757 | AH72: 1 | AI72: postal city of 57% of address points | AJ72: Ladera Ranch; Rancho Mission Viejo | AK72: Mission Viejo
A73: 72 | B73: 92647 | C73: Huntington Beach | D73: Orange | E73: Orange County | G73: Anaheim, CA | H73: 811.46192 | I73: SFR | J73: 1301519.8 | K73: 227 | M73: =TRUE() -> TRUE | N73: =IF(H73="","",IF(H73>=Assumptions!$B$5,1,IF(H73>=Assumptions!$B$6,2,IF(H73>=Assumptions!$B$7,3,"")))) -> 1 | O73: =IF(N73=1,Assumptions!$B$8,IF(N73=2,Assumptions!$B$9,IF(N73=3,Assumptions!$B$10,0))) -> 3 | P73: no data | Q73: no data | R73: no data | S73: no data | T73: no data | U73: no data | V73: no data | W73: no data | X73: no data | Y73: =IF(AND(X73="processed",ISNUMBER(S73)),S73*O73,"") | Z73: =IF(ISNUMBER(K73),K73*O73,0) -> 681 | AA73: INTERIM: Redfin SFR sales (12 mo) x tier weight | AB73: 14923 | AC73: 13696 | AD73: 481 | AE73: 2405.6626 | AF73: 855.50911 | AG73: 0.10683571 | AH73: 1 | AI73: postal city of 100% of address points | AJ73: Huntington Beach | AK73: Huntington Beach
A74: 73 | B74: 94080 | C74: South San Francisco | D74: San Mateo | E74: Peninsula & South Bay (Santa Clara / San Mateo) | F74: South San Francisco BART Plaza | G74: San Francisco, CA | H74: 885.31412 | I74: SFR | J74: 1290977.8 | K74: 225 | M74: =TRUE() -> TRUE | N74: =IF(H74="","",IF(H74>=Assumptions!$B$5,1,IF(H74>=Assumptions!$B$6,2,IF(H74>=Assumptions!$B$7,3,"")))) -> 1 | O74: =IF(N74=1,Assumptions!$B$8,IF(N74=2,Assumptions!$B$9,IF(N74=3,Assumptions!$B$10,0))) -> 3 | P74: no data | Q74: no data | R74: no data | S74: no data | T74: no data | U74: no data | V74: no data | W74: no data | X74: no data | Y74: =IF(AND(X74="processed",ISNUMBER(S74)),S74*O74,"") | Z74: =IF(ISNUMBER(K74),K74*O74,0) -> 675 | AA74: INTERIM: Redfin SFR sales (12 mo) x tier weight | AB74: 18950 | AC74: 16038 | AD74: 478 | AE74: 1792.1451 | AF74: 870.96774 | AG74: -0.010829493 | AH74: 0.96641539 | AI74: postal city of 99% of address points | AJ74: South San Francisco | AK74: South San Francisco
A75: 74 | B75: 94403 | C75: San Mateo | D75: San Mateo | E75: Peninsula & South Bay (Santa Clara / San Mateo) | F75: Bay Meadows Town Square | G75: San Francisco, CA | H75: 1233.3342 | I75: SFR | J75: 2103080.4 | K75: 224 | M75: =TRUE() -> TRUE | N75: =IF(H75="","",IF(H75>=Assumptions!$B$5,1,IF(H75>=Assumptions!$B$6,2,IF(H75>=Assumptions!$B$7,3,"")))) -> 1 | O75: =IF(N75=1,Assumptions!$B$8,IF(N75=2,Assumptions!$B$9,IF(N75=3,Assumptions!$B$10,0))) -> 3 | P75: no data | Q75: no data | R75: no data | S75: no data | T75: no data | U75: no data | V75: no data | W75: no data | X75: no data | Y75: =IF(AND(X75="processed",ISNUMBER(S75)),S75*O75,"") | Z75: =IF(ISNUMBER(K75),K75*O75,0) -> 672 | AA75: INTERIM: Redfin SFR sales (12 mo) x tier weight | AB75: 11948 | AC75: 10290 | AD75: 148 | AE75: 2268.8271 | AF75: 1278.6811 | AG75: 0.045320368 | AH75: 1 | AI75: postal city of 100% of address points | AJ75: San Mateo | AK75: San Mateo
A76: 75 | B76: 94061 | C76: Redwood City | D76: San Mateo | E76: Peninsula & South Bay (Santa Clara / San Mateo) | F76: Sequoia Tract | G76: San Francisco, CA | H76: 1288.5232 | I76: SFR | J76: 2198370 | K76: 223 | M76: =TRUE() -> TRUE | N76: =IF(H76="","",IF(H76>=Assumptions!$B$5,1,IF(H76>=Assumptions!$B$6,2,IF(H76>=Assumptions!$B$7,3,"")))) -> 1 | O76: =IF(N76=1,Assumptions!$B$8,IF(N76=2,Assumptions!$B$9,IF(N76=3,Assumptions!$B$10,0))) -> 3 | P76: no data | Q76: no data | R76: no data | S76: no data | T76: no data | U76: no data | V76: no data | W76: no data | X76: no data | Y76: =IF(AND(X76="processed",ISNUMBER(S76)),S76*O76,"") | Z76: =IF(ISNUMBER(K76),K76*O76,0) -> 669 | AA76: INTERIM: Redfin SFR sales (12 mo) x tier weight | AB76: 12058 | AC76: 9365 | AD76: 107 | AE76: 2151.2219 | AF76: 1395.5224 | AG76: 0.062205771 | AH76: 1 | AI76: postal city of 100% of address points | AJ76: Redwood City | AK76: Redwood City
A77: 76 | B77: 94131 | C77: San Francisco | D77: San Francisco | E77: San Francisco | F77: Diamond Heights; Forest Knolls; Sunnyside; Glen Park | G77: San Francisco, CA | H77: 1182.7691 | I77: SFR | J77: 2057031.4 | K77: 223 | M77: =TRUE() -> TRUE | N77: =IF(H77="","",IF(H77>=Assumptions!$B$5,1,IF(H77>=Assumptions!$B$6,2,IF(H77>=Assumptions!$B$7,3,"")))) -> 1 | O77: =IF(N77=1,Assumptions!$B$8,IF(N77=2,Assumptions!$B$9,IF(N77=3,Assumptions!$B$10,0))) -> 3 | P77: no data | Q77: no data | R77: no data | S77: no data | T77: no data | U77: no data | V77: no data | W77: no data | X77: no data | Y77: =IF(AND(X77="processed",ISNUMBER(S77)),S77*O77,"") | Z77: =IF(ISNUMBER(K77),K77*O77,0) -> 669 | AA77: INTERIM: Redfin SFR sales (12 mo) x tier weight | AB77: 8436 | AC77: 7907 | AD77: 48 | AE77: 1272.6528 | AF77: 1385.8337 | AG77: 0.176743 | AH77: 1 | AI77: postal city of 100% of address points | AJ77: San Francisco | AK77: San Francisco
A78: 77 | B78: 94402 | C78: San Mateo | D78: San Mateo | E78: Peninsula & South Bay (Santa Clara / San Mateo) | G78: San Francisco, CA | H78: 1351.5091 | I78: SFR | J78: 2643433.5 | K78: 218 | M78: =TRUE() -> TRUE | N78: =IF(H78="","",IF(H78>=Assumptions!$B$5,1,IF(H78>=Assumptions!$B$6,2,IF(H78>=Assumptions!$B$7,3,"")))) -> 1 | O78: =IF(N78=1,Assumptions!$B$8,IF(N78=2,Assumptions!$B$9,IF(N78=3,Assumptions!$B$10,0))) -> 3 | P78: no data | Q78: no data | R78: no data | S78: no data | T78: no data | U78: no data | V78: no data | W78: no data | X78: no data | Y78: =IF(AND(X78="processed",ISNUMBER(S78)),S78*O78,"") | Z78: =IF(ISNUMBER(K78),K78*O78,0) -> 654 | AA78: INTERIM: Redfin SFR sales (12 mo) x tier weight | AB78: 8983 | AC78: 7589 | AD78: 192 | AE78: 2339.4253 | AF78: 1454.5713 | AG78: 0.026499276 | AH78: 1 | AI78: postal city of 99% of address points | AJ78: San Mateo | AK78: San Mateo
A79: 78 | B79: 94602 | C79: Oakland | D79: Alameda | E79: Berkeley / Oakland / Alameda County | F79: Oakland Hills; Dimond District; Glenview; Oakmore Highlands | G79: Oakland, CA | H79: 719.58458 | I79: SFR | J79: 1100004.6 | K79: 217 | M79: =TRUE() -> TRUE | N79: =IF(H79="","",IF(H79>=Assumptions!$B$5,1,IF(H79>=Assumptions!$B$6,2,IF(H79>=Assumptions!$B$7,3,"")))) -> 1 | O79: =IF(N79=1,Assumptions!$B$8,IF(N79=2,Assumptions!$B$9,IF(N79=3,Assumptions!$B$10,0))) -> 3 | P79: no data | Q79: no data | R79: no data | S79: no data | T79: no data | U79: no data | V79: no data | W79: no data | X79: no data | Y79: =IF(AND(X79="processed",ISNUMBER(S79)),S79*O79,"") | Z79: =IF(ISNUMBER(K79),K79*O79,0) -> 651 | AA79: INTERIM: Redfin SFR sales (12 mo) x tier weight | AB79: 13346 | AC79: 9473 | AD79: 78 | AE79: 1623.9302 | AF79: 782.92683 | AG79: 0.18625277 | AH79: 1 | AI79: locality polygon (largest overlap) | AK79: Oakland
A80: 79 | B80: 94122 | C80: San Francisco | D80: San Francisco | E80: San Francisco | F80: Sunset District; Inner Sunset; Outer Sunset | G80: San Francisco, CA | H80: 1102.9881 | I80: SFR | J80: 1805560.2 | K80: 216 | M80: =TRUE() -> TRUE | N80: =IF(H80="","",IF(H80>=Assumptions!$B$5,1,IF(H80>=Assumptions!$B$6,2,IF(H80>=Assumptions!$B$7,3,"")))) -> 1 | O80: =IF(N80=1,Assumptions!$B$8,IF(N80=2,Assumptions!$B$9,IF(N80=3,Assumptions!$B$10,0))) -> 3 | P80: no data | Q80: no data | R80: no data | S80: no data | T80: no data | U80: no data | V80: no data | W80: no data | X80: no data | Y80: =IF(AND(X80="processed",ISNUMBER(S80)),S80*O80,"") | Z80: =IF(ISNUMBER(K80),K80*O80,0) -> 648 | AA80: INTERIM: Redfin SFR sales (12 mo) x tier weight | AB80: 14848 | AC80: 14496 | AD80: 76 | AE80: 1384.9932 | AF80: 1204.1284 | AG80: 0.12656188 | AH80: 1 | AI80: postal city of 100% of address points | AJ80: San Francisco | AK80: Broadmoor
A81: 80 | B81: 94903 | C81: San Rafael | D81: Marin | E81: Marin | F81: Terra Linda | G81: San Rafael, CA | H81: 787.22453 | I81: SFR | J81: 1376342.6 | K81: 216 | M81: =TRUE() -> TRUE | N81: =IF(H81="","",IF(H81>=Assumptions!$B$5,1,IF(H81>=Assumptions!$B$6,2,IF(H81>=Assumptions!$B$7,3,"")))) -> 1 | O81: =IF(N81=1,Assumptions!$B$8,IF(N81=2,Assumptions!$B$9,IF(N81=3,Assumptions!$B$10,0))) -> 3 | P81: no data | Q81: no data | R81: no data | S81: no data | T81: no data | U81: no data | V81: no data | W81: no data | X81: no data | Y81: =IF(AND(X81="processed",ISNUMBER(S81)),S81*O81,"") | Z81: =IF(ISNUMBER(K81),K81*O81,0) -> 648 | AA81: INTERIM: Redfin SFR sales (12 mo) x tier weight | AB81: 11550 | AC81: 8943 | AD81: 125 | AE81: 2535.7256 | AF81: 841.97955 | AG81: 0.0069580536 | AH81: 0.97681015 | AI81: postal city of 100% of address points | AJ81: San Rafael | AK81: San Rafael
A82: 81 | B82: 90042 | C82: Los Angeles | D82: Los Angeles | E82: Los Angeles County | F82: Highland Park | G82: Los Angeles, CA | H82: 910.32727 | I82: SFR | J82: 1218744.2 | K82: 215 | M82: =TRUE() -> TRUE | N82: =IF(H82="","",IF(H82>=Assumptions!$B$5,1,IF(H82>=Assumptions!$B$6,2,IF(H82>=Assumptions!$B$7,3,"")))) -> 1 | O82: =IF(N82=1,Assumptions!$B$8,IF(N82=2,Assumptions!$B$9,IF(N82=3,Assumptions!$B$10,0))) -> 3 | P82: no data | Q82: no data | R82: no data | S82: no data | T82: no data | U82: no data | V82: no data | W82: no data | X82: no data | Y82: =IF(AND(X82="processed",ISNUMBER(S82)),S82*O82,"") | Z82: =IF(ISNUMBER(K82),K82*O82,0) -> 645 | AA82: INTERIM: Redfin SFR sales (12 mo) x tier weight | AB82: 20015 | AC82: 13490 | AD82: 257 | AE82: 1532.0214 | AF82: 910.43678 | AG82: 0.019504328 | AH82: 1 | AI82: postal city of 100% of address points | AJ82: Los Angeles | AK82: Los Angeles
A83: 82 | B83: 91604 | C83: Studio City | D83: Los Angeles | E83: Los Angeles County | F83: Studio City; Studio City Neighborhood Council District; Silver Triangle | G83: Los Angeles, CA | H83: 929.38437 | I83: SFR | J83: 2222325.6 | K83: 215 | M83: =TRUE() -> TRUE | N83: =IF(H83="","",IF(H83>=Assumptions!$B$5,1,IF(H83>=Assumptions!$B$6,2,IF(H83>=Assumptions!$B$7,3,"")))) -> 1 | O83: =IF(N83=1,Assumptions!$B$8,IF(N83=2,Assumptions!$B$9,IF(N83=3,Assumptions!$B$10,0))) -> 3 | P83: no data | Q83: no data | R83: no data | S83: no data | T83: no data | U83: no data | V83: no data | W83: no data | X83: no data | Y83: =IF(AND(X83="processed",ISNUMBER(S83)),S83*O83,"") | Z83: =IF(ISNUMBER(K83),K83*O83,0) -> 645 | AA83: INTERIM: Redfin SFR sales (12 mo) x tier weight | AB83: 11095 | AC83: 7895 | AD83: 192 | AE83: 2442.0637 | AF83: 907.51445 | AG83: 0.00089310392 | AH83: 1 | AI83: postal city of 100% of address points | AJ83: Studio City | AK83: Los Angeles
A84: 83 | B84: 91302 | C84: Calabasas | D84: Los Angeles | E84: Los Angeles County | F84: Braewood | G84: Los Angeles, CA | H84: 708.53292 | I84: SFR | J84: 2000032.7 | K84: 214 | M84: =TRUE() -> TRUE | N84: =IF(H84="","",IF(H84>=Assumptions!$B$5,1,IF(H84>=Assumptions!$B$6,2,IF(H84>=Assumptions!$B$7,3,"")))) -> 1 | O84: =IF(N84=1,Assumptions!$B$8,IF(N84=2,Assumptions!$B$9,IF(N84=3,Assumptions!$B$10,0))) -> 3 | P84: no data | Q84: no data | R84: no data | S84: no data | T84: no data | U84: no data | V84: no data | W84: no data | X84: no data | Y84: =IF(AND(X84="processed",ISNUMBER(S84)),S84*O84,"") | Z84: =IF(ISNUMBER(K84),K84*O84,0) -> 642 | AA84: INTERIM: Redfin SFR sales (12 mo) x tier weight | AB84: 9873 | AC84: 8079 | AD84: 291 | AE84: 2948.0505 | AF84: 730.5728 | AG84: -0.040749828 | AH84: 0.99981012 | AI84: postal city of 100% of address points | AJ84: Calabasas | AK84: Calabasas
A85: 84 | B85: 94024 | C85: Los Altos | D85: Santa Clara | E85: Peninsula & South Bay (Santa Clara / San Mateo) | F85: Creston | G85: San Jose, CA | H85: 1798.3022 | I85: SFR | J85: 4535658.9 | K85: 214 | M85: =TRUE() -> TRUE | N85: =IF(H85="","",IF(H85>=Assumptions!$B$5,1,IF(H85>=Assumptions!$B$6,2,IF(H85>=Assumptions!$B$7,3,"")))) -> 1 | O85: =IF(N85=1,Assumptions!$B$8,IF(N85=2,Assumptions!$B$9,IF(N85=3,Assumptions!$B$10,0))) -> 3 | P85: no data | Q85: no data | R85: no data | S85: no data | T85: no data | U85: no data | V85: no data | W85: no data | X85: no data | Y85: =IF(AND(X85="processed",ISNUMBER(S85)),S85*O85,"") | Z85: =IF(ISNUMBER(K85),K85*O85,0) -> 642 | AA85: INTERIM: Redfin SFR sales (12 mo) x tier weight | AB85: 9523 | AC85: 8605 | AD85: 491 | AE85: 3183.5488 | AF85: 1809.1377 | AG85: 0.0068673565 | AH85: 1 | AI85: postal city of 94% of address points | AJ85: Los Altos | AK85: Los Altos
A86: 85 | B86: 91423 | C86: Sherman Oaks | D86: Los Angeles | E86: Los Angeles County | F86: Sherman Village | G86: Los Angeles, CA | H86: 820.79183 | I86: SFR | J86: 1981969.5 | K86: 213 | M86: =TRUE() -> TRUE | N86: =IF(H86="","",IF(H86>=Assumptions!$B$5,1,IF(H86>=Assumptions!$B$6,2,IF(H86>=Assumptions!$B$7,3,"")))) -> 1 | O86: =IF(N86=1,Assumptions!$B$8,IF(N86=2,Assumptions!$B$9,IF(N86=3,Assumptions!$B$10,0))) -> 3 | P86: no data | Q86: no data | R86: no data | S86: no data | T86: no data | U86: no data | V86: no data | W86: no data | X86: no data | Y86: =IF(AND(X86="processed",ISNUMBER(S86)),S86*O86,"") | Z86: =IF(ISNUMBER(K86),K86*O86,0) -> 639 | AA86: INTERIM: Redfin SFR sales (12 mo) x tier weight | AB86: 10448 | AC86: 7189 | AD86: 133 | AE86: 2368.8059 | AF86: 846.41801 | AG86: -0.040926588 | AH86: 1 | AI86: postal city of 100% of address points | AJ86: Sherman Oaks | AK86: Los Angeles
A87: 86 | B87: 94506 | C87: Danville | D87: Contra Costa | E87: Rest of California | F87: California Shadowhawk; Meadow Creek; Northridge Estates; Woodside Oaks | G87: Oakland, CA | H87: 726.81368 | I87: SFR | J87: 2372046.9 | K87: 213 | M87: =TRUE() -> TRUE | N87: =IF(H87="","",IF(H87>=Assumptions!$B$5,1,IF(H87>=Assumptions!$B$6,2,IF(H87>=Assumptions!$B$7,3,"")))) -> 1 | O87: =IF(N87=1,Assumptions!$B$8,IF(N87=2,Assumptions!$B$9,IF(N87=3,Assumptions!$B$10,0))) -> 3 | P87: no data | Q87: no data | R87: no data | S87: no data | T87: no data | U87: no data | V87: no data | W87: no data | X87: no data | Y87: =IF(AND(X87="processed",ISNUMBER(S87)),S87*O87,"") | Z87: =IF(ISNUMBER(K87),K87*O87,0) -> 639 | AA87: INTERIM: Redfin SFR sales (12 mo) x tier weight | AB87: 8521 | AC87: 7732 | AD87: 4269 | AE87: 3092.4609 | AF87: 720.10427 | AG87: -0.08825436 | AH87: 1 | AI87: postal city of 100% of address points | AJ87: Danville | AK87: Danville
A88: 87 | B88: 95014 | C88: Cupertino | D88: Santa Clara | E88: Peninsula & South Bay (Santa Clara / San Mateo) | F88: Rancho Rinconada; Wilson Park; Academic Quad; Cupertino Civic Center; Olive Court; Rally Court | G88: San Jose, CA | H88: 1673.3281 | I88: SFR | J88: 3404641.5 | K88: 212 | M88: =TRUE() -> TRUE | N88: =IF(H88="","",IF(H88>=Assumptions!$B$5,1,IF(H88>=Assumptions!$B$6,2,IF(H88>=Assumptions!$B$7,3,"")))) -> 1 | O88: =IF(N88=1,Assumptions!$B$8,IF(N88=2,Assumptions!$B$9,IF(N88=3,Assumptions!$B$10,0))) -> 3 | P88: no data | Q88: no data | R88: no data | S88: no data | T88: no data | U88: no data | V88: no data | W88: no data | X88: no data | Y88: =IF(AND(X88="processed",ISNUMBER(S88)),S88*O88,"") | Z88: =IF(ISNUMBER(K88),K88*O88,0) -> 636 | AA88: INTERIM: Redfin SFR sales (12 mo) x tier weight | AB88: 22373 | AC88: 15786 | AD88: 289 | AE88: 2487.4221 | AF88: 1652.0899 | AG88: -0.055582157 | AH88: 1 | AI88: postal city of 100% of address points | AJ88: Cupertino | AK88: Cupertino
A89: 88 | B89: 95008 | C89: Campbell | D89: Santa Clara | E89: Peninsula & South Bay (Santa Clara / San Mateo) | F89: San Tomas; Campbell Courtyard; Quad | G89: San Jose, CA | H89: 1232.7196 | I89: SFR | J89: 2132189.6 | K89: 211 | M89: =TRUE() -> TRUE | N89: =IF(H89="","",IF(H89>=Assumptions!$B$5,1,IF(H89>=Assumptions!$B$6,2,IF(H89>=Assumptions!$B$7,3,"")))) -> 1 | O89: =IF(N89=1,Assumptions!$B$8,IF(N89=2,Assumptions!$B$9,IF(N89=3,Assumptions!$B$10,0))) -> 3 | P89: no data | Q89: no data | R89: no data | S89: no data | T89: no data | U89: no data | V89: no data | W89: no data | X89: no data | Y89: =IF(AND(X89="processed",ISNUMBER(S89)),S89*O89,"") | Z89: =IF(ISNUMBER(K89),K89*O89,0) -> 633 | AA89: INTERIM: Redfin SFR sales (12 mo) x tier weight | AB89: 15374 | AC89: 12634 | AD89: 799 | AE89: 2327.7905 | AF89: 1250.1245 | AG89: -0.03948221 | AH89: 1 | AI89: postal city of 100% of address points | AJ89: Campbell | AK89: Campbell
A90: 89 | B90: 92673 | C90: San Clemente | D90: Orange | E90: Orange County | F90: Portofino; San Rafael; Compass Pointe; El Encanto; Flora Vista; San Angelo; Talega | G90: Anaheim, CA | H90: 710.1822 | I90: SFR | J90: 1848358.2 | K90: 210 | M90: =TRUE() -> TRUE | N90: =IF(H90="","",IF(H90>=Assumptions!$B$5,1,IF(H90>=Assumptions!$B$6,2,IF(H90>=Assumptions!$B$7,3,"")))) -> 1 | O90: =IF(N90=1,Assumptions!$B$8,IF(N90=2,Assumptions!$B$9,IF(N90=3,Assumptions!$B$10,0))) -> 3 | P90: no data | Q90: no data | R90: no data | S90: no data | T90: no data | U90: no data | V90: no data | W90: no data | X90: no data | Y90: =IF(AND(X90="processed",ISNUMBER(S90)),S90*O90,"") | Z90: =IF(ISNUMBER(K90),K90*O90,0) -> 630 | AA90: INTERIM: Redfin SFR sales (12 mo) x tier weight | AB90: 9530 | AC90: 8815 | AD90: 130 | AE90: 2545.0735 | AF90: 694.9158 | AG90: -0.01944985 | AH90: 1 | AI90: postal city of 100% of address points | AJ90: San Clemente | AK90: San Clemente
A91: 90 | B91: 92618 | C91: Irvine | D91: Orange | E91: Orange County | F91: Altair; Cypress Village; Great Park; Irvine Spectrum; Laguna Altura; Los Olivos; Oak Creek; Portola Springs; Woodbury East; Lambert Ranch; Travata; Woodbury Place Apartments | G91: Anaheim, CA | H91: 835.06192 | I91: SFR | J91: 2375134 | K91: 209 | M91: =TRUE() -> TRUE | N91: =IF(H91="","",IF(H91>=Assumptions!$B$5,1,IF(H91>=Assumptions!$B$6,2,IF(H91>=Assumptions!$B$7,3,"")))) -> 1 | O91: =IF(N91=1,Assumptions!$B$8,IF(N91=2,Assumptions!$B$9,IF(N91=3,Assumptions!$B$10,0))) -> 3 | P91: no data | Q91: no data | R91: no data | S91: no data | T91: no data | U91: no data | V91: no data | W91: no data | X91: no data | Y91: =IF(AND(X91="processed",ISNUMBER(S91)),S91*O91,"") | Z91: =IF(ISNUMBER(K91),K91*O91,0) -> 627 | AA91: INTERIM: Redfin SFR sales (12 mo) x tier weight | AB91: 17532 | AC91: 15366 | AD91: 517 | AE91: 1914.1045 | AF91: 825.65496 | AG91: -0.087581295 | AH91: 1 | AI91: postal city of 100% of address points | AJ91: Irvine | AK91: Irvine
A92: 91 | B92: 94546 | C92: Hayward | D92: Alameda | E92: Berkeley / Oakland / Alameda County | G92: Oakland, CA | H92: 695.01202 | I92: SFR | J92: 1107667.7 | K92: 313 | M92: =TRUE() -> TRUE | N92: =IF(H92="","",IF(H92>=Assumptions!$B$5,1,IF(H92>=Assumptions!$B$6,2,IF(H92>=Assumptions!$B$7,3,"")))) -> 2 | O92: =IF(N92=1,Assumptions!$B$8,IF(N92=2,Assumptions!$B$9,IF(N92=3,Assumptions!$B$10,0))) -> 2 | P92: no data | Q92: no data | R92: no data | S92: no data | T92: no data | U92: no data | V92: no data | W92: no data | X92: no data | Y92: =IF(AND(X92="processed",ISNUMBER(S92)),S92*O92,"") | Z92: =IF(ISNUMBER(K92),K92*O92,0) -> 626 | AA92: INTERIM: Redfin SFR sales (12 mo) x tier weight | AB92: 16868 | AC92: 13649 | AD92: 5174 | AE92: 2007.5481 | AF92: 706.16883 | AG92: -0.035015224 | AH92: 1 | AI92: locality polygon (largest overlap) | AK92: Hayward
A93: 92 | B93: 94501 | C93: Alameda | D93: Alameda | E93: Berkeley / Oakland / Alameda County | F93: East End; Fernside; Gold Coast; South Shore; West End; Woodstock | G93: Oakland, CA | H93: 785.37641 | I93: SFR | J93: 1372843.8 | K93: 208 | M93: =TRUE() -> TRUE | N93: =IF(H93="","",IF(H93>=Assumptions!$B$5,1,IF(H93>=Assumptions!$B$6,2,IF(H93>=Assumptions!$B$7,3,"")))) -> 1 | O93: =IF(N93=1,Assumptions!$B$8,IF(N93=2,Assumptions!$B$9,IF(N93=3,Assumptions!$B$10,0))) -> 3 | P93: no data | Q93: no data | R93: no data | S93: no data | T93: no data | U93: no data | V93: no data | W93: no data | X93: no data | Y93: =IF(AND(X93="processed",ISNUMBER(S93)),S93*O93,"") | Z93: =IF(ISNUMBER(K93),K93*O93,0) -> 624 | AA93: INTERIM: Redfin SFR sales (12 mo) x tier weight | AB93: 20980 | AC93: 15235 | AD93: 266 | AE93: 1671.9987 | AF93: 827.74049 | AG93: -0.04189038 | AH93: 0.63468919 | AI93: locality polygon (largest overlap) | AK93: Alameda
A94: 93 | B94: 95070 | C94: Saratoga | D94: Santa Clara | E94: Peninsula & South Bay (Santa Clara / San Mateo) | G94: San Jose, CA | H94: 1578.8767 | I94: SFR | J94: 4336254.8 | K94: 208 | M94: =TRUE() -> TRUE | N94: =IF(H94="","",IF(H94>=Assumptions!$B$5,1,IF(H94>=Assumptions!$B$6,2,IF(H94>=Assumptions!$B$7,3,"")))) -> 1 | O94: =IF(N94=1,Assumptions!$B$8,IF(N94=2,Assumptions!$B$9,IF(N94=3,Assumptions!$B$10,0))) -> 3 | P94: no data | Q94: no data | R94: no data | S94: no data | T94: no data | U94: no data | V94: no data | W94: no data | X94: no data | Y94: =IF(AND(X94="processed",ISNUMBER(S94)),S94*O94,"") | Z94: =IF(ISNUMBER(K94),K94*O94,0) -> 624 | AA94: INTERIM: Redfin SFR sales (12 mo) x tier weight | AB94: 12645 | AC94: 10887 | AD94: 3616 | AE94: 3456.0103 | AF94: 1640.525 | AG94: 0.057995036 | AH94: 0.99920653 | AI94: postal city of 100% of address points | AJ94: Saratoga | AK94: Saratoga
A95: 94 | B95: 91361 | C95: Westlake Village | D95: Ventura | E95: Ventura | F95: Bridgehaven; First Neighborhood; Westlake Bay; Westshore | G95: Oxnard, CA | H95: 714.2615 | I95: SFR | J95: 1922487.9 | K95: 207 | M95: =TRUE() -> TRUE | N95: =IF(H95="","",IF(H95>=Assumptions!$B$5,1,IF(H95>=Assumptions!$B$6,2,IF(H95>=Assumptions!$B$7,3,"")))) -> 1 | O95: =IF(N95=1,Assumptions!$B$8,IF(N95=2,Assumptions!$B$9,IF(N95=3,Assumptions!$B$10,0))) -> 3 | P95: no data | Q95: no data | R95: no data | S95: no data | T95: no data | U95: no data | V95: no data | W95: no data | X95: no data | Y95: =IF(AND(X95="processed",ISNUMBER(S95)),S95*O95,"") | Z95: =IF(ISNUMBER(K95),K95*O95,0) -> 621 | AA95: INTERIM: Redfin SFR sales (12 mo) x tier weight | AB95: 7440 | AC95: 6317 | AD95: 2172 | AE95: 2947.4792 | AF95: 767.91871 | AG95: 0.057443608 | AH95: 0.83078567 | AI95: postal city of 100% of address points | AJ95: Westlake Village | AK95: Thousand Oaks
A96: 95 | B96: 90650 | C96: Norwalk | D96: Los Angeles | E96: Los Angeles County | G96: Los Angeles, CA | H96: 636.7825 | I96: SFR | J96: 759563.11 | K96: 309 | M96: =TRUE() -> TRUE | N96: =IF(H96="","",IF(H96>=Assumptions!$B$5,1,IF(H96>=Assumptions!$B$6,2,IF(H96>=Assumptions!$B$7,3,"")))) -> 2 | O96: =IF(N96=1,Assumptions!$B$8,IF(N96=2,Assumptions!$B$9,IF(N96=3,Assumptions!$B$10,0))) -> 2 | P96: no data | Q96: no data | R96: no data | S96: no data | T96: no data | U96: no data | V96: no data | W96: no data | X96: no data | Y96: =IF(AND(X96="processed",ISNUMBER(S96)),S96*O96,"") | Z96: =IF(ISNUMBER(K96),K96*O96,0) -> 618 | AA96: INTERIM: Redfin SFR sales (12 mo) x tier weight | AB96: 32470 | AC96: 24139 | AD96: 219 | AE96: 1835.9526 | AF96: 638.65496 | AG96: 0.079106665 | AH96: 1 | AI96: postal city of 100% of address points | AJ96: Norwalk | AK96: Norwalk
A97: 96 | B97: 91107 | C97: Pasadena | D97: Los Angeles | E97: Los Angeles County | F97: San Pasqual; Chapman Woods; Lamanda Park | G97: Los Angeles, CA | H97: 866.05186 | I97: SFR | J97: 1598733 | K97: 206 | M97: =TRUE() -> TRUE | N97: =IF(H97="","",IF(H97>=Assumptions!$B$5,1,IF(H97>=Assumptions!$B$6,2,IF(H97>=Assumptions!$B$7,3,"")))) -> 1 | O97: =IF(N97=1,Assumptions!$B$8,IF(N97=2,Assumptions!$B$9,IF(N97=3,Assumptions!$B$10,0))) -> 3 | P97: no data | Q97: no data | R97: no data | S97: no data | T97: no data | U97: no data | V97: no data | W97: no data | X97: no data | Y97: =IF(AND(X97="processed",ISNUMBER(S97)),S97*O97,"") | Z97: =IF(ISNUMBER(K97),K97*O97,0) -> 618 | AA97: INTERIM: Redfin SFR sales (12 mo) x tier weight | AB97: 16867 | AC97: 12252 | AD97: 523 | AE97: 2018.7207 | AF97: 842.88543 | AG97: -0.020145693 | AH97: 1 | AI97: postal city of 100% of address points | AJ97: Pasadena | AK97: Pasadena
A98: 97 | B98: 95118 | C98: San Jose | D98: Santa Clara | E98: Peninsula & South Bay (Santa Clara / San Mateo) | G98: San Jose, CA | H98: 1129.1917 | I98: SFR | J98: 1690073.9 | K98: 203 | M98: =TRUE() -> TRUE | N98: =IF(H98="","",IF(H98>=Assumptions!$B$5,1,IF(H98>=Assumptions!$B$6,2,IF(H98>=Assumptions!$B$7,3,"")))) -> 1 | O98: =IF(N98=1,Assumptions!$B$8,IF(N98=2,Assumptions!$B$9,IF(N98=3,Assumptions!$B$10,0))) -> 3 | P98: no data | Q98: no data | R98: no data | S98: no data | T98: no data | U98: no data | V98: no data | W98: no data | X98: no data | Y98: =IF(AND(X98="processed",ISNUMBER(S98)),S98*O98,"") | Z98: =IF(ISNUMBER(K98),K98*O98,0) -> 609 | AA98: INTERIM: Redfin SFR sales (12 mo) x tier weight | AB98: 11715 | AC98: 8805 | AD98: 76 | AE98: 2428.0864 | AF98: 1119.4372 | AG98: -0.044099848 | AH98: 1 | AI98: postal city of 100% of address points | AJ98: San Jose | AK98: San Jose
A99: 98 | B99: 95060 | C99: Santa Cruz | D99: Santa Cruz | E99: Rest of California | F99: Downtown; Westside; Mission Hill Historic District | G99: Santa Cruz, CA | H99: 918.7305 | I99: SFR | J99: 1497027.2 | K99: 202 | M99: =TRUE() -> TRUE | N99: =IF(H99="","",IF(H99>=Assumptions!$B$5,1,IF(H99>=Assumptions!$B$6,2,IF(H99>=Assumptions!$B$7,3,"")))) -> 1 | O99: =IF(N99=1,Assumptions!$B$8,IF(N99=2,Assumptions!$B$9,IF(N99=3,Assumptions!$B$10,0))) -> 3 | P99: no data | Q99: no data | R99: no data | S99: no data | T99: no data | U99: no data | V99: no data | W99: no data | X99: no data | Y99: =IF(AND(X99="processed",ISNUMBER(S99)),S99*O99,"") | Z99: =IF(ISNUMBER(K99),K99*O99,0) -> 606 | AA99: INTERIM: Redfin SFR sales (12 mo) x tier weight | AB99: 19404 | AC99: 15485 | AD99: 3030 | AE99: 1828.9111 | AF99: 929.67539 | AG99: -0.013469324 | AH99: 0.96761561 | AI99: postal city of 97% of address points | AJ99: Santa Cruz | AK99: Santa Cruz
A100: 99 | B100: 92130 | C100: San Diego | D100: San Diego | E100: San Diego | F100: Carmel Valley; Pacific Highlands Ranch; Torrey Hills; Bosque Del Mar; Bougainvillea; Carmel Center; Carmel Creek; Carmel Knolls; Carmel Valley Creek; Carmel Valley Neighborhood 8b; Del Mar Mesa Estates; Del Mar Trails; Duck Pond Ranch; Greenbriar; Palacio Del Mar; Rancho Pacifica; Solana Highlands; Stratford; The Preserve at Del Mar Mesa; Torrey Glen; Ashley Falls; Carmel Country Highlands; Carmel Del Mar; Carmel View; Del Mar Highlands; Del Mar Mesa; Fairbanks Ranch Country Club; Gonzales Canyon; Ocean Air; Pacific Highlands Ranch Village; Rancho del Sol; San Dieguito (NCFUA Subarea-II); Santa Fe Summit; Sycramore Ridge | G100: San Diego, CA | H100: 830.50744 | I100: SFR | J100: 2482169.2 | K100: 201 | M100: =TRUE() -> TRUE | N100: =IF(H100="","",IF(H100>=Assumptions!$B$5,1,IF(H100>=Assumptions!$B$6,2,IF(H100>=Assumptions!$B$7,3,"")))) -> 1 | O100: =IF(N100=1,Assumptions!$B$8,IF(N100=2,Assumptions!$B$9,IF(N100=3,Assumptions!$B$10,0))) -> 3 | P100: no data | Q100: no data | R100: no data | S100: no data | T100: no data | U100: no data | V100: no data | W100: no data | X100: no data | Y100: =IF(AND(X100="processed",ISNUMBER(S100)),S100*O100,"") | Z100: =IF(ISNUMBER(K100),K100*O100,0) -> 603 | AA100: INTERIM: Redfin SFR sales (12 mo) x tier weight | AB100: 16257 | AC100: 13902 | AD100: 1081 | AE100: 2564.4326 | AF100: 875.15916 | AG100: 0.0062350337 | AH100: 1 | AI100: postal city of 100% of address points | AJ100: San Diego | AK100: San Diego
A101: 100 | B101: 95035 | C101: Milpitas | D101: Santa Clara | E101: Peninsula & South Bay (Santa Clara / San Mateo) | G101: San Jose, CA | H101: 993.60868 | I101: SFR | J101: 1640455.2 | K101: 201 | M101: =TRUE() -> TRUE | N101: =IF(H101="","",IF(H101>=Assumptions!$B$5,1,IF(H101>=Assumptions!$B$6,2,IF(H101>=Assumptions!$B$7,3,"")))) -> 1 | O101: =IF(N101=1,Assumptions!$B$8,IF(N101=2,Assumptions!$B$9,IF(N101=3,Assumptions!$B$10,0))) -> 3 | P101: no data | Q101: no data | R101: no data | S101: no data | T101: no data | U101: no data | V101: no data | W101: no data | X101: no data | Y101: =IF(AND(X101="processed",ISNUMBER(S101)),S101*O101,"") | Z101: =IF(ISNUMBER(K101),K101*O101,0) -> 603 | AA101: INTERIM: Redfin SFR sales (12 mo) x tier weight | AB101: 16051 | AC101: 14652 | AD101: 1850 | AE101: 2226.5283 | AF101: 997.60575 | AG101: -0.027033991 | AH101: 0.99908645 | AI101: postal city of 100% of address points | AJ101: Milpitas | AK101: Milpitas
A102: 101 | B102: 90505 | C102: Torrance | D102: Los Angeles | E102: Los Angeles County | F102: Southwood; Walteria | G102: Los Angeles, CA | H102: 846.14255 | I102: SFR | J102: 1538181.8 | K102: 198 | M102: =TRUE() -> TRUE | N102: =IF(H102="","",IF(H102>=Assumptions!$B$5,1,IF(H102>=Assumptions!$B$6,2,IF(H102>=Assumptions!$B$7,3,"")))) -> 1 | O102: =IF(N102=1,Assumptions!$B$8,IF(N102=2,Assumptions!$B$9,IF(N102=3,Assumptions!$B$10,0))) -> 3 | P102: no data | Q102: no data | R102: no data | S102: no data | T102: no data | U102: no data | V102: no data | W102: no data | X102: no data | Y102: =IF(AND(X102="processed",ISNUMBER(S102)),S102*O102,"") | Z102: =IF(ISNUMBER(K102),K102*O102,0) -> 594 | AA102: INTERIM: Redfin SFR sales (12 mo) x tier weight | AB102: 12057 | AC102: 9985 | AD102: 129 | AE102: 2286.3108 | AF102: 865.58942 | AG102: -0.011112527 | AH102: 1 | AI102: postal city of 100% of address points | AJ102: Torrance | AK102: Torrance
A103: 102 | B103: 92054 | C103: Oceanside | D103: San Diego | E103: San Diego | F103: Buccaneer Beach; Escondido Junction; Crown Heights; Downtown Oceanside; Fire Mountain; Seaside; South Oceanside | G103: San Diego, CA | H103: 742.01046 | I103: SFR | J103: 1351944.4 | K103: 198 | M103: =TRUE() -> TRUE | N103: =IF(H103="","",IF(H103>=Assumptions!$B$5,1,IF(H103>=Assumptions!$B$6,2,IF(H103>=Assumptions!$B$7,3,"")))) -> 1 | O103: =IF(N103=1,Assumptions!$B$8,IF(N103=2,Assumptions!$B$9,IF(N103=3,Assumptions!$B$10,0))) -> 3 | P103: no data | Q103: no data | R103: no data | S103: no data | T103: no data | U103: no data | V103: no data | W103: no data | X103: no data | Y103: =IF(AND(X103="processed",ISNUMBER(S103)),S103*O103,"") | Z103: =IF(ISNUMBER(K103),K103*O103,0) -> 594 | AA103: INTERIM: Redfin SFR sales (12 mo) x tier weight | AB103: 13148 | AC103: 10708 | AD103: 329 | AE103: 2153.7393 | AF103: 749.21136 | AG103: -0.054080811 | AH103: 0.9836984 | AI103: postal city of 100% of address points | AJ103: Oceanside | AK103: Oceanside
A104: 103 | B104: 91367 | C104: Woodland Hills | D104: Los Angeles | E104: Los Angeles County | F104: Warner Center | G104: Los Angeles, CA | H104: 639.89789 | I104: SFR | J104: 1396682.4 | K104: 296 | M104: =TRUE() -> TRUE | N104: =IF(H104="","",IF(H104>=Assumptions!$B$5,1,IF(H104>=Assumptions!$B$6,2,IF(H104>=Assumptions!$B$7,3,"")))) -> 2 | O104: =IF(N104=1,Assumptions!$B$8,IF(N104=2,Assumptions!$B$9,IF(N104=3,Assumptions!$B$10,0))) -> 2 | P104: no data | Q104: no data | R104: no data | S104: no data | T104: no data | U104: no data | V104: no data | W104: no data | X104: no data | Y104: =IF(AND(X104="processed",ISNUMBER(S104)),S104*O104,"") | Z104: =IF(ISNUMBER(K104),K104*O104,0) -> 592 | AA104: INTERIM: Redfin SFR sales (12 mo) x tier weight | AB104: 13598 | AC104: 10040 | AD104: 271 | AE104: 2927.4839 | AF104: 661.48902 | AG104: -0.02587867 | AH104: 1 | AI104: postal city of 100% of address points | AJ104: Woodland Hills | AK104: Los Angeles
...

Sheet By County
A1: Focus regions and every California county (live counts from 'All ZIPs')
A3: Region / county | B3: Counties | C3: ZIPs | D3: Tier 1 ZIPs | E3: Tier 2 ZIPs | F3: Tier 3 ZIPs | G3: Any-tier ZIPs | H3: SFR homes sold 12 mo (tiered ZIPs) | I3: Median of ZIP $/sq ft | J3: Parcel data status
A4: FOCUS REGIONS
A5: Orange County | B5: Orange | C5: =COUNTIF('All ZIPs'!$E$2:$E$1878,"Orange County") -> 88 | D5: =COUNTIFS('All ZIPs'!$E$2:$E$1878,"Orange County",'All ZIPs'!$N$2:$N$1878,1) -> 43 | E5: =COUNTIFS('All ZIPs'!$E$2:$E$1878,"Orange County",'All ZIPs'!$N$2:$N$1878,2) -> 40 | F5: =COUNTIFS('All ZIPs'!$E$2:$E$1878,"Orange County",'All ZIPs'!$N$2:$N$1878,3) -> 4 | G5: =SUM(D5:F5) -> 87 | H5: =SUMIFS('All ZIPs'!$K$2:$K$1878,'All ZIPs'!$E$2:$E$1878,"Orange County",'All ZIPs'!$N$2:$N$1878,">0") -> 13272 | I5: 699.61785 | J5: Orange: NO DATA ('portal' source needs a manual export to data/parcels/orange.gpkg)
A6: Los Angeles County | B6: Los Angeles | C6: =COUNTIF('All ZIPs'!$E$2:$E$1878,"Los Angeles County") -> 292 | D6: =COUNTIFS('All ZIPs'!$E$2:$E$1878,"Los Angeles County",'All ZIPs'!$N$2:$N$1878,1) -> 104 | E6: =COUNTIFS('All ZIPs'!$E$2:$E$1878,"Los Angeles County",'All ZIPs'!$N$2:$N$1878,2) -> 60 | F6: =COUNTIFS('All ZIPs'!$E$2:$E$1878,"Los Angeles County",'All ZIPs'!$N$2:$N$1878,3) -> 85 | G6: =SUM(D6:F6) -> 249 | H6: =SUMIFS('All ZIPs'!$K$2:$K$1878,'All ZIPs'!$E$2:$E$1878,"Los Angeles County",'All ZIPs'!$N$2:$N$1878,">0") -> 29492 | I6: 630.83209 | J6: Los Angeles: NO DATA (BLOCKED by this environment's network policy (proxy 403))
A7: San Francisco | B7: San Francisco | C7: =COUNTIF('All ZIPs'!$E$2:$E$1878,"San Francisco") -> 27 | D7: =COUNTIFS('All ZIPs'!$E$2:$E$1878,"San Francisco",'All ZIPs'!$N$2:$N$1878,1) -> 25 | E7: =COUNTIFS('All ZIPs'!$E$2:$E$1878,"San Francisco",'All ZIPs'!$N$2:$N$1878,2) -> 1 | F7: =COUNTIFS('All ZIPs'!$E$2:$E$1878,"San Francisco",'All ZIPs'!$N$2:$N$1878,3) -> 0 | G7: =SUM(D7:F7) -> 26 | H7: =SUMIFS('All ZIPs'!$K$2:$K$1878,'All ZIPs'!$E$2:$E$1878,"San Francisco",'All ZIPs'!$N$2:$N$1878,">0") -> 2990 | I7: 1095.5127 | J7: San Francisco: NO DATA ('portal' source needs a manual export to data/parcels/san_francisco.gpkg)
A8: Berkeley / Oakland / Alameda County | B8: Alameda | C8: =COUNTIF('All ZIPs'!$E$2:$E$1878,"Berkeley / Oakland / Alameda County") -> 49 | D8: =COUNTIFS('All ZIPs'!$E$2:$E$1878,"Berkeley / Oakland / Alameda County",'All ZIPs'!$N$2:$N$1878,1) -> 24 | E8: =COUNTIFS('All ZIPs'!$E$2:$E$1878,"Berkeley / Oakland / Alameda County",'All ZIPs'!$N$2:$N$1878,2) -> 14 | F8: =COUNTIFS('All ZIPs'!$E$2:$E$1878,"Berkeley / Oakland / Alameda County",'All ZIPs'!$N$2:$N$1878,3) -> 2 | G8: =SUM(D8:F8) -> 40 | H8: =SUMIFS('All ZIPs'!$K$2:$K$1878,'All ZIPs'!$E$2:$E$1878,"Berkeley / Oakland / Alameda County",'All ZIPs'!$N$2:$N$1878,">0") -> 6865 | I8: 704.67241 | J8: Alameda: NO DATA ('portal' source needs a manual export to data/parcels/alameda.gpkg)
A9: Peninsula & South Bay (Santa Clara / San Mateo) | B9: Santa Clara, San Mateo | C9: =COUNTIF('All ZIPs'!$E$2:$E$1878,"Peninsula & South Bay (Santa Clara / San Mateo)") -> 87 | D9: =COUNTIFS('All ZIPs'!$E$2:$E$1878,"Peninsula & South Bay (Santa Clara / San Mateo)",'All ZIPs'!$N$2:$N$1878,1) -> 77 | E9: =COUNTIFS('All ZIPs'!$E$2:$E$1878,"Peninsula & South Bay (Santa Clara / San Mateo)",'All ZIPs'!$N$2:$N$1878,2) -> 2 | F9: =COUNTIFS('All ZIPs'!$E$2:$E$1878,"Peninsula & South Bay (Santa Clara / San Mateo)",'All ZIPs'!$N$2:$N$1878,3) -> 2 | G9: =SUM(D9:F9) -> 81 | H9: =SUMIFS('All ZIPs'!$K$2:$K$1878,'All ZIPs'!$E$2:$E$1878,"Peninsula & South Bay (Santa Clara / San Mateo)",'All ZIPs'!$N$2:$N$1878,">0") -> 11827 | I9: 1102.9571 | J9: Santa Clara: NO DATA ('portal' source needs a manual export to data/parcels/santa_clara.gpkg); San Mateo: NO DATA ('portal' source needs a manual export to data/parcels/san_mateo.gpkg)
A10: Marin | B10: Marin | C10: =COUNTIF('All ZIPs'!$E$2:$E$1878,"Marin") -> 29 | D10: =COUNTIFS('All ZIPs'!$E$2:$E$1878,"Marin",'All ZIPs'!$N$2:$N$1878,1) -> 20 | E10: =COUNTIFS('All ZIPs'!$E$2:$E$1878,"Marin",'All ZIPs'!$N$2:$N$1878,2) -> 4 | F10: =COUNTIFS('All ZIPs'!$E$2:$E$1878,"Marin",'All ZIPs'!$N$2:$N$1878,3) -> 2 | G10: =SUM(D10:F10) -> 26 | H10: =SUMIFS('All ZIPs'!$K$2:$K$1878,'All ZIPs'!$E$2:$E$1878,"Marin",'All ZIPs'!$N$2:$N$1878,">0") -> 1881 | I10: 880.84278 | J10: Marin: NO DATA ('portal' source needs a manual export to data/parcels/marin.gpkg)
A11: San Diego | B11: San Diego | C11: =COUNTIF('All ZIPs'!$E$2:$E$1878,"San Diego") -> 106 | D11: =COUNTIFS('All ZIPs'!$E$2:$E$1878,"San Diego",'All ZIPs'!$N$2:$N$1878,1) -> 31 | E11: =COUNTIFS('All ZIPs'!$E$2:$E$1878,"San Diego",'All ZIPs'!$N$2:$N$1878,2) -> 12 | F11: =COUNTIFS('All ZIPs'!$E$2:$E$1878,"San Diego",'All ZIPs'!$N$2:$N$1878,3) -> 26 | G11: =SUM(D11:F11) -> 69 | H11: =SUMIFS('All ZIPs'!$K$2:$K$1878,'All ZIPs'!$E$2:$E$1878,"San Diego",'All ZIPs'!$N$2:$N$1878,">0") -> 11468 | I11: 558.32242 | J11: San Diego: NO DATA (BLOCKED by this environment's network policy (proxy 403))
A12: Ventura | B12: Ventura | C12: =COUNTIF('All ZIPs'!$E$2:$E$1878,"Ventura") -> 29 | D12: =COUNTIFS('All ZIPs'!$E$2:$E$1878,"Ventura",'All ZIPs'!$N$2:$N$1878,1) -> 4 | E12: =COUNTIFS('All ZIPs'!$E$2:$E$1878,"Ventura",'All ZIPs'!$N$2:$N$1878,2) -> 2 | F12: =COUNTIFS('All ZIPs'!$E$2:$E$1878,"Ventura",'All ZIPs'!$N$2:$N$1878,3) -> 9 | G12: =SUM(D12:F12) -> 15 | H12: =SUMIFS('All ZIPs'!$K$2:$K$1878,'All ZIPs'!$E$2:$E$1878,"Ventura",'All ZIPs'!$N$2:$N$1878,">0") -> 2910 | I12: 510.59736 | J12: Ventura: NO DATA ('portal' source needs a manual export to data/parcels/ventura.gpkg)
A13: Sacramento | B13: Sacramento | C13: =COUNTIF('All ZIPs'!$E$2:$E$1878,"Sacramento") -> 54 | D13: =COUNTIFS('All ZIPs'!$E$2:$E$1878,"Sacramento",'All ZIPs'!$N$2:$N$1878,1) -> 0 | E13: =COUNTIFS('All ZIPs'!$E$2:$E$1878,"Sacramento",'All ZIPs'!$N$2:$N$1878,2) -> 0 | F13: =COUNTIFS('All ZIPs'!$E$2:$E$1878,"Sacramento",'All ZIPs'!$N$2:$N$1878,3) -> 3 | G13: =SUM(D13:F13) -> 3 | H13: =SUMIFS('All ZIPs'!$K$2:$K$1878,'All ZIPs'!$E$2:$E$1878,"Sacramento",'All ZIPs'!$N$2:$N$1878,">0") -> 494 | I13: 336.10695 | J13: Sacramento: NO DATA ('portal' source needs a manual export to data/parcels/sacramento.gpkg)
A14: Inland Empire (Riverside / San Bernardino) | B14: Riverside, San Bernardino | C14: =COUNTIF('All ZIPs'!$E$2:$E$1878,"Inland Empire (Riverside / San Bernardino)") -> 159 | D14: =COUNTIFS('All ZIPs'!$E$2:$E$1878,"Inland Empire (Riverside / San Bernardino)",'All ZIPs'!$N$2:$N$1878,1) -> 0 | E14: =COUNTIFS('All ZIPs'!$E$2:$E$1878,"Inland Empire (Riverside / San Bernardino)",'All ZIPs'!$N$2:$N$1878,2) -> 2 | F14: =COUNTIFS('All ZIPs'!$E$2:$E$1878,"Inland Empire (Riverside / San Bernardino)",'All ZIPs'!$N$2:$N$1878,3) -> 2 | G14: =SUM(D14:F14) -> 4 | H14: =SUMIFS('All ZIPs'!$K$2:$K$1878,'All ZIPs'!$E$2:$E$1878,"Inland Empire (Riverside / San Bernardino)",'All ZIPs'!$N$2:$N$1878,">0") -> 879 | I14: 312.9133 | J14: Riverside: NO DATA ('portal' source needs a manual export to data/parcels/riverside.gpkg); San Bernardino: NO DATA ('portal' source needs a manual export to data/parcels/san_bernardino.gpkg)
A15: Rest of California | B15: all other counties | C15: =COUNTIF('All ZIPs'!$E$2:$E$1878,"Rest of California") -> 843 | D15: =COUNTIFS('All ZIPs'!$E$2:$E$1878,"Rest of California",'All ZIPs'!$N$2:$N$1878,1) -> 61 | E15: =COUNTIFS('All ZIPs'!$E$2:$E$1878,"Rest of California",'All ZIPs'!$N$2:$N$1878,2) -> 32 | F15: =COUNTIFS('All ZIPs'!$E$2:$E$1878,"Rest of California",'All ZIPs'!$N$2:$N$1878,3) -> 43 | G15: =SUM(D15:F15) -> 136 | H15: =SUMIFS('All ZIPs'!$K$2:$K$1878,'All ZIPs'!$E$2:$E$1878,"Rest of California",'All ZIPs'!$N$2:$N$1878,">0") -> 13396 | I15: 297.06673 | J15: all other counties: n/a
A17: ALL COUNTIES
A18: (no ZCTA: PO-box / unique ZIP) | B18: (no ZCTA: PO-box / unique ZIP) | C18: =COUNTIF('All ZIPs'!$D$2:$D$1878,"(no ZCTA: PO-box / unique ZIP)") -> 114 | D18: =COUNTIFS('All ZIPs'!$D$2:$D$1878,"(no ZCTA: PO-box / unique ZIP)",'All ZIPs'!$N$2:$N$1878,1) -> 38 | E18: =COUNTIFS('All ZIPs'!$D$2:$D$1878,"(no ZCTA: PO-box / unique ZIP)",'All ZIPs'!$N$2:$N$1878,2) -> 17 | F18: =COUNTIFS('All ZIPs'!$D$2:$D$1878,"(no ZCTA: PO-box / unique ZIP)",'All ZIPs'!$N$2:$N$1878,3) -> 17 | G18: =SUM(D18:F18) -> 72 | H18: =SUMIFS('All ZIPs'!$K$2:$K$1878,'All ZIPs'!$D$2:$D$1878,"(no ZCTA: PO-box / unique ZIP)",'All ZIPs'!$N$2:$N$1878,">0") -> 354 | I18: 585.16128 | J18: (no ZCTA: PO-box / unique ZIP): n/a
A19: Alameda | B19: Alameda | C19: =COUNTIF('All ZIPs'!$D$2:$D$1878,"Alameda") -> 49 | D19: =COUNTIFS('All ZIPs'!$D$2:$D$1878,"Alameda",'All ZIPs'!$N$2:$N$1878,1) -> 24 | E19: =COUNTIFS('All ZIPs'!$D$2:$D$1878,"Alameda",'All ZIPs'!$N$2:$N$1878,2) -> 14 | F19: =COUNTIFS('All ZIPs'!$D$2:$D$1878,"Alameda",'All ZIPs'!$N$2:$N$1878,3) -> 2 | G19: =SUM(D19:F19) -> 40 | H19: =SUMIFS('All ZIPs'!$K$2:$K$1878,'All ZIPs'!$D$2:$D$1878,"Alameda",'All ZIPs'!$N$2:$N$1878,">0") -> 6865 | I19: 704.67241 | J19: Alameda: NO DATA ('portal' source needs a manual export to data/parcels/alameda.gpkg)
A20: Alpine | B20: Alpine | C20: =COUNTIF('All ZIPs'!$D$2:$D$1878,"Alpine") -> 3 | D20: =COUNTIFS('All ZIPs'!$D$2:$D$1878,"Alpine",'All ZIPs'!$N$2:$N$1878,1) -> 0 | E20: =COUNTIFS('All ZIPs'!$D$2:$D$1878,"Alpine",'All ZIPs'!$N$2:$N$1878,2) -> 0 | F20: =COUNTIFS('All ZIPs'!$D$2:$D$1878,"Alpine",'All ZIPs'!$N$2:$N$1878,3) -> 1 | G20: =SUM(D20:F20) -> 1 | H20: =SUMIFS('All ZIPs'!$K$2:$K$1878,'All ZIPs'!$D$2:$D$1878,"Alpine",'All ZIPs'!$N$2:$N$1878,">0") -> 2 | I20: 508.11529 | J20: Alpine: NO DATA (no automated source configured; place a county or Regrid export at data/parcels/alpine.gpkg)
A21: Amador | B21: Amador | C21: =COUNTIF('All ZIPs'!$D$2:$D$1878,"Amador") -> 11 | D21: =COUNTIFS('All ZIPs'!$D$2:$D$1878,"Amador",'All ZIPs'!$N$2:$N$1878,1) -> 0 | E21: =COUNTIFS('All ZIPs'!$D$2:$D$1878,"Amador",'All ZIPs'!$N$2:$N$1878,2) -> 0 | F21: =COUNTIFS('All ZIPs'!$D$2:$D$1878,"Amador",'All ZIPs'!$N$2:$N$1878,3) -> 0 | G21: =SUM(D21:F21) -> 0 | H21: =SUMIFS('All ZIPs'!$K$2:$K$1878,'All ZIPs'!$D$2:$D$1878,"Amador",'All ZIPs'!$N$2:$N$1878,">0") -> 0 | J21: Amador: NO DATA (no automated source configured; place a county or Regrid export at data/parcels/amador.gpkg)
A22: Butte | B22: Butte | C22: =COUNTIF('All ZIPs'!$D$2:$D$1878,"Butte") -> 18 | D22: =COUNTIFS('All ZIPs'!$D$2:$D$1878,"Butte",'All ZIPs'!$N$2:$N$1878,1) -> 0 | E22: =COUNTIFS('All ZIPs'!$D$2:$D$1878,"Butte",'All ZIPs'!$N$2:$N$1878,2) -> 0 | F22: =COUNTIFS('All ZIPs'!$D$2:$D$1878,"Butte",'All ZIPs'!$N$2:$N$1878,3) -> 0 | G22: =SUM(D22:F22) -> 0 | H22: =SUMIFS('All ZIPs'!$K$2:$K$1878,'All ZIPs'!$D$2:$D$1878,"Butte",'All ZIPs'!$N$2:$N$1878,">0") -> 0 | I22: 242.91692 | J22: Butte: NO DATA (no automated source configured; place a county or Regrid export at data/parcels/butte.gpkg)
A23: Calaveras | B23: Calaveras | C23: =COUNTIF('All ZIPs'!$D$2:$D$1878,"Calaveras") -> 18 | D23: =COUNTIFS('All ZIPs'!$D$2:$D$1878,"Calaveras",'All ZIPs'!$N$2:$N$1878,1) -> 0 | E23: =COUNTIFS('All ZIPs'!$D$2:$D$1878,"Calaveras",'All ZIPs'!$N$2:$N$1878,2) -> 0 | F23: =COUNTIFS('All ZIPs'!$D$2:$D$1878,"Calaveras",'All ZIPs'!$N$2:$N$1878,3) -> 0 | G23: =SUM(D23:F23) -> 0 | H23: =SUMIFS('All ZIPs'!$K$2:$K$1878,'All ZIPs'!$D$2:$D$1878,"Calaveras",'All ZIPs'!$N$2:$N$1878,">0") -> 0 | J23: Calaveras: NO DATA (no automated source configured; place a county or Regrid export at data/parcels/calaveras.gpkg)
A24: Colusa | B24: Colusa | C24: =COUNTIF('All ZIPs'!$D$2:$D$1878,"Colusa") -> 7 | D24: =COUNTIFS('All ZIPs'!$D$2:$D$1878,"Colusa",'All ZIPs'!$N$2:$N$1878,1) -> 0 | E24: =COUNTIFS('All ZIPs'!$D$2:$D$1878,"Colusa",'All ZIPs'!$N$2:$N$1878,2) -> 0 | F24: =COUNTIFS('All ZIPs'!$D$2:$D$1878,"Colusa",'All ZIPs'!$N$2:$N$1878,3) -> 0 | G24: =SUM(D24:F24) -> 0 | H24: =SUMIFS('All ZIPs'!$K$2:$K$1878,'All ZIPs'!$D$2:$D$1878,"Colusa",'All ZIPs'!$N$2:$N$1878,">0") -> 0 | J24: Colusa: NO DATA (no automated source configured; place a county or Regrid export at data/parcels/colusa.gpkg)
A25: Contra Costa | B25: Contra Costa | C25: =COUNTIF('All ZIPs'!$D$2:$D$1878,"Contra Costa") -> 44 | D25: =COUNTIFS('All ZIPs'!$D$2:$D$1878,"Contra Costa",'All ZIPs'!$N$2:$N$1878,1) -> 16 | E25: =COUNTIFS('All ZIPs'!$D$2:$D$1878,"Contra Costa",'All ZIPs'!$N$2:$N$1878,2) -> 1 | F25: =COUNTIFS('All ZIPs'!$D$2:$D$1878,"Contra Costa",'All ZIPs'!$N$2:$N$1878,3) -> 9 | G25: =SUM(D25:F25) -> 26 | H25: =SUMIFS('All ZIPs'!$K$2:$K$1878,'All ZIPs'!$D$2:$D$1878,"Contra Costa",'All ZIPs'!$N$2:$N$1878,">0") -> 4231 | I25: 524.66568 | J25: Contra Costa: NO DATA (SFR use-code rule unverified for this source; not processed)
A26: Del Norte | B26: Del Norte | C26: =COUNTIF('All ZIPs'!$D$2:$D$1878,"Del Norte") -> 4 | D26: =COUNTIFS('All ZIPs'!$D$2:$D$1878,"Del Norte",'All ZIPs'!$N$2:$N$1878,1) -> 0 | E26: =COUNTIFS('All ZIPs'!$D$2:$D$1878,"Del Norte",'All ZIPs'!$N$2:$N$1878,2) -> 0 | F26: =COUNTIFS('All ZIPs'!$D$2:$D$1878,"Del Norte",'All ZIPs'!$N$2:$N$1878,3) -> 0 | G26: =SUM(D26:F26) -> 0 | H26: =SUMIFS('All ZIPs'!$K$2:$K$1878,'All ZIPs'!$D$2:$D$1878,"Del Norte",'All ZIPs'!$N$2:$N$1878,">0") -> 0 | I26: 264.53165 | J26: Del Norte: NO DATA (no automated source configured; place a county or Regrid export at data/parcels/del_norte.gpkg)
A27: El Dorado | B27: El Dorado | C27: =COUNTIF('All ZIPs'!$D$2:$D$1878,"El Dorado") -> 22 | D27: =COUNTIFS('All ZIPs'!$D$2:$D$1878,"El Dorado",'All ZIPs'!$N$2:$N$1878,1) -> 0 | E27: =COUNTIFS('All ZIPs'!$D$2:$D$1878,"El Dorado",'All ZIPs'!$N$2:$N$1878,2) -> 2 | F27: =COUNTIFS('All ZIPs'!$D$2:$D$1878,"El Dorado",'All ZIPs'!$N$2:$N$1878,3) -> 0 | G27: =SUM(D27:F27) -> 2 | H27: =SUMIFS('All ZIPs'!$K$2:$K$1878,'All ZIPs'!$D$2:$D$1878,"El Dorado",'All ZIPs'!$N$2:$N$1878,">0") -> 84 | I27: 307.00016 | J27: El Dorado: NO DATA (no automated source configured; place a county or Regrid export at data/parcels/el_dorado.gpkg)
A28: Fresno | B28: Fresno | C28: =COUNTIF('All ZIPs'!$D$2:$D$1878,"Fresno") -> 54 | D28: =COUNTIFS('All ZIPs'!$D$2:$D$1878,"Fresno",'All ZIPs'!$N$2:$N$1878,1) -> 0 | E28: =COUNTIFS('All ZIPs'!$D$2:$D$1878,"Fresno",'All ZIPs'!$N$2:$N$1878,2) -> 0 | F28: =COUNTIFS('All ZIPs'!$D$2:$D$1878,"Fresno",'All ZIPs'!$N$2:$N$1878,3) -> 0 | G28: =SUM(D28:F28) -> 0 | H28: =SUMIFS('All ZIPs'!$K$2:$K$1878,'All ZIPs'!$D$2:$D$1878,"Fresno",'All ZIPs'!$N$2:$N$1878,">0") -> 0 | I28: 253.43122 | J28: Fresno: NO DATA (no automated source configured; place a county or Regrid export at data/parcels/fresno.gpkg)
A29: Glenn | B29: Glenn | C29: =COUNTIF('All ZIPs'!$D$2:$D$1878,"Glenn") -> 6 | D29: =COUNTIFS('All ZIPs'!$D$2:$D$1878,"Glenn",'All ZIPs'!$N$2:$N$1878,1) -> 0 | E29: =COUNTIFS('All ZIPs'!$D$2:$D$1878,"Glenn",'All ZIPs'!$N$2:$N$1878,2) -> 0 | F29: =COUNTIFS('All ZIPs'!$D$2:$D$1878,"Glenn",'All ZIPs'!$N$2:$N$1878,3) -> 0 | G29: =SUM(D29:F29) -> 0 | H29: =SUMIFS('All ZIPs'!$K$2:$K$1878,'All ZIPs'!$D$2:$D$1878,"Glenn",'All ZIPs'!$N$2:$N$1878,">0") -> 0 | J29: Glenn: NO DATA (no automated source configured; place a county or Regrid export at data/parcels/glenn.gpkg)
A30: Humboldt | B30: Humboldt | C30: =COUNTIF('All ZIPs'!$D$2:$D$1878,"Humboldt") -> 35 | D30: =COUNTIFS('All ZIPs'!$D$2:$D$1878,"Humboldt",'All ZIPs'!$N$2:$N$1878,1) -> 1 | E30: =COUNTIFS('All ZIPs'!$D$2:$D$1878,"Humboldt",'All ZIPs'!$N$2:$N$1878,2) -> 0 | F30: =COUNTIFS('All ZIPs'!$D$2:$D$1878,"Humboldt",'All ZIPs'!$N$2:$N$1878,3) -> 0 | G30: =SUM(D30:F30) -> 1 | H30: =SUMIFS('All ZIPs'!$K$2:$K$1878,'All ZIPs'!$D$2:$D$1878,"Humboldt",'All ZIPs'!$N$2:$N$1878,">0") -> 2 | I30: 275.60004 | J30: Humboldt: NO DATA (no automated source configured; place a county or Regrid export at data/parcels/humboldt.gpkg)
A31: Imperial | B31: Imperial | C31: =COUNTIF('All ZIPs'!$D$2:$D$1878,"Imperial") -> 16 | D31: =COUNTIFS('All ZIPs'!$D$2:$D$1878,"Imperial",'All ZIPs'!$N$2:$N$1878,1) -> 0 | E31: =COUNTIFS('All ZIPs'!$D$2:$D$1878,"Imperial",'All ZIPs'!$N$2:$N$1878,2) -> 0 | F31: =COUNTIFS('All ZIPs'!$D$2:$D$1878,"Imperial",'All ZIPs'!$N$2:$N$1878,3) -> 0 | G31: =SUM(D31:F31) -> 0 | H31: =SUMIFS('All ZIPs'!$K$2:$K$1878,'All ZIPs'!$D$2:$D$1878,"Imperial",'All ZIPs'!$N$2:$N$1878,">0") -> 0 | I31: 236.8152 | J31: Imperial: NO DATA (no automated source configured; place a county or Regrid export at data/parcels/imperial.gpkg)
A32: Inyo | B32: Inyo | C32: =COUNTIF('All ZIPs'!$D$2:$D$1878,"Inyo") -> 10 | D32: =COUNTIFS('All ZIPs'!$D$2:$D$1878,"Inyo",'All ZIPs'!$N$2:$N$1878,1) -> 0 | E32: =COUNTIFS('All ZIPs'!$D$2:$D$1878,"Inyo",'All ZIPs'!$N$2:$N$1878,2) -> 0 | F32: =COUNTIFS('All ZIPs'!$D$2:$D$1878,"Inyo",'All ZIPs'!$N$2:$N$1878,3) -> 0 | G32: =SUM(D32:F32) -> 0 | H32: =SUMIFS('All ZIPs'!$K$2:$K$1878,'All ZIPs'!$D$2:$D$1878,"Inyo",'All ZIPs'!$N$2:$N$1878,">0") -> 0 | J32: Inyo: NO DATA (no automated source configured; place a county or Regrid export at data/parcels/inyo.gpkg)
A33: Kern | B33: Kern | C33: =COUNTIF('All ZIPs'!$D$2:$D$1878,"Kern") -> 45 | D33: =COUNTIFS('All ZIPs'!$D$2:$D$1878,"Kern",'All ZIPs'!$N$2:$N$1878,1) -> 0 | E33: =COUNTIFS('All ZIPs'!$D$2:$D$1878,"Kern",'All ZIPs'!$N$2:$N$1878,2) -> 0 | F33: =COUNTIFS('All ZIPs'!$D$2:$D$1878,"Kern",'All ZIPs'!$N$2:$N$1878,3) -> 0 | G33: =SUM(D33:F33) -> 0 | H33: =SUMIFS('All ZIPs'!$K$2:$K$1878,'All ZIPs'!$D$2:$D$1878,"Kern",'All ZIPs'!$N$2:$N$1878,">0") -> 0 | I33: 232.32936 | J33: Kern: NO DATA (no automated source configured; place a county or Regrid export at data/parcels/kern.gpkg)
A34: Kings | B34: Kings | C34: =COUNTIF('All ZIPs'!$D$2:$D$1878,"Kings") -> 6 | D34: =COUNTIFS('All ZIPs'!$D$2:$D$1878,"Kings",'All ZIPs'!$N$2:$N$1878,1) -> 0 | E34: =COUNTIFS('All ZIPs'!$D$2:$D$1878,"Kings",'All ZIPs'!$N$2:$N$1878,2) -> 0 | F34: =COUNTIFS('All ZIPs'!$D$2:$D$1878,"Kings",'All ZIPs'!$N$2:$N$1878,3) -> 0 | G34: =SUM(D34:F34) -> 0 | H34: =SUMIFS('All ZIPs'!$K$2:$K$1878,'All ZIPs'!$D$2:$D$1878,"Kings",'All ZIPs'!$N$2:$N$1878,">0") -> 0 | I34: 231.62153 | J34: Kings: NO DATA (no automated source configured; place a county or Regrid export at data/parcels/kings.gpkg)
A35: Lake | B35: Lake | C35: =COUNTIF('All ZIPs'!$D$2:$D$1878,"Lake") -> 14 | D35: =COUNTIFS('All ZIPs'!$D$2:$D$1878,"Lake",'All ZIPs'!$N$2:$N$1878,1) -> 0 | E35: =COUNTIFS('All ZIPs'!$D$2:$D$1878,"Lake",'All ZIPs'!$N$2:$N$1878,2) -> 0 | F35: =COUNTIFS('All ZIPs'!$D$2:$D$1878,"Lake",'All ZIPs'!$N$2:$N$1878,3) -> 0 | G35: =SUM(D35:F35) -> 0 | H35: =SUMIFS('All ZIPs'!$K$2:$K$1878,'All ZIPs'!$D$2:$D$1878,"Lake",'All ZIPs'!$N$2:$N$1878,">0") -> 0 | I35: 216.4961 | J35: Lake: NO DATA (no automated source configured; place a county or Regrid export at data/parcels/lake.gpkg)
A36: Lassen | B36: Lassen | C36: =COUNTIF('All ZIPs'!$D$2:$D$1878,"Lassen") -> 16 | D36: =COUNTIFS('All ZIPs'!$D$2:$D$1878,"Lassen",'All ZIPs'!$N$2:$N$1878,1) -> 0 | E36: =COUNTIFS('All ZIPs'!$D$2:$D$1878,"Lassen",'All ZIPs'!$N$2:$N$1878,2) -> 0 | F36: =COUNTIFS('All ZIPs'!$D$2:$D$1878,"Lassen",'All ZIPs'!$N$2:$N$1878,3) -> 0 | G36: =SUM(D36:F36) -> 0 | H36: =SUMIFS('All ZIPs'!$K$2:$K$1878,'All ZIPs'!$D$2:$D$1878,"Lassen",'All ZIPs'!$N$2:$N$1878,">0") -> 0 | I36: 159.87188 | J36: Lassen: NO DATA (no automated source configured; place a county or Regrid export at data/parcels/lassen.gpkg)
A37: Los Angeles | B37: Los Angeles | C37: =COUNTIF('All ZIPs'!$D$2:$D$1878,"Los Angeles") -> 292 | D37: =COUNTIFS('All ZIPs'!$D$2:$D$1878,"Los Angeles",'All ZIPs'!$N$2:$N$1878,1) -> 104 | E37: =COUNTIFS('All ZIPs'!$D$2:$D$1878,"Los Angeles",'All ZIPs'!$N$2:$N$1878,2) -> 60 | F37: =COUNTIFS('All ZIPs'!$D$2:$D$1878,"Los Angeles",'All ZIPs'!$N$2:$N$1878,3) -> 85 | G37: =SUM(D37:F37) -> 249 | H37: =SUMIFS('All ZIPs'!$K$2:$K$1878,'All ZIPs'!$D$2:$D$1878,"Los Angeles",'All ZIPs'!$N$2:$N$1878,">0") -> 29492 | I37: 630.83209 | J37: Los Angeles: NO DATA (BLOCKED by this environment's network policy (proxy 403))
A38: Madera | B38: Madera | C38: =COUNTIF('All ZIPs'!$D$2:$D$1878,"Madera") -> 13 | D38: =COUNTIFS('All ZIPs'!$D$2:$D$1878,"Madera",'All ZIPs'!$N$2:$N$1878,1) -> 0 | E38: =COUNTIFS('All ZIPs'!$D$2:$D$1878,"Madera",'All ZIPs'!$N$2:$N$1878,2) -> 0 | F38: =COUNTIFS('All ZIPs'!$D$2:$D$1878,"Madera",'All ZIPs'!$N$2:$N$1878,3) -> 0 | G38: =SUM(D38:F38) -> 0 | H38: =SUMIFS('All ZIPs'!$K$2:$K$1878,'All ZIPs'!$D$2:$D$1878,"Madera",'All ZIPs'!$N$2:$N$1878,">0") -> 0 | I38: 249.00532 | J38: Madera: NO DATA (no automated source configured; place a county or Regrid export at data/parcels/madera.gpkg)
A39: Marin | B39: Marin | C39: =COUNTIF('All ZIPs'!$D$2:$D$1878,"Marin") -> 29 | D39: =COUNTIFS('All ZIPs'!$D$2:$D$1878,"Marin",'All ZIPs'!$N$2:$N$1878,1) -> 20 | E39: =COUNTIFS('All ZIPs'!$D$2:$D$1878,"Marin",'All ZIPs'!$N$2:$N$1878,2) -> 4 | F39: =COUNTIFS('All ZIPs'!$D$2:$D$1878,"Marin",'All ZIPs'!$N$2:$N$1878,3) -> 2 | G39: =SUM(D39:F39) -> 26 | H39: =SUMIFS('All ZIPs'!$K$2:$K$1878,'All ZIPs'!$D$2:$D$1878,"Marin",'All ZIPs'!$N$2:$N$1878,">0") -> 1881 | I39: 880.84278 | J39: Marin: NO DATA ('portal' source needs a manual export to data/parcels/marin.gpkg)
A40: Mariposa | B40: Mariposa | C40: =COUNTIF('All ZIPs'!$D$2:$D$1878,"Mariposa") -> 8 | D40: =COUNTIFS('All ZIPs'!$D$2:$D$1878,"Mariposa",'All ZIPs'!$N$2:$N$1878,1) -> 0 | E40: =COUNTIFS('All ZIPs'!$D$2:$D$1878,"Mariposa",'All ZIPs'!$N$2:$N$1878,2) -> 0 | F40: =COUNTIFS('All ZIPs'!$D$2:$D$1878,"Mariposa",'All ZIPs'!$N$2:$N$1878,3) -> 0 | G40: =SUM(D40:F40) -> 0 | H40: =SUMIFS('All ZIPs'!$K$2:$K$1878,'All ZIPs'!$D$2:$D$1878,"Mariposa",'All ZIPs'!$N$2:$N$1878,">0") -> 0 | J40: Mariposa: NO DATA (no automated source configured; place a county or Regrid export at data/parcels/mariposa.gpkg)
A41: Mendocino | B41: Mendocino | C41: =COUNTIF('All ZIPs'!$D$2:$D$1878,"Mendocino") -> 26 | D41: =COUNTIFS('All ZIPs'!$D$2:$D$1878,"Mendocino",'All ZIPs'!$N$2:$N$1878,1) -> 0 | E41: =COUNTIFS('All ZIPs'!$D$2:$D$1878,"Mendocino",'All ZIPs'!$N$2:$N$1878,2) -> 1 | F41: =COUNTIFS('All ZIPs'!$D$2:$D$1878,"Mendocino",'All ZIPs'!$N$2:$N$1878,3) -> 3 | G41: =SUM(D41:F41) -> 4 | H41: =SUMIFS('All ZIPs'!$K$2:$K$1878,'All ZIPs'!$D$2:$D$1878,"Mendocino",'All ZIPs'!$N$2:$N$1878,">0") -> 35 | I41: 356.60347 | J41: Mendocino: NO DATA (no automated source configured; place a county or Regrid export at data/parcels/mendocino.gpkg)
A42: Merced | B42: Merced | C42: =COUNTIF('All ZIPs'!$D$2:$D$1878,"Merced") -> 19 | D42: =COUNTIFS('All ZIPs'!$D$2:$D$1878,"Merced",'All ZIPs'!$N$2:$N$1878,1) -> 0 | E42: =COUNTIFS('All ZIPs'!$D$2:$D$1878,"Merced",'All ZIPs'!$N$2:$N$1878,2) -> 0 | F42: =COUNTIFS('All ZIPs'!$D$2:$D$1878,"Merced",'All ZIPs'!$N$2:$N$1878,3) -> 0 | G42: =SUM(D42:F42) -> 0 | H42: =SUMIFS('All ZIPs'!$K$2:$K$1878,'All ZIPs'!$D$2:$D$1878,"Merced",'All ZIPs'!$N$2:$N$1878,">0") -> 0 | I42: 274.00589 | J42: Merced: NO DATA (no automated source configured; place a county or Regrid export at data/parcels/merced.gpkg)
A43: Modoc | B43: Modoc | C43: =COUNTIF('All ZIPs'!$D$2:$D$1878,"Modoc") -> 10 | D43: =COUNTIFS('All ZIPs'!$D$2:$D$1878,"Modoc",'All ZIPs'!$N$2:$N$1878,1) -> 0 | E43: =COUNTIFS('All ZIPs'!$D$2:$D$1878,"Modoc",'All ZIPs'!$N$2:$N$1878,2) -> 0 | F43: =COUNTIFS('All ZIPs'!$D$2:$D$1878,"Modoc",'All ZIPs'!$N$2:$N$1878,3) -> 0 | G43: =SUM(D43:F43) -> 0 | H43: =SUMIFS('All ZIPs'!$K$2:$K$1878,'All ZIPs'!$D$2:$D$1878,"Modoc",'All ZIPs'!$N$2:$N$1878,">0") -> 0 | J43: Modoc: NO DATA (no automated source configured; place a county or Regrid export at data/parcels/modoc.gpkg)
A44: Mono | B44: Mono | C44: =COUNTIF('All ZIPs'!$D$2:$D$1878,"Mono") -> 8 | D44: =COUNTIFS('All ZIPs'!$D$2:$D$1878,"Mono",'All ZIPs'!$N$2:$N$1878,1) -> 0 | E44: =COUNTIFS('All ZIPs'!$D$2:$D$1878,"Mono",'All ZIPs'!$N$2:$N$1878,2) -> 0 | F44: =COUNTIFS('All ZIPs'!$D$2:$D$1878,"Mono",'All ZIPs'!$N$2:$N$1878,3) -> 0 | G44: =SUM(D44:F44) -> 0 | H44: =SUMIFS('All ZIPs'!$K$2:$K$1878,'All ZIPs'!$D$2:$D$1878,"Mono",'All ZIPs'!$N$2:$N$1878,">0") -> 0 | J44: Mono: NO DATA (no automated source configured; place a county or Regrid export at data/parcels/mono.gpkg)
A45: Monterey | B45: Monterey | C45: =COUNTIF('All ZIPs'!$D$2:$D$1878,"Monterey") -> 29 | D45: =COUNTIFS('All ZIPs'!$D$2:$D$1878,"Monterey",'All ZIPs'!$N$2:$N$1878,1) -> 8 | E45: =COUNTIFS('All ZIPs'!$D$2:$D$1878,"Monterey",'All ZIPs'!$N$2:$N$1878,2) -> 1 | F45: =COUNTIFS('All ZIPs'!$D$2:$D$1878,"Monterey",'All ZIPs'!$N$2:$N$1878,3) -> 6 | G45: =SUM(D45:F45) -> 15 | H45: =SUMIFS('All ZIPs'!$K$2:$K$1878,'All ZIPs'!$D$2:$D$1878,"Monterey",'All ZIPs'!$N$2:$N$1878,">0") -> 1515 | I45: 507.04297 | J45: Monterey: NO DATA (no automated source configured; place a county or Regrid export at data/parcels/monterey.gpkg)
A46: Napa | B46: Napa | C46: =COUNTIF('All ZIPs'!$D$2:$D$1878,"Napa") -> 10 | D46: =COUNTIFS('All ZIPs'!$D$2:$D$1878,"Napa",'All ZIPs'!$N$2:$N$1878,1) -> 3 | E46: =COUNTIFS('All ZIPs'!$D$2:$D$1878,"Napa",'All ZIPs'!$N$2:$N$1878,2) -> 2 | F46: =COUNTIFS('All ZIPs'!$D$2:$D$1878,"Napa",'All ZIPs'!$N$2:$N$1878,3) -> 1 | G46: =SUM(D46:F46) -> 6 | H46: =SUMIFS('All ZIPs'!$K$2:$K$1878,'All ZIPs'!$D$2:$D$1878,"Napa",'All ZIPs'!$N$2:$N$1878,">0") -> 758 | I46: 577.35616 | J46: Napa: NO DATA (no automated source configured; place a county or Regrid export at data/parcels/napa.gpkg)
A47: Nevada | B47: Nevada | C47: =COUNTIF('All ZIPs'!$D$2:$D$1878,"Nevada") -> 6 | D47: =COUNTIFS('All ZIPs'!$D$2:$D$1878,"Nevada",'All ZIPs'!$N$2:$N$1878,1) -> 0 | E47: =COUNTIFS('All ZIPs'!$D$2:$D$1878,"Nevada",'All ZIPs'!$N$2:$N$1878,2) -> 0 | F47: =COUNTIFS('All ZIPs'!$D$2:$D$1878,"Nevada",'All ZIPs'!$N$2:$N$1878,3) -> 0 | G47: =SUM(D47:F47) -> 0 | H47: =SUMIFS('All ZIPs'!$K$2:$K$1878,'All ZIPs'!$D$2:$D$1878,"Nevada",'All ZIPs'!$N$2:$N$1878,">0") -> 0 | I47: 301.0769 | J47: Nevada: NO DATA (no automated source configured; place a county or Regrid export at data/parcels/nevada.gpkg)
A48: Orange | B48: Orange | C48: =COUNTIF('All ZIPs'!$D$2:$D$1878,"Orange") -> 88 | D48: =COUNTIFS('All ZIPs'!$D$2:$D$1878,"Orange",'All ZIPs'!$N$2:$N$1878,1) -> 43 | E48: =COUNTIFS('All ZIPs'!$D$2:$D$1878,"Orange",'All ZIPs'!$N$2:$N$1878,2) -> 40 | F48: =COUNTIFS('All ZIPs'!$D$2:$D$1878,"Orange",'All ZIPs'!$N$2:$N$1878,3) -> 4 | G48: =SUM(D48:F48) -> 87 | H48: =SUMIFS('All ZIPs'!$K$2:$K$1878,'All ZIPs'!$D$2:$D$1878,"Orange",'All ZIPs'!$N$2:$N$1878,">0") -> 13272 | I48: 699.61785 | J48: Orange: NO DATA ('portal' source needs a manual export to data/parcels/orange.gpkg)
A49: Placer | B49: Placer | C49: =COUNTIF('All ZIPs'!$D$2:$D$1878,"Placer") -> 32 | D49: =COUNTIFS('All ZIPs'!$D$2:$D$1878,"Placer",'All ZIPs'!$N$2:$N$1878,1) -> 3 | E49: =COUNTIFS('All ZIPs'!$D$2:$D$1878,"Placer",'All ZIPs'!$N$2:$N$1878,2) -> 6 | F49: =COUNTIFS('All ZIPs'!$D$2:$D$1878,"Placer",'All ZIPs'!$N$2:$N$1878,3) -> 0 | G49: =SUM(D49:F49) -> 9 | H49: =SUMIFS('All ZIPs'!$K$2:$K$1878,'All ZIPs'!$D$2:$D$1878,"Placer",'All ZIPs'!$N$2:$N$1878,">0") -> 889 | I49: 350.92264 | J49: Placer: NO DATA (no automated source configured; place a county or Regrid export at data/parcels/placer.gpkg)
A50: Plumas | B50: Plumas | C50: =COUNTIF('All ZIPs'!$D$2:$D$1878,"Plumas") -> 16 | D50: =COUNTIFS('All ZIPs'!$D$2:$D$1878,"Plumas",'All ZIPs'!$N$2:$N$1878,1) -> 0 | E50: =COUNTIFS('All ZIPs'!$D$2:$D$1878,"Plumas",'All ZIPs'!$N$2:$N$1878,2) -> 0 | F50: =COUNTIFS('All ZIPs'!$D$2:$D$1878,"Plumas",'All ZIPs'!$N$2:$N$1878,3) -> 0 | G50: =SUM(D50:F50) -> 0 | H50: =SUMIFS('All ZIPs'!$K$2:$K$1878,'All ZIPs'!$D$2:$D$1878,"Plumas",'All ZIPs'!$N$2:$N$1878,">0") -> 0 | J50: Plumas: NO DATA (no automated source configured; place a county or Regrid export at data/parcels/plumas.gpkg)
A51: Riverside | B51: Riverside | C51: =COUNTIF('All ZIPs'!$D$2:$D$1878,"Riverside") -> 70 | D51: =COUNTIFS('All ZIPs'!$D$2:$D$1878,"Riverside",'All ZIPs'!$N$2:$N$1878,1) -> 0 | E51: =COUNTIFS('All ZIPs'!$D$2:$D$1878,"Riverside",'All ZIPs'!$N$2:$N$1878,2) -> 2 | F51: =COUNTIFS('All ZIPs'!$D$2:$D$1878,"Riverside",'All ZIPs'!$N$2:$N$1878,3) -> 0 | G51: =SUM(D51:F51) -> 2 | H51: =SUMIFS('All ZIPs'!$K$2:$K$1878,'All ZIPs'!$D$2:$D$1878,"Riverside",'All ZIPs'!$N$2:$N$1878,">0") -> 426 | I51: 305.74809 | J51: Riverside: NO DATA ('portal' source needs a manual export to data/parcels/riverside.gpkg)
A52: Sacramento | B52: Sacramento | C52: =COUNTIF('All ZIPs'!$D$2:$D$1878,"Sacramento") -> 54 | D52: =COUNTIFS('All ZIPs'!$D$2:$D$1878,"Sacramento",'All ZIPs'!$N$2:$N$1878,1) -> 0 | E52: =COUNTIFS('All ZIPs'!$D$2:$D$1878,"Sacramento",'All ZIPs'!$N$2:$N$1878,2) -> 0 | F52: =COUNTIFS('All ZIPs'!$D$2:$D$1878,"Sacramento",'All ZIPs'!$N$2:$N$1878,3) -> 3 | G52: =SUM(D52:F52) -> 3 | H52: =SUMIFS('All ZIPs'!$K$2:$K$1878,'All ZIPs'!$D$2:$D$1878,"Sacramento",'All ZIPs'!$N$2:$N$1878,">0") -> 494 | I52: 336.10695 | J52: Sacramento: NO DATA ('portal' source needs a manual export to data/parcels/sacramento.gpkg)
A53: San Benito | B53: San Benito | C53: =COUNTIF('All ZIPs'!$D$2:$D$1878,"San Benito") -> 5 | D53: =COUNTIFS('All ZIPs'!$D$2:$D$1878,"San Benito",'All ZIPs'!$N$2:$N$1878,1) -> 0 | E53: =COUNTIFS('All ZIPs'!$D$2:$D$1878,"San Benito",'All ZIPs'!$N$2:$N$1878,2) -> 0 | F53: =COUNTIFS('All ZIPs'!$D$2:$D$1878,"San Benito",'All ZIPs'!$N$2:$N$1878,3) -> 2 | G53: =SUM(D53:F53) -> 2 | H53: =SUMIFS('All ZIPs'!$K$2:$K$1878,'All ZIPs'!$D$2:$D$1878,"San Benito",'All ZIPs'!$N$2:$N$1878,">0") -> 21 | I53: 484.95439 | J53: San Benito: NO DATA (no automated source configured; place a county or Regrid export at data/parcels/san_benito.gpkg)
A54: San Bernardino | B54: San Bernardino | C54: =COUNTIF('All ZIPs'!$D$2:$D$1878,"San Bernardino") -> 89 | D54: =COUNTIFS('All ZIPs'!$D$2:$D$1878,"San Bernardino",'All ZIPs'!$N$2:$N$1878,1) -> 0 | E54: =COUNTIFS('All ZIPs'!$D$2:$D$1878,"San Bernardino",'All ZIPs'!$N$2:$N$1878,2) -> 0 | F54: =COUNTIFS('All ZIPs'!$D$2:$D$1878,"San Bernardino",'All ZIPs'!$N$2:$N$1878,3) -> 2 | G54: =SUM(D54:F54) -> 2 | H54: =SUMIFS('All ZIPs'!$K$2:$K$1878,'All ZIPs'!$D$2:$D$1878,"San Bernardino",'All ZIPs'!$N$2:$N$1878,">0") -> 453 | I54: 330.69137 | J54: San Bernardino: NO DATA ('portal' source needs a manual export to data/parcels/san_bernardino.gpkg)
A55: San Diego | B55: San Diego | C55: =COUNTIF('All ZIPs'!$D$2:$D$1878,"San Diego") -> 106 | D55: =COUNTIFS('All ZIPs'!$D$2:$D$1878,"San Diego",'All ZIPs'!$N$2:$N$1878,1) -> 31 | E55: =COUNTIFS('All ZIPs'!$D$2:$D$1878,"San Diego",'All ZIPs'!$N$2:$N$1878,2) -> 12 | F55: =COUNTIFS('All ZIPs'!$D$2:$D$1878,"San Diego",'All ZIPs'!$N$2:$N$1878,3) -> 26 | G55: =SUM(D55:F55) -> 69 | H55: =SUMIFS('All ZIPs'!$K$2:$K$1878,'All ZIPs'!$D$2:$D$1878,"San Diego",'All ZIPs'!$N$2:$N$1878,">0") -> 11468 | I55: 558.32242 | J55: San Diego: NO DATA (BLOCKED by this environment's network policy (proxy 403))
A56: San Francisco | B56: San Francisco | C56: =COUNTIF('All ZIPs'!$D$2:$D$1878,"San Francisco") -> 27 | D56: =COUNTIFS('All ZIPs'!$D$2:$D$1878,"San Francisco",'All ZIPs'!$N$2:$N$1878,1) -> 25 | E56: =COUNTIFS('All ZIPs'!$D$2:$D$1878,"San Francisco",'All ZIPs'!$N$2:$N$1878,2) -> 1 | F56: =COUNTIFS('All ZIPs'!$D$2:$D$1878,"San Francisco",'All ZIPs'!$N$2:$N$1878,3) -> 0 | G56: =SUM(D56:F56) -> 26 | H56: =SUMIFS('All ZIPs'!$K$2:$K$1878,'All ZIPs'!$D$2:$D$1878,"San Francisco",'All ZIPs'!$N$2:$N$1878,">0") -> 2990 | I56: 1095.5127 | J56: San Francisco: NO DATA ('portal' source needs a manual export to data/parcels/san_francisco.gpkg)
A57: San Joaquin | B57: San Joaquin | C57: =COUNTIF('All ZIPs'!$D$2:$D$1878,"San Joaquin") -> 30 | D57: =COUNTIFS('All ZIPs'!$D$2:$D$1878,"San Joaquin",'All ZIPs'!$N$2:$N$1878,1) -> 0 | E57: =COUNTIFS('All ZIPs'!$D$2:$D$1878,"San Joaquin",'All ZIPs'!$N$2:$N$1878,2) -> 0 | F57: =COUNTIFS('All ZIPs'!$D$2:$D$1878,"San Joaquin",'All ZIPs'!$N$2:$N$1878,3) -> 0 | G57: =SUM(D57:F57) -> 0 | H57: =SUMIFS('All ZIPs'!$K$2:$K$1878,'All ZIPs'!$D$2:$D$1878,"San Joaquin",'All ZIPs'!$N$2:$N$1878,">0") -> 0 | I57: 316.65754 | J57: San Joaquin: NO DATA (no automated source configured; place a county or Regrid export at data/parcels/san_joaquin.gpkg)
A58: San Luis Obispo | B58: San Luis Obispo | C58: =COUNTIF('All ZIPs'!$D$2:$D$1878,"San Luis Obispo") -> 20 | D58: =COUNTIFS('All ZIPs'!$D$2:$D$1878,"San Luis Obispo",'All ZIPs'!$N$2:$N$1878,1) -> 5 | E58: =COUNTIFS('All ZIPs'!$D$2:$D$1878,"San Luis Obispo",'All ZIPs'!$N$2:$N$1878,2) -> 3 | F58: =COUNTIFS('All ZIPs'!$D$2:$D$1878,"San Luis Obispo",'All ZIPs'!$N$2:$N$1878,3) -> 6 | G58: =SUM(D58:F58) -> 14 | H58: =SUMIFS('All ZIPs'!$K$2:$K$1878,'All ZIPs'!$D$2:$D$1878,"San Luis Obispo",'All ZIPs'!$N$2:$N$1878,">0") -> 1465 | I58: 589.79162 | J58: San Luis Obispo: NO DATA (no automated source configured; place a county or Regrid export at data/parcels/san_luis_obispo.gpkg)
A59: San Mateo | B59: San Mateo | C59: =COUNTIF('All ZIPs'!$D$2:$D$1878,"San Mateo") -> 29 | D59: =COUNTIFS('All ZIPs'!$D$2:$D$1878,"San Mateo",'All ZIPs'!$N$2:$N$1878,1) -> 25 | E59: =COUNTIFS('All ZIPs'!$D$2:$D$1878,"San Mateo",'All ZIPs'!$N$2:$N$1878,2) -> 1 | F59: =COUNTIFS('All ZIPs'!$D$2:$D$1878,"San Mateo",'All ZIPs'!$N$2:$N$1878,3) -> 0 | G59: =SUM(D59:F59) -> 26 | H59: =SUMIFS('All ZIPs'!$K$2:$K$1878,'All ZIPs'!$D$2:$D$1878,"San Mateo",'All ZIPs'!$N$2:$N$1878,">0") -> 3812 | I59: 1108.4866 | J59: San Mateo: NO DATA ('portal' source needs a manual export to data/parcels/san_mateo.gpkg)
A60: Santa Barbara | B60: Santa Barbara | C60: =COUNTIF('All ZIPs'!$D$2:$D$1878,"Santa Barbara") -> 23 | D60: =COUNTIFS('All ZIPs'!$D$2:$D$1878,"Santa Barbara",'All ZIPs'!$N$2:$N$1878,1) -> 12 | E60: =COUNTIFS('All ZIPs'!$D$2:$D$1878,"Santa Barbara",'All ZIPs'!$N$2:$N$1878,2) -> 1 | F60: =COUNTIFS('All ZIPs'!$D$2:$D$1878,"Santa Barbara",'All ZIPs'!$N$2:$N$1878,3) -> 1 | G60: =SUM(D60:F60) -> 14 | H60: =SUMIFS('All ZIPs'!$K$2:$K$1878,'All ZIPs'!$D$2:$D$1878,"Santa Barbara",'All ZIPs'!$N$2:$N$1878,">0") -> 1168 | I60: 866.04146 | J60: Santa Barbara: NO DATA (no automated source configured; place a county or Regrid export at data/parcels/santa_barbara.gpkg)
A61: Santa Clara | B61: Santa Clara | C61: =COUNTIF('All ZIPs'!$D$2:$D$1878,"Santa Clara") -> 58 | D61: =COUNTIFS('All ZIPs'!$D$2:$D$1878,"Santa Clara",'All ZIPs'!$N$2:$N$1878,1) -> 52 | E61: =COUNTIFS('All ZIPs'!$D$2:$D$1878,"Santa Clara",'All ZIPs'!$N$2:$N$1878,2) -> 1 | F61: =COUNTIFS('All ZIPs'!$D$2:$D$1878,"Santa Clara",'All ZIPs'!$N$2:$N$1878,3) -> 2 | G61: =SUM(D61:F61) -> 55 | H61: =SUMIFS('All ZIPs'!$K$2:$K$1878,'All ZIPs'!$D$2:$D$1878,"Santa Clara",'All ZIPs'!$N$2:$N$1878,">0") -> 8015 | I61: 1097.4275 | J61: Santa Clara: NO DATA ('portal' source needs a manual export to data/parcels/santa_clara.gpkg)
A62: Santa Cruz | B62: Santa Cruz | C62: =COUNTIF('All ZIPs'!$D$2:$D$1878,"Santa Cruz") -> 17 | D62: =COUNTIFS('All ZIPs'!$D$2:$D$1878,"Santa Cruz",'All ZIPs'!$N$2:$N$1878,1) -> 6 | E62: =COUNTIFS('All ZIPs'!$D$2:$D$1878,"Santa Cruz",'All ZIPs'!$N$2:$N$1878,2) -> 5 | F62: =COUNTIFS('All ZIPs'!$D$2:$D$1878,"Santa Cruz",'All ZIPs'!$N$2:$N$1878,3) -> 2 | G62: =SUM(D62:F62) -> 13 | H62: =SUMIFS('All ZIPs'!$K$2:$K$1878,'All ZIPs'!$D$2:$D$1878,"Santa Cruz",'All ZIPs'!$N$2:$N$1878,">0") -> 1306 | I62: 678.86074 | J62: Santa Cruz: NO DATA (no automated source configured; place a county or Regrid export at data/parcels/santa_cruz.gpkg)
A63: Shasta | B63: Shasta | C63: =COUNTIF('All ZIPs'!$D$2:$D$1878,"Shasta") -> 26 | D63: =COUNTIFS('All ZIPs'!$D$2:$D$1878,"Shasta",'All ZIPs'!$N$2:$N$1878,1) -> 0 | E63: =COUNTIFS('All ZIPs'!$D$2:$D$1878,"Shasta",'All ZIPs'!$N$2:$N$1878,2) -> 1 | F63: =COUNTIFS('All ZIPs'!$D$2:$D$1878,"Shasta",'All ZIPs'!$N$2:$N$1878,3) -> 0 | G63: =SUM(D63:F63) -> 1 | H63: =SUMIFS('All ZIPs'!$K$2:$K$1878,'All ZIPs'!$D$2:$D$1878,"Shasta",'All ZIPs'!$N$2:$N$1878,">0") -> 5 | I63: 209.2678 | J63: Shasta: NO DATA (no automated source configured; place a county or Regrid export at data/parcels/shasta.gpkg)
A64: Sierra | B64: Sierra | C64: =COUNTIF('All ZIPs'!$D$2:$D$1878,"Sierra") -> 9 | D64: =COUNTIFS('All ZIPs'!$D$2:$D$1878,"Sierra",'All ZIPs'!$N$2:$N$1878,1) -> 0 | E64: =COUNTIFS('All ZIPs'!$D$2:$D$1878,"Sierra",'All ZIPs'!$N$2:$N$1878,2) -> 0 | F64: =COUNTIFS('All ZIPs'!$D$2:$D$1878,"Sierra",'All ZIPs'!$N$2:$N$1878,3) -> 0 | G64: =SUM(D64:F64) -> 0 | H64: =SUMIFS('All ZIPs'!$K$2:$K$1878,'All ZIPs'!$D$2:$D$1878,"Sierra",'All ZIPs'!$N$2:$N$1878,">0") -> 0 | J64: Sierra: NO DATA (no automated source configured; place a county or Regrid export at data/parcels/sierra.gpkg)
A65: Siskiyou | B65: Siskiyou | C65: =COUNTIF('All ZIPs'!$D$2:$D$1878,"Siskiyou") -> 22 | D65: =COUNTIFS('All ZIPs'!$D$2:$D$1878,"Siskiyou",'All ZIPs'!$N$2:$N$1878,1) -> 0 | E65: =COUNTIFS('All ZIPs'!$D$2:$D$1878,"Siskiyou",'All ZIPs'!$N$2:$N$1878,2) -> 0 | F65: =COUNTIFS('All ZIPs'!$D$2:$D$1878,"Siskiyou",'All ZIPs'!$N$2:$N$1878,3) -> 0 | G65: =SUM(D65:F65) -> 0 | H65: =SUMIFS('All ZIPs'!$K$2:$K$1878,'All ZIPs'!$D$2:$D$1878,"Siskiyou",'All ZIPs'!$N$2:$N$1878,">0") -> 0 | J65: Siskiyou: NO DATA (no automated source configured; place a county or Regrid export at data/parcels/siskiyou.gpkg)
A66: Solano | B66: Solano | C66: =COUNTIF('All ZIPs'!$D$2:$D$1878,"Solano") -> 15 | D66: =COUNTIFS('All ZIPs'!$D$2:$D$1878,"Solano",'All ZIPs'!$N$2:$N$1878,1) -> 0 | E66: =COUNTIFS('All ZIPs'!$D$2:$D$1878,"Solano",'All ZIPs'!$N$2:$N$1878,2) -> 0 | F66: =COUNTIFS('All ZIPs'!$D$2:$D$1878,"Solano",'All ZIPs'!$N$2:$N$1878,3) -> 0 | G66: =SUM(D66:F66) -> 0 | H66: =SUMIFS('All ZIPs'!$K$2:$K$1878,'All ZIPs'!$D$2:$D$1878,"Solano",'All ZIPs'!$N$2:$N$1878,">0") -> 0 | I66: 343.04877 | J66: Solano: NO DATA (no automated source configured; place a county or Regrid export at data/parcels/solano.gpkg)
A67: Sonoma | B67: Sonoma | C67: =COUNTIF('All ZIPs'!$D$2:$D$1878,"Sonoma") -> 35 | D67: =COUNTIFS('All ZIPs'!$D$2:$D$1878,"Sonoma",'All ZIPs'!$N$2:$N$1878,1) -> 6 | E67: =COUNTIFS('All ZIPs'!$D$2:$D$1878,"Sonoma",'All ZIPs'!$N$2:$N$1878,2) -> 8 | F67: =COUNTIFS('All ZIPs'!$D$2:$D$1878,"Sonoma",'All ZIPs'!$N$2:$N$1878,3) -> 9 | G67: =SUM(D67:F67) -> 23 | H67: =SUMIFS('All ZIPs'!$K$2:$K$1878,'All ZIPs'!$D$2:$D$1878,"Sonoma",'All ZIPs'!$N$2:$N$1878,">0") -> 1904 | I67: 525.04573 | J67: Sonoma: NO DATA (no automated source configured; place a county or Regrid export at data/parcels/sonoma.gpkg)
A68: Stanislaus | B68: Stanislaus | C68: =COUNTIF('All ZIPs'!$D$2:$D$1878,"Stanislaus") -> 25 | D68: =COUNTIFS('All ZIPs'!$D$2:$D$1878,"Stanislaus",'All ZIPs'!$N$2:$N$1878,1) -> 0 | E68: =COUNTIFS('All ZIPs'!$D$2:$D$1878,"Stanislaus",'All ZIPs'!$N$2:$N$1878,2) -> 0 | F68: =COUNTIFS('All ZIPs'!$D$2:$D$1878,"Stanislaus",'All ZIPs'!$N$2:$N$1878,3) -> 1 | G68: =SUM(D68:F68) -> 1 | H68: =SUMIFS('All ZIPs'!$K$2:$K$1878,'All ZIPs'!$D$2:$D$1878,"Stanislaus",'All ZIPs'!$N$2:$N$1878,">0") -> 2 | I68: 307.16531 | J68: Stanislaus: NO DATA (no automated source configured; place a county or Regrid export at data/parcels/stanislaus.gpkg)
A69: Sutter | B69: Sutter | C69: =COUNTIF('All ZIPs'!$D$2:$D$1878,"Sutter") -> 9 | D69: =COUNTIFS('All ZIPs'!$D$2:$D$1878,"Sutter",'All ZIPs'!$N$2:$N$1878,1) -> 0 | E69: =COUNTIFS('All ZIPs'!$D$2:$D$1878,"Sutter",'All ZIPs'!$N$2:$N$1878,2) -> 0 | F69: =COUNTIFS('All ZIPs'!$D$2:$D$1878,"Sutter",'All ZIPs'!$N$2:$N$1878,3) -> 1 | G69: =SUM(D69:F69) -> 1 | H69: =SUMIFS('All ZIPs'!$K$2:$K$1878,'All ZIPs'!$D$2:$D$1878,"Sutter",'All ZIPs'!$N$2:$N$1878,">0") -> 4 | I69: 303.85767 | J69: Sutter: NO DATA (no automated source configured; place a county or Regrid export at data/parcels/sutter.gpkg)
A70: Tehama | B70: Tehama | C70: =COUNTIF('All ZIPs'!$D$2:$D$1878,"Tehama") -> 12 | D70: =COUNTIFS('All ZIPs'!$D$2:$D$1878,"Tehama",'All ZIPs'!$N$2:$N$1878,1) -> 0 | E70: =COUNTIFS('All ZIPs'!$D$2:$D$1878,"Tehama",'All ZIPs'!$N$2:$N$1878,2) -> 1 | F70: =COUNTIFS('All ZIPs'!$D$2:$D$1878,"Tehama",'All ZIPs'!$N$2:$N$1878,3) -> 0 | G70: =SUM(D70:F70) -> 1 | H70: =SUMIFS('All ZIPs'!$K$2:$K$1878,'All ZIPs'!$D$2:$D$1878,"Tehama",'All ZIPs'!$N$2:$N$1878,">0") -> 2 | I70: 223.51611 | J70: Tehama: NO DATA (no automated source configured; place a county or Regrid export at data/parcels/tehama.gpkg)
A71: Trinity | B71: Trinity | C71: =COUNTIF('All ZIPs'!$D$2:$D$1878,"Trinity") -> 12 | D71: =COUNTIFS('All ZIPs'!$D$2:$D$1878,"Trinity",'All ZIPs'!$N$2:$N$1878,1) -> 0 | E71: =COUNTIFS('All ZIPs'!$D$2:$D$1878,"Trinity",'All ZIPs'!$N$2:$N$1878,2) -> 0 | F71: =COUNTIFS('All ZIPs'!$D$2:$D$1878,"Trinity",'All ZIPs'!$N$2:$N$1878,3) -> 0 | G71: =SUM(D71:F71) -> 0 | H71: =SUMIFS('All ZIPs'!$K$2:$K$1878,'All ZIPs'!$D$2:$D$1878,"Trinity",'All ZIPs'!$N$2:$N$1878,">0") -> 0 | J71: Trinity: NO DATA (no automated source configured; place a county or Regrid export at data/parcels/trinity.gpkg)
A72: Tulare | B72: Tulare | C72: =COUNTIF('All ZIPs'!$D$2:$D$1878,"Tulare") -> 35 | D72: =COUNTIFS('All ZIPs'!$D$2:$D$1878,"Tulare",'All ZIPs'!$N$2:$N$1878,1) -> 0 | E72: =COUNTIFS('All ZIPs'!$D$2:$D$1878,"Tulare",'All ZIPs'!$N$2:$N$1878,2) -> 0 | F72: =COUNTIFS('All ZIPs'!$D$2:$D$1878,"Tulare",'All ZIPs'!$N$2:$N$1878,3) -> 0 | G72: =SUM(D72:F72) -> 0 | H72: =SUMIFS('All ZIPs'!$K$2:$K$1878,'All ZIPs'!$D$2:$D$1878,"Tulare",'All ZIPs'!$N$2:$N$1878,">0") -> 0 | I72: 237.81135 | J72: Tulare: NO DATA (no automated source configured; place a county or Regrid export at data/parcels/tulare.gpkg)
A73: Tuolumne | B73: Tuolumne | C73: =COUNTIF('All ZIPs'!$D$2:$D$1878,"Tuolumne") -> 14 | D73: =COUNTIFS('All ZIPs'!$D$2:$D$1878,"Tuolumne",'All ZIPs'!$N$2:$N$1878,1) -> 0 | E73: =COUNTIFS('All ZIPs'!$D$2:$D$1878,"Tuolumne",'All ZIPs'!$N$2:$N$1878,2) -> 0 | F73: =COUNTIFS('All ZIPs'!$D$2:$D$1878,"Tuolumne",'All ZIPs'!$N$2:$N$1878,3) -> 0 | G73: =SUM(D73:F73) -> 0 | H73: =SUMIFS('All ZIPs'!$K$2:$K$1878,'All ZIPs'!$D$2:$D$1878,"Tuolumne",'All ZIPs'!$N$2:$N$1878,">0") -> 0 | I73: 248.78414 | J73: Tuolumne: NO DATA (no automated source configured; place a county or Regrid export at data/parcels/tuolumne.gpkg)
A74: Ventura | B74: Ventura | C74: =COUNTIF('All ZIPs'!$D$2:$D$1878,"Ventura") -> 29 | D74: =COUNTIFS('All ZIPs'!$D$2:$D$1878,"Ventura",'All ZIPs'!$N$2:$N$1878,1) -> 4 | E74: =COUNTIFS('All ZIPs'!$D$2:$D$1878,"Ventura",'All ZIPs'!$N$2:$N$1878,2) -> 2 | F74: =COUNTIFS('All ZIPs'!$D$2:$D$1878,"Ventura",'All ZIPs'!$N$2:$N$1878,3) -> 9 | G74: =SUM(D74:F74) -> 15 | H74: =SUMIFS('All ZIPs'!$K$2:$K$1878,'All ZIPs'!$D$2:$D$1878,"Ventura",'All ZIPs'!$N$2:$N$1878,">0") -> 2910 | I74: 510.59736 | J74: Ventura: NO DATA ('portal' source needs a manual export to data/parcels/ventura.gpkg)
A75: Yolo | B75: Yolo | C75: =COUNTIF('All ZIPs'!$D$2:$D$1878,"Yolo") -> 17 | D75: =COUNTIFS('All ZIPs'!$D$2:$D$1878,"Yolo",'All ZIPs'!$N$2:$N$1878,1) -> 1 | E75: =COUNTIFS('All ZIPs'!$D$2:$D$1878,"Yolo",'All ZIPs'!$N$2:$N$1878,2) -> 0 | F75: =COUNTIFS('All ZIPs'!$D$2:$D$1878,"Yolo",'All ZIPs'!$N$2:$N$1878,3) -> 1 | G75: =SUM(D75:F75) -> 2 | H75: =SUMIFS('All ZIPs'!$K$2:$K$1878,'All ZIPs'!$D$2:$D$1878,"Yolo",'All ZIPs'!$N$2:$N$1878,">0") -> 3 | I75: 346.65644 | J75: Yolo: NO DATA (no automated source configured; place a county or Regrid export at data/parcels/yolo.gpkg)
A76: Yuba | B76: Yuba | C76: =COUNTIF('All ZIPs'!$D$2:$D$1878,"Yuba") -> 11 | D76: =COUNTIFS('All ZIPs'!$D$2:$D$1878,"Yuba",'All ZIPs'!$N$2:$N$1878,1) -> 0 | E76: =COUNTIFS('All ZIPs'!$D$2:$D$1878,"Yuba",'All ZIPs'!$N$2:$N$1878,2) -> 0 | F76: =COUNTIFS('All ZIPs'!$D$2:$D$1878,"Yuba",'All ZIPs'!$N$2:$N$1878,3) -> 0 | G76: =SUM(D76:F76) -> 0 | H76: =SUMIFS('All ZIPs'!$K$2:$K$1878,'All ZIPs'!$D$2:$D$1878,"Yuba",'All ZIPs'!$N$2:$N$1878,">0") -> 0 | I76: 260.7322 | J76: Yuba: NO DATA (no automated source configured; place a county or Regrid export at data/parcels/yuba.gpkg)
A78: Median of ZIP $/sq ft is a static value at build time; other counts are live formulas.

Sheet Neighborhoods
A1: ZIP | B1: City | C1: County | D1: Neighborhood | E1: Overture place type | F1: Tier | G1: ZIP rank
A2: 92677 | B2: Laguna Niguel | C2: Orange | D2: El Niguel Heights | E2: neighborhood | F2: Tier 1 (>= $700/sf) | G2: 1
A3: 92677 | B3: Laguna Niguel | C3: Orange | D3: Niguel Summit | E3: neighborhood | F3: Tier 1 (>= $700/sf) | G3: 1
A4: 94550 | B4: Livermore | C4: Alameda | D4: Livermorium Plaza / Mills Square Park | E4: microhood | F4: Tier 1 (>= $700/sf) | G4: 2
A5: 94550 | B5: Livermore | C5: Alameda | D5: Lizzie Fountain Plaza | E5: microhood | F5: Tier 1 (>= $700/sf) | G5: 2
A6: 94550 | B6: Livermore | C6: Alameda | D6: Sandhurst | E6: neighborhood | F6: Tier 1 (>= $700/sf) | G6: 2
A7: 94550 | B7: Livermore | C7: Alameda | D7: The Grove | E7: neighborhood | F7: Tier 1 (>= $700/sf) | G7: 2
A8: 94550 | B8: Livermore | C8: Alameda | D8: Village II | E8: neighborhood | F8: Tier 1 (>= $700/sf) | G8: 2
A9: 94550 | B9: Livermore | C9: Alameda | D9: Vinsanto II | E9: neighborhood | F9: Tier 1 (>= $700/sf) | G9: 2
A10: 95125 | B10: San Jose | C10: Santa Clara | D10: Dry Creek | E10: macrohood | F10: Tier 1 (>= $700/sf) | G10: 3
A11: 95125 | B11: San Jose | C11: Santa Clara | D11: Willow Glen | E11: macrohood | F11: Tier 1 (>= $700/sf) | G11: 3
A12: 92024 | B12: Encinitas | C12: San Diego | D12: Downtown Encinitas | E12: neighborhood | F12: Tier 1 (>= $700/sf) | G12: 4
A13: 92024 | B13: Encinitas | C13: San Diego | D13: Encinitas Highlands | E13: neighborhood | F13: Tier 1 (>= $700/sf) | G13: 4
... A2054: 95456 | B2054: Little River | C2054: Mendocino | D2054: The Woods | E2054: neighborhood | F2054: Tier 2 ($600-699/sf) | G2054: 733
A2055: 90006 | B2055: Los Angeles | C2055: Los Angeles | D2055: Alvarado Terrace Historic District | E2055: neighborhood | F2055: Below $500/sf
A2056: 90006 | B2056: Los Angeles | C2056: Los Angeles | D2056: Harvard Heights | E2056: neighborhood | F2056: Below $500/sf
A2057: 90006 | B2057: Los Angeles | C2057: Los Angeles | D2057: Monseñor Óscar Arnulfo Romero Square | E2057: microhood | F2057: Below $500/sf
A2058: 90006 | B2058: Los Angeles | C2058: Los Angeles | D2058: Pico-Union | E2058: macrohood | F2058: Below $500/sf
A2059: 90007 | B2059: Los Angeles | C2059: Los Angeles | D2059: Saint James Park | E2059: neighborhood | F2059: Below $500/sf
A2060: 90007 | B2060: Los Angeles | C2060: Los Angeles | D2060: University Park | E2060: microhood | F2060: Below $500/sf
A2061: 90037 | B2061: Los Angeles | C2061: Los Angeles | D2061: Wildasin | E2061: neighborhood | F2061: Below $500/sf
A2062: 90071 | B2062: Los Angeles | C2062: Los Angeles | D2062: Bank of America Plaza | E2062: microhood
A2063: 90071 | B2063: Los Angeles | C2063: Los Angeles | D2063: Bunker Hill | E2063: microhood
A2064: 90095 | B2064: Los Angeles | C2064: Los Angeles | D2064: Court of Philanthropy | E2064: microhood
A2065: 90742 | B2065: Huntington Beach | C2065: Orange | D2065: Sunset Beach | E2065: neighborhood
A2066: 91311 | B2066: Chatsworth | C2066: Los Angeles | D2066: Chatsworth | E2066: macrohood | F2066: Below $500/sf
A2067: 91311 | B2067: Chatsworth | C2067: Los Angeles | D2067: Chatsworth Neighborhood Council District | E2067: macrohood | F2067: Below $500/sf
A2068: 91311 | B2068: Chatsworth | C2068: Los Angeles | D2068: Deerlake Ranch | E2068: neighborhood | F2068: Below $500/sf
A2069: 91321 | B2069: Newhall | C2069: Los Angeles | D2069: Newhall | E2069: macrohood | F2069: Below $500/sf
A2070: 91330 | B2070: Northridge | C2070: Los Angeles | D2070: Matador Spirit Plaza | E2070: microhood
A2071: 91350 | B2071: Santa Clarita | C2071: Los Angeles | D2071: Brock Billa | E2071: neighborhood | F2071: Below $500/sf
A2072: 91350 | B2072: Santa Clarita | C2072: Los Angeles | D2072: Plum Canyon | E2072: neighborhood | F2072: Below $500/sf
A2073: 91350 | B2073: Santa Clarita | C2073: Los Angeles | D2073: Saugus | E2073: macrohood | F2073: Below $500/sf
A2074: 91351 | B2074: Canyon Country | C2074: Los Angeles | D2074: Canyon Country | E2074: macrohood | F2074: Below $500/sf
A2075: 91351 | B2075: Canyon Country | C2075: Los Angeles | D2075: Honby | E2075: neighborhood | F2075: Below $500/sf
A2076: 91354 | B2076: Valencia | C2076: Los Angeles | D2076: Copper Hill | E2076: macrohood | F2076: Below $500/sf
A2077: 91381 | B2077: Stevenson Ranch | C2077: Los Angeles | D2077: Entrada South | E2077: microhood | F2077: Below $500/sf
A2078: 91381 | B2078: Stevenson Ranch | C2078: Los Angeles | D2078: Homestead | E2078: neighborhood | F2078: Below $500/sf
A2079: 91381 | B2079: Stevenson Ranch | C2079: Los Angeles | D2079: Landmark Village | E2079: microhood | F2079: Below $500/sf
A2080: 91381 | B2080: Stevenson Ranch | C2080: Los Angeles | D2080: Southern Oaks | E2080: microhood | F2080: Below $500/sf
A2081: 91381 | B2081: Stevenson Ranch | C2081: Los Angeles | D2081: Stevenson Ranch | E2081: macrohood | F2081: Below $500/sf
A2082: 91381 | B2082: Stevenson Ranch | C2082: Los Angeles | D2082: Sunset Pointe | E2082: microhood | F2082: Below $500/sf
... A2089: 91387 | B2089: Canyon Country | C2089: Los Angeles | D2089: Sand Canyon | E2089: macrohood | F2089: Below $500/sf
A2090: 91608 | B2090: Universal City | C2090: Los Angeles | D2090: Universal City | E2090: microhood
A2091: 91708 | B2091: Chino | C2091: San Bernardino | D2091: The Preserve | E2091: macrohood | F2091: Below $500/sf
A2092: 91710 | B2092: Chino | C2092: San Bernardino | D2092: Agave Neighborhood | E2092: neighborhood | F2092: Below $500/sf
A2093: 91730 | B2093: Rancho Cucamonga | C2093: San Bernardino | D2093: Central North | E2093: neighborhood | F2093: Below $500/sf
A2094: 91730 | B2094: Rancho Cucamonga | C2094: San Bernardino | D2094: Central South | E2094: neighborhood | F2094: Below $500/sf
A2095: 91730 | B2095: Rancho Cucamonga | C2095: San Bernardino | D2095: Cucamonga | E2095: neighborhood | F2095: Below $500/sf
A2096: 91730 | B2096: Rancho Cucamonga | C2096: San Bernardino | D2096: Red Hill | E2096: neighborhood | F2096: Below $500/sf
A2097: 91730 | B2097: Rancho Cucamonga | C2097: San Bernardino | D2097: Rochester | E2097: neighborhood | F2097: Below $500/sf
A2098: 91730 | B2098: Rancho Cucamonga | C2098: San Bernardino | D2098: Southeast | E2098: neighborhood | F2098: Below $500/sf
A2099: 91737 | B2099: Rancho Cucamonga | C2099: San Bernardino | D2099: Alta Loma | E2099: neighborhood | F2099: Below $500/sf
A2100: 91737 | B2100: Rancho Cucamonga | C2100: San Bernardino | D2100: Etiwanda Heights Town Center | E2100: neighborhood | F2100: Below $500/sf
A2101: 91739 | B2101: Rancho Cucamonga | C2101: San Bernardino | D2101: Eastside | E2101: neighborhood | F2101: Below $500/sf
A2102: 91739 | B2102: Rancho Cucamonga | C2102: San Bernardino | D2102: Etiwanda | E2102: neighborhood | F2102: Below $500/sf
... A2156: 92040 | B2156: Lakeside | C2156: San Diego | D2156: Riverview Farms | E2156: neighborhood | F2156: Below $500/sf
A2157: 92055 | B2157: San Clemente | C2157: San Diego | D2157: Chappo | E2157: neighborhood
A2158: 92057 | B2158: Oceanside | C2158: San Diego | D2158: Arrowood | E2158: microhood | F2158: Below $500/sf
A2159: 92057 | B2159: Oceanside | C2159: San Diego | D2159: Guajome | E2159: microhood | F2159: Below $500/sf
A2160: 92057 | B2160: Oceanside | C2160: San Diego | D2160: Ivey Ranch | E2160: microhood | F2160: Below $500/sf
A2161: 92057 | B2161: Oceanside | C2161: San Diego | D2161: Libby Lake | E2161: microhood | F2161: Below $500/sf
A2162: 92057 | B2162: Oceanside | C2162: San Diego | D2162: Mission Meadows | E2162: microhood | F2162: Below $500/sf
A2163: 92057 | B2163: Oceanside | C2163: San Diego | D2163: Morro Hills | E2163: neighborhood | F2163: Below $500/sf
A2164: 92057 | B2164: Oceanside | C2164: San Diego | D2164: North River Farms | E2164: neighborhood | F2164: Below $500/sf
A2165: 92057 | B2165: Oceanside | C2165: San Diego | D2165: Oceana | E2165: microhood | F2165: Below $500/sf
A2166: 92065 | B2166: Ramona | C2166: San Diego | D2166: Mt. Woodson Castle | E2166: neighborhood | F2166: Below $500/sf
A2167: 92084 | B2167: Vista | C2167: San Diego | D2167: Alta Vista | E2167: microhood | F2167: Below $500/sf
A2168: 92084 | B2168: Vista | C2168: San Diego | D2168: Downtown Vista | E2168: microhood | F2168: Below $500/sf
A2169: 92145 | B2169: San Diego | C2169: San Diego | D2169: Rancho Encantada | E2169: macrohood
A2170: 92154 | B2170: San Diego | C2170: San Diego | D2170: Dennery Ranch | E2170: neighborhood | F2170: Below $500/sf
A2171: 92154 | B2171: San Diego | C2171: San Diego | D2171: Egger Highlands | E2171: microhood | F2171: Below $500/sf
A2172: 92154 | B2172: San Diego | C2172: San Diego | D2172: Hidden Trails | E2172: neighborhood | F2172: Below $500/sf
A2173: 92154 | B2173: San Diego | C2173: San Diego | D2173: Nestor | E2173: microhood | F2173: Below $500/sf
A2174: 92154 | B2174: San Diego | C2174: San Diego | D2174: Ocean View Hills | E2174: neighborhood | F2174: Below $500/sf
A2175: 92154 | B2175: San Diego | C2175: San Diego | D2175: Otay International Center | E2175: microhood | F2175: Below $500/sf
A2176: 92154 | B2176: San Diego | C2176: San Diego | D2176: Otay Mesa | E2176: macrohood | F2176: Below $500/sf
A2177: 92154 | B2177: San Diego | C2177: San Diego | D2177: Otay Mesa West | E2177: microhood | F2177: Below $500/sf
A2178: 92154 | B2178: San Diego | C2178: San Diego | D2178: Palm City | E2178: microhood | F2178: Below $500/sf
A2179: 92154 | B2179: San Diego | C2179: San Diego | D2179: Palm Ridge | E2179: microhood | F2179: Below $500/sf
A2180: 92154 | B2180: San Diego | C2180: San Diego | D2180: Parkview | E2180: neighborhood | F2180: Below $500/sf
A2181: 92154 | B2181: San Diego | C2181: San Diego | D2181: Ream Field | E2181: neighborhood | F2181: Below $500/sf
... A2216: 92276 | B2216: Thousand Palms | C2216: Riverside | D2216: Shadow Ridge Creek | E2216: neighborhood | F2216: Below $500/sf
A2217: 92310 | B2217: Fort Irwin | C2217: San Bernardino | D2217: Bitter Springs | E2217: neighborhood
A2218: 92310 | B2218: Fort Irwin | C2218: San Bernardino | D2218: Cactus Cove | E2218: neighborhood
A2219: 92310 | B2219: Fort Irwin | C2219: San Bernardino | D2219: Calico Estates | E2219: neighborhood
A2220: 92310 | B2220: Fort Irwin | C2220: San Bernardino | D2220: Coyote Springs | E2220: neighborhood
A2221: 92310 | B2221: Fort Irwin | C2221: San Bernardino | D2221: Crackerjack Flats | E2221: neighborhood
A2222: 92310 | B2222: Fort Irwin | C2222: San Bernardino | D2222: Desert Winds | E2222: neighborhood
A2223: 92310 | B2223: Fort Irwin | C2223: San Bernardino | D2223: Dove Gulch | E2223: neighborhood
A2224: 92310 | B2224: Fort Irwin | C2224: San Bernardino | D2224: Granite Canyon | E2224: neighborhood
A2225: 92310 | B2225: Fort Irwin | C2225: San Bernardino | D2225: Mojave Village | E2225: neighborhood
A2226: 92310 | B2226: Fort Irwin | C2226: San Bernardino | D2226: Sage Brush | E2226: neighborhood
A2227: 92310 | B2227: Fort Irwin | C2227: San Bernardino | D2227: Sandy Basin | E2227: neighborhood
A2228: 92310 | B2228: Fort Irwin | C2228: San Bernardino | D2228: Sleepy Hollow | E2228: neighborhood
A2229: 92310 | B2229: Fort Irwin | C2229: San Bernardino | D2229: Tiefort View | E2229: neighborhood
A2230: 92311 | B2230: Barstow | C2230: San Bernardino | D2230: Desert View Housing Area | E2230: neighborhood | F2230: Below $500/sf
A2231: 92311 | B2231: Barstow | C2231: San Bernardino | D2231: Nebo Center | E2231: microhood | F2231: Below $500/sf
A2232: 92311 | B2232: Barstow | C2232: San Bernardino | D2232: North Barstow | E2232: macrohood | F2232: Below $500/sf
A2233: 92316 | B2233: Bloomington | C2233: San Bernardino | D2233: Crestmore | E2233: neighborhood | F2233: Below $500/sf
...

Sheet Valpak
A1: ZIP | B1: City | C1: Neighborhood | D1: Qualifying household estimate | E1: Tier | F1: Rank | G1: SFR homes sold (12 mo) | H1: Median $/sq ft (12 mo) | I1: Estimate basis
A2: 92677 | B2: Laguna Niguel | C2: El Niguel Heights; Niguel Summit | D2: no data | E2: Tier 1 (>= $700/sf) | F2: 1 | G2: 424 | H2: 811.06558 | I2: Parcel data unavailable for this county; count pending (see Source Inventory)
A3: 94550 | B3: Livermore | C3: Sandhurst; The Grove; Village II | D3: no data | E3: Tier 1 (>= $700/sf) | F3: 2 | G3: 412 | H3: 704.67241 | I3: Parcel data unavailable for this county; count pending (see Source Inventory)
A4: 95125 | B4: San Jose | C4: Dry Creek; Willow Glen | D4: no data | E4: Tier 1 (>= $700/sf) | F4: 3 | G4: 381 | H4: 1137.9459 | I4: Parcel data unavailable for this county; count pending (see Source Inventory)
A5: 92024 | B5: Encinitas | C5: Leucadia; Olivenhain; Downtown Encinitas | D5: no data | E5: Tier 1 (>= $700/sf) | F5: 4 | G5: 369 | H5: 964.56064 | I5: Parcel data unavailable for this county; count pending (see Source Inventory)
A6: 95124 | B6: San Jose | C6: Willow Glen Place | D6: no data | E6: Tier 1 (>= $700/sf) | F6: 5 | G6: 368 | H6: 1220.4989 | I6: Parcel data unavailable for this county; count pending (see Source Inventory)
A7: 96161 | B7: Truckee | C7: Glenshire-Devonshire; Tahoe Donner; Armstrong | D7: no data | E7: Tier 2 ($600-699/sf) | F7: 6 | G7: 533 | H7: 612.99992 | I7: Parcel data unavailable for this county; count pending (see Source Inventory)
A8: 92117 | B8: San Diego | C8: Bay Ho; Clairemont; Clairemont Mesa Gateway | D8: no data | E8: Tier 1 (>= $700/sf) | F8: 7 | G8: 349 | H8: 805.70845 | I8: Parcel data unavailable for this county; count pending (see Source Inventory)
A9: 94112 | B9: San Francisco | C9: Ocean View; Outer Mission; St. Mary's Park | D9: no data | E9: Tier 1 (>= $700/sf) | F9: 8 | G9: 335 | H9: 856.09109 | I9: Parcel data unavailable for this county; count pending (see Source Inventory)
A10: 92646 | B10: Huntington Beach | D10: no data | E10: Tier 1 (>= $700/sf) | F10: 9 | G10: 333 | H10: 825.07272 | I10: Parcel data unavailable for this county; count pending (see Source Inventory)
A11: 94010 | B11: Burlingame | C11: Burlingame Hills; Burlingame Village; Burlingame Town Square | D11: no data | E11: Tier 1 (>= $700/sf) | F11: 10 | G11: 328 | H11: 1516.4872 | I11: Parcel data unavailable for this county; count pending (see Source Inventory)
A12: 95123 | B12: San Jose | C12: Parkview | D12: no data | E12: Tier 1 (>= $700/sf) | F12: 11 | G12: 326 | H12: 911.12898 | I12: Parcel data unavailable for this county; count pending (see Source Inventory)
A13: 94025 | B13: Menlo Park | C13: Stanford Hills; Stanford Weekend Acres; Hacker Square | D13: no data | E13: Tier 1 (>= $700/sf) | F13: 12 | G13: 321 | H13: 1691.4166 | I13: Parcel data unavailable for this county; count pending (see Source Inventory)
A14: 90066 | B14: Los Angeles | C14: Mar Vista; Culver Garden; Westdale | D14: no data | E14: Tier 1 (>= $700/sf) | F14: 13 | G14: 315 | H14: 1163.8054 | I14: Parcel data unavailable for this county; count pending (see Source Inventory)
A15: 94566 | B15: Pleasanton | C15: Del Prado; Irby Ranch; Ruby Hill | D15: no data | E15: Tier 1 (>= $700/sf) | F15: 14 | G15: 305 | H15: 817.19279 | I15: Parcel data unavailable for this county; count pending (see Source Inventory)
A16: 90275 | B16: Rancho Palos Verdes | D16: no data | E16: Tier 1 (>= $700/sf) | F16: 15 | G16: 302 | H16: 789.09299 | I16: Parcel data unavailable for this county; count pending (see Source Inventory)
A17: 94568 | B17: Dublin | D17: no data | E17: Tier 1 (>= $700/sf) | F17: 16 | G17: 297 | H17: 730.13592 | I17: Parcel data unavailable for this county; count pending (see Source Inventory)
A18: 94536 | B18: Fremont | C18: Centerville District; Niles District; Niles Junction | D18: no data | E18: Tier 1 (>= $700/sf) | F18: 17 | G18: 294 | H18: 1002.4841 | I18: Parcel data unavailable for this county; count pending (see Source Inventory)
A19: 90808 | B19: Long Beach | D19: no data | E19: Tier 1 (>= $700/sf) | F19: 18 | G19: 290 | H19: 716.19567 | I19: Parcel data unavailable for this county; count pending (see Source Inventory)
A20: 92037 | B20: La Jolla | C20: La Jolla; Biology Field Station; Campus Services Complex | D20: no data | E20: Tier 1 (>= $700/sf) | F20: 19 | G20: 284 | H20: 1361.8037 | I20: Parcel data unavailable for this county; count pending (see Source Inventory)
A21: 95120 | B21: San Jose | C21: Almaden Valley | D21: no data | E21: Tier 1 (>= $700/sf) | F21: 20 | G21: 282 | H21: 1003.0732 | I21: Parcel data unavailable for this county; count pending (see Source Inventory)
A22: 92009 | B22: Carlsbad | C22: La Costa; Bressi Ranch; La Costa Greens | D22: no data | E22: Tier 1 (>= $700/sf) | F22: 21 | G22: 281 | H22: 705.44022 | I22: Parcel data unavailable for this county; count pending (see Source Inventory)
A23: 94941 | B23: Mill Valley | C23: Almonte | D23: no data | E23: Tier 1 (>= $700/sf) | F23: 22 | G23: 279 | H23: 1083.9878 | I23: Parcel data unavailable for this county; count pending (see Source Inventory)
A24: 92129 | B24: San Diego | C24: Rancho Peñasquitos; Torrey Highlands; Greystone Torrey Highlands | D24: no data | E24: Tier 1 (>= $700/sf) | F24: 23 | G24: 277 | H24: 704.04314 | I24: Parcel data unavailable for this county; count pending (see Source Inventory)
A25: 90815 | B25: Long Beach | C25: Los Altos | D25: no data | E25: Tier 1 (>= $700/sf) | F25: 24 | G25: 275 | H25: 736.42722 | I25: Parcel data unavailable for this county; count pending (see Source Inventory)
A26: 90049 | B26: Los Angeles | C26: Brentwood; Brentwood Glen; Brentwood Heights | D26: no data | E26: Tier 1 (>= $700/sf) | F26: 25 | G26: 273 | H26: 1323.402 | I26: Parcel data unavailable for this county; count pending (see Source Inventory)
A27: 94549 | B27: Lafayette | C27: Burton Valley; Reliez Valley | D27: no data | E27: Tier 1 (>= $700/sf) | F27: 26 | G27: 268 | H27: 827.75787 | I27: Parcel data unavailable for this county; count pending (see Source Inventory)
A28: 92651 | B28: Laguna Beach | C28: Emerald Bay | D28: no data | E28: Tier 1 (>= $700/sf) | F28: 27 | G28: 265 | H28: 1545.4744 | I28: Parcel data unavailable for this county; count pending (see Source Inventory)
A29: 94070 | B29: San Carlos | C29: Devonshire | D29: no data | E29: Tier 1 (>= $700/sf) | F29: 28 | G29: 265 | H29: 1389.7012 | I29: Parcel data unavailable for this county; count pending (see Source Inventory)
A30: 95127 | B30: San Jose | C30: Alum Rock | D30: no data | E30: Tier 1 (>= $700/sf) | F30: 29 | G30: 265 | H30: 795.73846 | I30: Parcel data unavailable for this county; count pending (see Source Inventory)
A31: 94087 | B31: Sunnyvale | C31: Birdland | D31: no data | E31: Tier 1 (>= $700/sf) | F31: 30 | G31: 264 | H31: 1663.5655 | I31: Parcel data unavailable for this county; count pending (see Source Inventory)
... A37: 94611 | B37: Oakland | C37: Broadway Auto Row; Harrison/Oakland; Montclair | D37: no data | E37: Tier 2 ($600-699/sf) | F37: 36 | G37: 386 | H37: 686.28151 | I37: Parcel data unavailable for this county; count pending (see Source Inventory)
A38: 94560 | B38: Newark | D38: no data | E38: Tier 1 (>= $700/sf) | F38: 37 | G38: 255 | H38: 837.30364 | I38: Parcel data unavailable for this county; count pending (see Source Inventory)
A39: 92660 | B39: Newport Beach | C39: UCI - North Campus; Bayside Village; Belcourt | D39: no data | E39: Tier 1 (>= $700/sf) | F39: 38 | G39: 254 | H39: 1380.84 | I39: Parcel data unavailable for this county; count pending (see Source Inventory)
A40: 92127 | B40: San Diego | C40: Black Mountain Ranch; 4S Commons; Auberge | D40: no data | E40: Tier 1 (>= $700/sf) | F40: 39 | G40: 252 | H40: 713.32127 | I40: Parcel data unavailable for this county; count pending (see Source Inventory)
A41: 92064 | B41: Poway | C41: Bridlewood; Bridlewood Country Estates; Bridlewood Lakeside | D41: no data | E41: Tier 2 ($600-699/sf) | F41: 40 | G41: 375 | H41: 641.68389 | I41: Parcel data unavailable for this county; count pending (see Source Inventory)
A42: 92679 | B42: Rancho Santa Margarita | C42: Dove Canyon; Portola Hills; Robinson Ranch | D42: no data | E42: Tier 2 ($600-699/sf) | F42: 41 | G42: 375 | H42: 631.13114 | I42: Parcel data unavailable for this county; count pending (see Source Inventory)
A43: 90068 | B43: Los Angeles | C43: Beachwood Canyon; Hollywood Dell; Whitley Heights Historic District | D43: no data | E43: Tier 1 (>= $700/sf) | F43: 42 | G43: 248 | H43: 870.9198 | I43: Parcel data unavailable for this county; count pending (see Source Inventory)
A44: 95037 | B44: Morgan Hill | D44: no data | E44: Tier 2 ($600-699/sf) | F44: 43 | G44: 372 | H44: 660.69466 | I44: Parcel data unavailable for this county; count pending (see Source Inventory)
A45: 90210 | B45: Beverly Hills | C45: The Flats; Trousdale Estates; Beverly Crest | D45: no data | E45: Tier 1 (>= $700/sf) | F45: 44 | G45: 247 | H45: 1275.3541 | I45: Parcel data unavailable for this county; count pending (see Source Inventory)
A46: 92626 | B46: Costa Mesa | C46: College Park; Mesa Verde | D46: no data | E46: Tier 1 (>= $700/sf) | F46: 45 | G46: 247 | H46: 888.08112 | I46: Parcel data unavailable for this county; count pending (see Source Inventory)
A47: 94587 | B47: Union City | C47: Alvarado; Decoto; Contempo | D47: no data | E47: Tier 1 (>= $700/sf) | F47: 46 | G47: 247 | H47: 814.84483 | I47: Parcel data unavailable for this county; count pending (see Source Inventory)
A48: 90274 | B48: Palos Verdes Peninsula | C48: Palos Verdes Estates; Rolling Hills; Rolling Hills Estates | D48: no data | E48: Tier 1 (>= $700/sf) | F48: 47 | G48: 246 | H48: 975.8403 | I48: Parcel data unavailable for this county; count pending (see Source Inventory)
A49: 94526 | B49: Danville | C49: Anderson Ranch; Brookview; California Chateau | D49: no data | E49: Tier 1 (>= $700/sf) | F49: 48 | G49: 246 | H49: 818.4109 | I49: Parcel data unavailable for this county; count pending (see Source Inventory)
A50: 95051 | B50: Santa Clara | D50: no data | E50: Tier 1 (>= $700/sf) | F50: 49 | G50: 246 | H50: 1419.1115 | I50: Parcel data unavailable for this county; count pending (see Source Inventory)
A51: 94062 | B51: Redwood City | C51: Emerald Lake Hills; Kensington Square | D51: no data | E51: Tier 1 (>= $700/sf) | F51: 50 | G51: 245 | H51: 1306.3344 | I51: Parcel data unavailable for this county; count pending (see Source Inventory)
A52: 92115 | B52: San Diego | C52: Mid-City; Montezuma Mesa; Alvarado Estates | D52: no data | E52: Tier 1 (>= $700/sf) | F52: 51 | G52: 244 | H52: 717.53638 | I52: Parcel data unavailable for this county; count pending (see Source Inventory)
A53: 94044 | B53: Pacifica | C53: Castle Hill; Edgemar; Fairway Park | D53: no data | E53: Tier 1 (>= $700/sf) | F53: 52 | G53: 244 | H53: 867.36228 | I53: Parcel data unavailable for this county; count pending (see Source Inventory)
A54: 94539 | B54: Fremont | C54: Mission San Jose District; Warm Springs District | D54: no data | E54: Tier 1 (>= $700/sf) | F54: 53 | G54: 240 | H54: 1193.9697 | I54: Parcel data unavailable for this county; count pending (see Source Inventory)
A55: 92675 | B55: San Juan Capistrano | C55: Rienda; Rancho Mission Viejo | D55: no data | E55: Tier 1 (>= $700/sf) | F55: 54 | G55: 239 | H55: 725.47033 | I55: Parcel data unavailable for this county; count pending (see Source Inventory)
A56: 90046 | B56: Los Angeles | C56: Hollywood Hills West | D56: no data | E56: Tier 1 (>= $700/sf) | F56: 55 | G56: 238 | H56: 963.51314 | I56: Parcel data unavailable for this county; count pending (see Source Inventory)
A57: 92672 | B57: San Clemente | C57: Bay Cliff Village; Colony Cove; Sea Summit | D57: no data | E57: Tier 1 (>= $700/sf) | F57: 56 | G57: 238 | H57: 999.24195 | I57: Parcel data unavailable for this county; count pending (see Source Inventory)
A58: 94901 | B58: San Rafael | C58: Canal; Chicken Point; Dominican | D58: no data | E58: Tier 1 (>= $700/sf) | F58: 57 | G58: 238 | H58: 757.76377 | I58: Parcel data unavailable for this county; count pending (see Source Inventory)
A59: 95476 | B59: Sonoma | D59: no data | E59: Tier 2 ($600-699/sf) | F59: 58 | G59: 356 | H59: 644.47498 | I59: Parcel data unavailable for this county; count pending (see Source Inventory)
A60: 90045 | B60: Los Angeles | C60: Westchester; Westchester Triangle | D60: no data | E60: Tier 1 (>= $700/sf) | F60: 59 | G60: 237 | H60: 952.25122 | I60: Parcel data unavailable for this county; count pending (see Source Inventory)
A61: 94105 | B61: San Francisco | C61: Rincon Hill; 50 Beale Street Plaza; 560 Mission Street Plaza | D61: no data | E61: Tier 1 (>= $700/sf) | F61: 60 | G61: 237 | H61: 1097.7808 | I61: Parcel data unavailable for this county; count pending (see Source Inventory)
A62: 95003 | B62: Aptos | D62: no data | E62: Tier 1 (>= $700/sf) | F62: 61 | G62: 237 | H62: 815.35008 | I62: Parcel data unavailable for this county; count pending (see Source Inventory)
A63: 94015 | B63: Daly City | C63: Serramonte; Westlake | D63: no data | E63: Tier 1 (>= $700/sf) | F63: 62 | G63: 236 | H63: 856.38105 | I63: Parcel data unavailable for this county; count pending (see Source Inventory)
A64: 94583 | B64: San Ramon | C64: Alexander Square | D64: no data | E64: Tier 1 (>= $700/sf) | F64: 63 | G64: 236 | H64: 749.0144 | I64: Parcel data unavailable for this county; count pending (see Source Inventory)
A65: 94563 | B65: Orinda | C65: Glorietta; Wilder; Orinda Theatre Square | D65: no data | E65: Tier 1 (>= $700/sf) | F65: 64 | G65: 234 | H65: 768.83347 | I65: Parcel data unavailable for this county; count pending (see Source Inventory)
A66: 92648 | B66: Huntington Beach | D66: no data | E66: Tier 1 (>= $700/sf) | F66: 65 | G66: 233 | H66: 846.0964 | I66: Parcel data unavailable for this county; count pending (see Source Inventory)
A67: 94116 | B67: San Francisco | C67: Parkside; Forest Hill; Golden Gate Heights | D67: no data | E67: Tier 1 (>= $700/sf) | F67: 66 | G67: 233 | H67: 1093.2446 | I67: Parcel data unavailable for this county; count pending (see Source Inventory)
A68: 90065 | B68: Los Angeles | C68: Dayton Avenue; Glassell Park; Mount Washington | D68: no data | E68: Tier 1 (>= $700/sf) | F68: 67 | G68: 232 | H68: 806.80722 | I68: Parcel data unavailable for this county; count pending (see Source Inventory)
A69: 92886 | B69: Yorba Linda | C69: Country Club; Fairlynn | D69: no data | E69: Tier 2 ($600-699/sf) | F69: 68 | G69: 348 | H69: 659.11359 | I69: Parcel data unavailable for this county; count pending (see Source Inventory)
A70: 92691 | B70: Mission Viejo | D70: no data | E70: Tier 2 ($600-699/sf) | F70: 69 | G70: 344 | H70: 672.26668 | I70: Parcel data unavailable for this county; count pending (see Source Inventory)
A71: 92705 | B71: Santa Ana | C71: Cowan Heights; Fairbridge Square; Lemon Heights | D71: no data | E71: Tier 1 (>= $700/sf) | F71: 70 | G71: 229 | H71: 703.34542 | I71: Parcel data unavailable for this county; count pending (see Source Inventory)
A72: 92694 | B72: Ladera Ranch | C72: Los Patrones | D72: no data | E72: Tier 2 ($600-699/sf) | F72: 71 | G72: 341 | H72: 656.34391 | I72: Parcel data unavailable for this county; count pending (see Source Inventory)
A73: 92647 | B73: Huntington Beach | D73: no data | E73: Tier 1 (>= $700/sf) | F73: 72 | G73: 227 | H73: 811.46192 | I73: Parcel data unavailable for this county; count pending (see Source Inventory)
